Workbook

Sheet SKILL
A2: Aura, Spell, AoE, Fire Level: (1-20) Reservation: 50% Mana Cooldown Time: 1.20 sec Can Store 1 Use(s) Cast Time: Instant Requires Level 24 Casts an aura that adds fire damage to the attacks and spells of you and your allies. +(0-1.9) metres to radius You and nearby allies deal (16-109) to (23-155) additional Fire Damage with Attacks You and nearby allies deal (16-109) to (23-155) additional Fire Damage with Spells | B2: Earthquake Attack, AoE, Melee, Duration, Slam Level: (1-20) Cost: (10-13) Mana Attack Speed: 75% of base Attack Damage: (143-229)% of base Effectiveness of Added Damage: (143-229)% AoE Radius: 18 / 28 Requires Level 28 Smashes the ground, dealing damage in an area and cracking the earth. The crack will erupt in a powerful aftershock after a duration. Cracks created before the first one has erupted will not generate their own aftershocks. Requires an Axe, Mace, Sceptre, Staff or Unarmed. Base duration is 1.00 second Aftershock deals 150% more Damage with Hits and Ailments | C2: Exsanguinate Spell, Chaining, Physical, Duration Level: (1-20) Cost: (16-46) Life Cast Time: 0.80 sec Critical Strike Chance: 6.00% Effectiveness of Added Damage: (150-270)% Requires Level 12 Releases several tendrils of blood from your character, targeting enemies in a narrow angle in front of you. The beams deal physical damage and inflict a physical damage over time debuff to enemies, which can stack up to 3 times. Effects which allow skills to chain can apply to these tendrils. Deals (17-1193) to (25-1789) Physical Damage Deals (26.9-1534.2) Base Physical Damage per second Base duration is 1.00 second Modifiers to Spell Damage apply to this Skill's Damage Over Time effect Fires tendrils at up to (7-9) Targets | D2: Ground Slam Attack, AoE, Melee, Slam Level: (1-20) Cost: (6-11) Mana Attack Speed: 90% of base Attack Damage: (132-356)% of base Effectiveness of Added Damage: (132-356)% AoE Radius: 35 Slams the ground in front of you, creating a wave that travels forward and damages enemies with an increased chance to stun. The wave deals more damage to closer enemies. Requires an Axe, Mace, Sceptre, Staff or Unarmed. 25% reduced Enemy Stun Threshold +(0-1) metre to radius Deals up to (40-49)% more Damage with Hits to closer targets | E2: Herald of Ash Spell, AoE, Fire, Herald, Duration Level: (1-20) Reservation: 25% Mana Cooldown Time: 1.00 sec Can Store 1 Use(s) Cast Time: Instant AoE Radius: 10 Requires Level 16 Grants a buff providing fire damage based on your physical damage. While you have this buff, if you kill an enemy, other enemies near them will be burned based on the overkill damage. The burn inflicted by this skill can only be affected by modifiers to damage over time (burning damage is damage over time). Base duration is 4.00 seconds Base Burning Damage is 25% of Overkill Damage (0-38)% more Burning Damage Buff grants (15-20)% of your Physical Damage as Extra Fire Damage | F2: Molten Strike Attack, Projectile, AoE, Melee, Strike, Fire Level: (1-20) Cost: (6-10) Mana Attack Damage: (126-329)% of base Effectiveness of Added Damage: (126-329)% Projectile Speed: 750 Infuses your melee weapon with molten energies to attack with physical and fire damage. This attack causes balls of molten magma to launch forth from the enemies you hit, divided amongst all enemies hit by the strike. These will deal area attack damage to enemies where they land. Fires 4 Projectiles 60% of Physical Damage Converted to Fire Damage Projectiles deal 60% less Damage with Hits and Ailments | G2: Pride Spell, AoE, Aura, Physical Level: (1-20) Reservation: 50% Mana Cooldown Time: 1.20 sec Can Store 1 Use(s) Cast Time: Instant Requires Level 24 Casts an aura that causes nearby enemies to take more physical damage. +(0-1) metre to radius Nearby Enemies take at least (15-19)% more Physical Damage, raising up to (30-39)% as they stay in the Aura for 4 seconds | H2: Reap Spell, Physical, AoE, Duration Level: (1-20) Cost: (25-46) Life Cast Time: 0.80 sec Critical Strike Chance: 6.00% Effectiveness of Added Damage: (150-210)% Requires Level 28 A bloody scythe swipes across a selected area, applying a physical damage over time debuff and hitting enemies with physical damage. If any survive, you gain a blood charge which raises the damage and cost of the skill. Players can have 5 maximum blood charges. Deals (57-943) to (86-1414) Physical Damage Deals (138.2-2002.5) Base Physical Damage per second Base duration is 1.00 second Modifiers to Spell Damage apply to this Skill's Damage Over Time effect Gain a Blood Charge if this Skill Hits Enemies and none of them Die Lose a Blood Charge when an Enemy Dies while affected by this Skill's Debuff Costs 20% more Life per Blood Charge Deals 15% more Damage per Blood Charge | I2: Smite Lightning, Melee, Attack, AoE, Duration, Strike, Aura Level: (1-20) Cost: (7-12) Mana Attack Speed: 85% of base Attack Damage: (225-488)% of base Effectiveness of Added Damage: (225-488)% Performs a melee attack, and causes lightning to strike a nearby enemy, dealing damage in an area. Each target can only be hit once by this skill. Hitting an enemy grants an aura for a duration. Requires a Sword, Axe, Mace, Sceptre, Staff or Unarmed. 50% of Physical Damage Converted to Lightning Damage Base duration is 4.00 seconds (30-20)% less Area Damage Base radius is (1.5-2.1) metres Base Aura radius is (3.6-4.2) metres Lightning strikes 1 target within 5 metres Aura grants (1-12) to (4-220) added Lightning Damage Aura grants (10-19)% chance to Shock | J2: Summon Stone Golem Minion, Spell, Golem, Physical Level: (1-20) Cost: (30-54) Mana Cooldown Time: 6.00 sec Can Store 1 Use(s) Cast Time: 1.00 sec Requires Level 34 Summons a Stone Golem that grants you life regeneration and defences. In addition to its melee attack, the Stone Golem uses a rolling charge and a powerful slam that can taunt enemies. Maximum 1 Summoned Golem Golems grant (33-105) Life Regenerated per second Golems grant 20% increased Defences | K2: Swordstorm Attack, Melee, AoE, Retaliation Level: (1-20) Cost: (7-10) Mana Cooldown Time: 3.00 sec Can Store 1 Use(s) Attack Damage: (123-247)% of base Effectiveness of Added Damage: (123-247)% Requires Level 16 Retaliate against a blocked hit with a hail of blades that rains down in front of you, repeatedly dealing the damage of both your weapons combined. Requires Dual Wielding Melee Weapons. Cannot be used by default Becomes Usable once for 2 seconds when you Block a Hit Can't be Evaded Base radius is (1.8-2.3) metres Damages Enemies 8 times | L2: Volcanic Fissure Melee, Attack, Projectile, AoE, Slam, Fire Level: (1-20) Cost: (8-13) Mana Attack Speed: 80% of base Attack Damage: (177-344)% of base Effectiveness of Added Damage: (177-344)% Requires Level 12 Slam the ground, creating a winding fissure that deals area damage while travelling outwards. When it reaches the target location it erupts, releasing a burst of molten projectiles. Requires an Axe, Mace, Sceptre, Staff or Unarmed. Fires 5 Projectiles 60% of Physical Damage Converted to Fire Damage Projectiles deal 50% less Damage with Hits and Ailments
A4: Animate Weapon Duration, Minion, Spell, Physical Level: (1-20) Cost: (4-16) Mana Cast Time: 0.60 sec Requires Level 4 Animates a Melee Weapon Item or Lingering Blade to fight by your side. You cannot animate unidentified Weapons. Will not animate weapons with 6 sockets. Cannot be used by Traps or Mines. Base duration is 40.00 seconds Maximum (5-14) Animated Weapons Can use Items requiring up to Level (9-100) Minions' Attacks deal (5-126) to (8-184) additional Physical Damage Animated Lingering Blades deal (1-17) to (2-80) Added Attack Physical Damage Minions deal (0-38)% more Damage Minions have (0-38)% more Attack Speed | B4: Barrage Attack, Projectile, Bow Level: (1-20) Cost: (5-9) Mana Attack Speed: 115% of base Attack Damage: (47-54)% of base Effectiveness of Added Damage: (47-55)% Requires Level 12 After a short preparation time, you fire individual projectiles repeatedly with a Bow or Wand. These projectiles have a small randomised spread. This skill cannot be Triggered. Fires 5 Projectiles Fires Projectiles sequentially | C4: Blade Vortex Spell, AoE, Duration, Physical Level: (1-20) Cost: (6-16) Mana Cast Time: 0.50 sec Critical Strike Chance: 6.00% Effectiveness of Added Damage: 30% Requires Level 12 This spell creates ethereal blades which orbit in an area around you, dealing damage every 0.6 seconds to all enemies in their radius. As more blades are added, the damage becomes greater and more frequent. Deals (3-140) to (5-211) Physical Damage Base duration is 4.00 seconds +(0-0.2) metres to radius 35% increased Hit Rate for each blade 35% more Damage for each blade Can have up to 10 active spinning blades | D4: Blast Rain Fire, Attack, AoE, Projectile, Bow Level: (1-20) Cost: (7-10) Mana Attack Damage: (30-35)% of base Effectiveness of Added Damage: (30-36)% Requires Level 28 Fires arrows up in the air, to rain down in an area. Each arrow deals area damage around where it lands, and they will all overlap on the targeted location. Fires 6 Arrows 100% of Physical Damage Converted to Fire Damage Penetrates (20-30)% Fire Resistance | E4: Burning Arrow Attack, Projectile, Fire, Bow Level: (1-20) Cost: (8-14) Mana Attack Speed: 70% of base Attack Damage: (280-420)% of base Effectiveness of Added Damage: (280-420)% Projectile Speed: 3260 Fires a burning arrow that deals fire damage and has a chance to ignite. 25% chance to Ignite enemies 100% of Physical Damage Converted to Fire Damage | F4: Cobra Lash Attack, Projectile, Chaos Level: (1-20) Cost: (5-8) Mana Attack Speed: 120% of base Attack Damage: (125-205)% of base Effectiveness of Added Damage: (125-205)% Fires a poisonous projectile based on your weapon that will chain between enemies. Requires a Dagger or Claw. 8% more Damage with Hits and Ailments for each remaining Chain Chains +(3-5) Times 60% of Physical Damage Converted to Chaos Damage 40% chance to Poison on Hit | G4: Cyclone Attack, AoE, Melee, Movement, Channelling Level: (1-20) Cost: (2-3) Mana Attack Speed: 300% of base Attack Damage: (81-150)% of base Effectiveness of Added Damage: (81-150)% AoE Radius: 1.6 Requires Level 28 Channel this skill to move towards a targeted location while spinning constantly attacking enemies in an area around you. While channelling this skill, you cannot be knocked back. 15% increased Area of Effect per 0.1 metre additional Melee Strike Range (30-20)% less Movement Speed | H4: Detonate Dead Spell, AoE, Fire Level: (1-20) Cost: (5-20) Mana Cast Time: 0.60 sec Critical Strike Chance: 6.00% Effectiveness of Added Damage: 160% AoE Radius: 22 Requires Level 4 Targets a corpse, and deals spell damage to enemies around the corpse, as well as causing the corpse to explode, dealing fire damage. The explosion is not affected by modifiers to spell damage and cannot be reflected. Deals (15-798) to (22-1197) Fire Damage Explosion deals base Fire Damage equal to (6-7.9)% of the corpse's Maximum Life Base radius is (2.2-2.6) metres | I4: Explosive Arrow Attack, Projectile, AoE, Duration, Fire, Bow Level: (1-20) Cost: (7-10) Mana Projectile Speed: 3260 AoE Radius: 15 Requires Level 28 Fires an arrow which will stick into an enemy or wall, and then explode, dealing area damage around it, either after a duration or when the maximum number of arrows stuck to that target is reached. If an enemy has multiple Explosive Arrows stuck in them, the first one to explode will consume the others, adding their damage to its explosion. Base duration is 1.00 second Explosion deals 50% less Base Damage Explosion will have (47-522) to (71-783) added Fire Damage +0.2 metres to Explosion Radius per Explosive Arrow on Target, up to a maximum of +1.2 metres Explosion deals 6% more Damage with Hits per Explosive Arrow on Target Explosion deals 3% more Damage with Ailments per Explosive Arrow on Target Maximum 20 Explosive Arrows stuck in an Enemy | J4: Explosive Concoction Attack, AoE, Fire, Cold, Lightning, Projectile Level: (1-20) Cost: (6-9) Mana Attack Speed: 115% of base Requires Level 28 Throws a bottle that explodes to deal unarmed attack damage in an area. Can consume charges from your Ruby, Sapphire, and Topaz flasks to add further damage. Requires an empty main hand, and no off-hand weapon. (65-806) to (98-1210) Added Fire Damage +6% to Critical Strike Chance Base radius is 1.8 metres Can consume Charges from Ruby, Sapphire, and Topaz Flasks Consumes 1 Charge per Projectile Fired from 1 Flask of each valid type, if possible Deals (57-706) to (86-1058) Added Cold Damage if Charges were consumed from a Sapphire Flask Deals (12-151) to (143-1764) Added Lightning Damage if Charges were consumed from a Topaz Flask +(120-196)% to Damage over Time Multiplier with Ignite if Charges were consumed from a Ruby Flask | K4: Flicker Strike Attack, Melee, Strike, Movement, Duration Level: (1-20) Cost: (5-8) Mana Cooldown Time: 2.00 sec Can Store 1 Use(s) Attack Speed: 120% of base Attack Damage: (177-408)% of base Effectiveness of Added Damage: (177-408)% Requires Level 10 Teleports the character to a nearby monster and attacks with a melee weapon. If no specific monster is targeted, one is picked at random. Grants a buff that increases movement speed for a duration. The cooldown can be bypassed by expending a Frenzy Charge. Base duration is 3.00 seconds 10% increased Attack Speed per Frenzy Charge 15% chance to gain a Frenzy Charge on Hit Buff grants 20% increased Movement Speed | L4: Frost Blades Attack, Projectile, Melee, Strike, Cold Level: (1-20) Cost: (6-10) Mana Attack Damage: (143-409)% of base Effectiveness of Added Damage: (143-409)% Projectile Speed: 2250 Attack enemies with increased range, releasing icy blades from the first enemy hit which fly at other enemies. Requires a Melee Weapon. Fires (5-8) Projectiles 60% of Physical Damage Converted to Cold Damage +(1.8-2.1) metres to Melee Strike Range Projectiles deal 30% less Damage with Hits and Ailments | M4: Galvanic Arrow Lightning, Attack, Projectile, AoE, Bow Level: (1-20) Cost: (6-10) Mana Attack Damage: (92-113)% of base Effectiveness of Added Damage: (92-113)% Fire a trio of electrical arrows that quickly dissipate, vanishing shortly after being loosed. The arrows are fired with such force that they create a burst of lightning, damaging enemies in a cone in front of you. 50% of Physical Damage Converted to Lightning Damage Fires 3 Arrows +(0-0.5) metres to radius Increases and Reductions to Projectile Speed also apply to this Skill's Area of Effect | N4: Haste Aura, Spell, AoE Level: (1-20) Reservation: 50% Mana Cooldown Time: 1.20 sec Can Store 1 Use(s) Cast Time: Instant AoE Radius: 36 Requires Level 24 Casts an aura that increases the movement speed, attack speed and cast speed of you and your allies. +(0-1.9) metres to radius You and nearby allies gain (10-16)% increased Movement Speed You and nearby allies gain (15-24)% increased Attack Speed You and nearby allies gain (15-24)% increased Cast Speed | O4: Hatred Aura, Spell, AoE, Cold Level: (1-20) Reservation: 50% Mana Cooldown Time: 1.20 sec Can Store 1 Use(s) Cast Time: Instant AoE Radius: 36 Requires Level 24 Casts an aura that grants extra cold damage based on physical damage to you and your allies. +(0-1.9) metres to radius You and nearby allies gain (30-39)% of Physical Damage as Extra Cold Damage | P4: Herald of Agony Spell, Herald, Minion, Chaos, Physical Level: (1-20) Reservation: 25% Mana Cooldown Time: 1.00 sec Can Store 1 Use(s) Cast Time: Instant Requires Level 16 Grants a buff giving more poison damage and a chance to inflict poison. When you poison an enemy while you have this buff, you gain Virulence, and summon an Agony Crawler minion that uses projectile and area attacks. You will lose Virulence over time, at a rate which increases the more Virulence you have. The minion will die when you have no Virulence. Maximum 1 Summoned Agony Crawler Buff grants 20% chance to Poison on Hit Grants Virulence when you Poison an Enemy Buff grants 10% more Damage with Poison 40 Maximum Virulence Minions cannot Taunt Enemies Agony Crawler has (2-4)% increased Attack Speed per Virulence you have Agony Crawler deals (5-9)% increased Physical Damage per Virulence you have Agony Crawler has (1-45) to (3-84) Added Physical Damage per Virulence you have | Q4: Herald of Ice Spell, AoE, Cold, Herald Level: (1-20) Reservation: 25% Mana Cooldown Time: 1.00 sec Can Store 1 Use(s) Cast Time: Instant Effectiveness of Added Damage: 80% Requires Level 16 Grants a buff adding cold damage to spells and attacks. If you shatter an enemy, this skill will cause them to explode and deal AoE cold damage to enemies near them. This damage is not affected by modifiers to spell damage. Deals (18-308) to (26-462) Cold Damage Damage cannot be Reflected Base radius is 1.2 metres Buff grants (4-38) to (5-56) Added Attack Cold Damage Buff grants (4-38) to (5-56) Added Spell Cold Damag | R4: Ice Shot Attack, Projectile, AoE, Cold, Bow Level: (1-20) Cost: (6-10) Mana Attack Damage: (149-200)% of base Effectiveness of Added Damage: (149-200)% Projectile Speed: 3260 AoE Radius: 23 / 10 Fires an arrow that converts some physical damage to cold on its target and converts all physical damage to cold in a cone behind that target. 60% of Physical Damage Converted to Cold Damage Base radius is 2.4 metres Chills Enemies as though dealing (100-195)% more Damage | S4: Lacerate Attack, AoE, Melee, Physical Level: (1-20) Cost: (10-17) Mana Attack Speed: 60% of base Attack Damage: (171-393)% of base Effectiveness of Added Damage: (171-393)% AoE Radius: 38 Requires Level 12 Slashes twice, releasing waves of force that damage enemies they hit. Enemies in the middle of the slashes can be hit by both. The slashes will have a chance to inflict bleeding in Blood Stance, or have a wider angle in Sand Stance. Can be used with Axes and Swords. You are in Blood Stance by default. +(0-0.9) metres to radius (50-88)% more Damage with Bleeding while in Blood Stance 25% chance to cause Bleeding while in Blood Stance 50% increased angle while in Sand Stance | T4: Lightning Arrow Attack, AoE, Projectile, Lightning, Bow Level: (1-20) Cost: (6-10) Mana Attack Damage: (149-177)% of base Effectiveness of Added Damage: (149-177)% Projectile Speed: 3260 Requires Level 12 Fires a charged arrow which damages enemies by causing them to be struck by a bolt of lightning, which also damages a number of surrounding enemies. 50% of Physical Damage Converted to Lightning Damage Hits up to 3 additional enemies near the target Shocks Enemies as though dealing (100-290)% more Damage | U4: Lightning Strike Attack, Projectile, Melee, Strike, Lightning Level: (1-20) Cost: (6-10) Mana Attack Damage: (198-456)% of base Effectiveness of Added Damage: (198-456)% Requires Level 12 Infuses your melee weapon with electrical energies as you swing. In addition to converting some of your physical damage to lightning damage, the stored energy is released from the weapon as projectiles as you strike, flying out to hit farther-away enemies. The projectiles cannot miss if the melee attack hit a target. 50% of Physical Damage Converted to Lightning Damage Fires 3 Projectiles Projectiles deal 50% less Damage with Hits and Ailments | V4: Poisonous Concoction Attack, AoE, Chaos, Projectile Level: (1-20) Cost: (5-9) Mana Attack Speed: 115% of base Requires Level 12 Throws a bottle that explodes to deal unarmed attack damage in an area and has a chance to poison. Can consume charges from a Life flask to add further damage. Requires an empty main hand, and no off-hand weapon. (22-537) to (33-806) Added Chaos Damage 40% chance to Poison on Hit +6% to Critical Strike Chance Base radius is 1.8 metres Consumes 1 Charge per Projectile Fired from 1 Life Flask, if possible Added Chaos Damage equal to (4-16)% of Flask's Recovery Amount if Charges were consumed from a Life Flask | W4: Precision Aura, Critical, Spell, AoE Level: (1-20) Reservation: (22-186) Mana Cooldown Time: 1.20 sec Can Store 1 Use(s) Cast Time: Instant Requires Level 10 Casts an aura that grants accuracy and critical strike chance to you and your allies. +(0-1.9) metres to radius You and nearby allies gain (20-58)% increased Critical Strike Chance You and nearby allies gain +(93-701) to Accuracy Rating | X4: Rain of Arrows Attack, AoE, Projectile, Bow Level: (1-20) Cost: (6-10) Mana Attack Damage: (48-60)% of base Effectiveness of Added Damage: (48-60)% AoE Radius: 24 Requires Level 12 Fires multiple arrows into the air, to land in sequence after a delay, starting at the targeted location and spreading outwards in all directions. Each arrow deals damage in an area around it. Half of the arrows will land directly on targets if there are targets in their range. Fires (18-22) Arrows | Y4: Scourge Arrow Attack, Projectile, Channelling, Chaos, Bow Level: (1-20) Cost: (4-5) Mana Attack Speed: 190% of base Attack Damage: (48-65)% of base Effectiveness of Added Damage: (48-65)% Requires Level 28 Channel to infuse an arrow with chaos, gaining stages while it is held. Release to fire it, leaving spore pods in its wake. Each spore pod blooms, firing thorn arrows, which travel for a short time before dissipating. Modifiers that cause additional projectiles to be fired will only apply to the initial arrows, and the spore pods will be divided between those arrows. Arrows Pierce all Targets 60% of Physical Damage Converted to Chaos Damage 150% more Damage with Hits and Ailments per Stage Maximum 5 Stages Leaves 1 Spore Pod per Stage Each Spore Pod fires 9 Thorn Arrows Thorn Arrows deal (60-50)% less Damage | Z4: Tornado Shot Attack, Projectile, Bow Level: (1-20) Cost: (9-13) Mana Attack Speed: 80% of base Attack Damage: (100-120)% of base Effectiveness of Added Damage: (100-120)% Requires Level 28 Fires a piercing shot that travels until it reaches the targeted location. It will then fire projectiles out in all directions from that point, which will travel for a short time before disappearing. Fires 3 secondary Projectiles | AA4: Toxic Rain Attack, AoE, Chaos, Duration, Projectile, Bow Level: (1-20) Cost: (6-10) Mana Attack Damage: (50-72)% of base Effectiveness of Added Damage: (50-73)% Requires Level 12 Fire arrows into the air that rain down around the targeted area, dealing damage to enemies they hit and creating spore pods where they land. Each spore pod deals chaos damage over time to nearby enemies and slows their movement speed. The pods last for a duration before bursting, dealing area damage. Deals (8-238) Base Chaos Damage per second Base duration is 1.00 second Fires 5 Arrows Modifiers to Projectile Damage apply to this Skill's Damage Over Time effect 60% of Physical Damage Converted to Chaos Damage Each Spore Pod applies 5% less Movement Speed to nearby Enemies, to a maximum of 30%
A6: Arc Spell, Chaining, Lightning Level: (1-20) Cost: (8-23) Mana Cast Time: 0.70 sec Critical Strike Chance: 6.00% Effectiveness of Added Damage: 120% Requires Level 12 An arc of lightning reaches from the caster to a targeted enemy and chains to other enemies, but not immediately back. Each time the arc chains, it will also chain a secondary arc to another enemy that the main arc has not already hit, which cannot chain further. Deals (6-198) to (32-1122) Lightning Damage Chains +(4-7) Times 15% more Damage with Hits and Ailments for each remaining Chain | B6: Ball Lightning Spell, Projectile, AoE, Lightning Level: (1-20) Cost: (12-23) Mana Cast Time: 0.70 sec Critical Strike Chance: 5.00% Effectiveness of Added Damage: 60% Projectile Speed: 400 AoE Radius: 22 Requires Level 28 Fires a slow-moving projectile that damages each enemy in an area around it repeatedly with bolts of lightning. Deals (2-32) to (47-617) Lightning Damage Base radius is 1.8 metres | C6: Blight Spell, Chaos, AoE, Channelling, Duration Level: (1-20) Cost: (2-5) Mana Cast Time: 0.30 sec AoE Radius: 26 Apply a debuff to enemies in front of you which deals chaos damage over time. Enemies who aren't already debuffed by Blight are also hindered for a shorter secondary duration, slowing their movement. Continued channelling adds layers of damage to the debuff, each with their own duration. Deals (5.9-421.5) Base Chaos Damage per second Base duration is 2.00 seconds Base secondary duration is 1.00 seconds Modifiers to Spell Damage apply to this Skill's Damage Over Time effect +(0-0.6) metres to radius 80% reduced Movement Speed Debuff can have up to 20 layers of Damage | D6: Blazing Salvo Spell, AoE, Fire, Projectile Level: (1-20) Cost: (8-23) Mana Cast Time: 0.70 sec Critical Strike Chance: 6.00% Effectiveness of Added Damage: 60% Requires Level 12 Fires projectiles which fly in an arc, dealing area damage on impact with either enemies or the ground near where you target. Targeting farther away causes the projectiles to spread out and land over a wider area. Deals (7-270) to (10-405) Fire Damage Fires (5-7) Projectiles | E6: Eye of Winter Spell, Projectile, Cold Level: (1-20) Cost: (14-26) Mana Cast Time: 0.80 sec Critical Strike Chance: 6.00% Effectiveness of Added Damage: 55% Requires Level 28 Fires a single eye projectile which constantly releases shard projectiles in a spiral. The shards will damage enemies they impact, dealing cold damage. The eye cannot damage enemies. When the eye dissipates or collides with terrain, it releases a faster spiral of extra shards. Deals (16-245) to (25-367) Cold Damage Modifiers to number of Projectiles only apply to the final Spiral Fires 8 Shard Projectiles in a Spiral when Projectile ends Projectiles continuously gain Damage, up to 200% more Damage by the time they dissipate | F6: Fireball Projectile, Spell, AoE, Fire Level: (1-20) Cost: (6-25) Mana Cast Time: 0.75 sec Critical Strike Chance: 6.00% Effectiveness of Added Damage: (260-370)% Projectile Speed: 1040 AoE Radius: 9 Unleashes a ball of fire towards a target which explodes, damaging nearby foes. Deals (9-1640) to (14-2460) Fire Damage 25% chance to Ignite enemies Base radius is (0.9-1.4) metres | G6: Forbidden Rite Spell, AoE, Chaos, Projectile Level: (1-20) Cost: (8-21) Mana Cast Time: 0.75 sec Critical Strike Chance: 6.00% Effectiveness of Added Damage: 110% Requires Level 16 Lobs an exploding projectile near the targeted location, and extra projectiles toward enemies around you. The projectiles deal chaos damage based on your life and energy shield. Casting this spell damages you. Deals (15-498) to (22-747) Chaos Damage Deals 5% of your maximum Energy Shield as base Chaos Damage Deals 12% of your maximum Life as base Chaos Damage Take 40% of maximum Life and 25% of maximum Energy Shield as Chaos Damage Fires extra Projectiles at up to (6-7) surrounding Enemies | H6: Freezing Pulse Spell, Projectile, Cold Level: (1-20) Cost: (5-21) Mana Cast Time: 0.65 sec Critical Strike Chance: 6.00% Effectiveness of Added Damage: (250-330)% Projectile Speed: 1800 An icy projectile which has a chance to freeze enemies it passes through. The projectile fades quickly, reducing damage and freezing chance until it dissipates. Deals (8-1458) to (12-2188) Cold Damage Projectiles Pierce all Targets Projectiles continuously lose Damage, up to 50% less Damage by the time they dissipate Projectiles have 25% chance to Freeze, which is lost over the first quarter of their flight | I6: Herald of Thunder Spell, AoE, Duration, Lightning, Herald Level: (1-20) Reservation: 25% Mana Cooldown Time: 1.00 sec Can Store 1 Use(s) Cast Time: Instant AoE Radius: 32 Requires Level 16 Grants a buff which adds lightning damage to spells and attacks. If you kill a shocked enemy, this skill will create a storm, causing lightning bolts to strike enemies around you for a duration. The damage inflicted by this skill is not affected by modifiers to spell damage. Deals (1-23) to (31-1108) Lightning Damage Cannot inflict Shock Base duration is 6.00 seconds Storm Hits an Enemy every 0.25 Seconds Creates a storm when you Kill a Shocked Enemy Buff grants (2-19) to (7-76) Added Attack Lightning Damage Buff grants (2-19) to (7-76) Added Spell Lightning Damage | J6: Kinetic Blast Attack, Projectile, AoE Level: (1-20) Cost: (6-9) Mana Attack Speed: 115% of base Attack Damage: (140-155)% of base Effectiveness of Added Damage: (140-155)% AoE Radius: 14 Requires Level 28 Fires a projectile from a Wand that causes a series of area explosions in a secondary radius around its point of impact, each damaging enemies. Kinetic Blast creates 4 additional explosions Increases and Reductions to Spell Damage also apply to Attack Damage from this Skill at 200% of their value 35% less Area Damage Base explosion radius is 1.4 metres Base secondary radius is 2 metres | K6: Kinetic Rain Attack, AoE, Projectile, Duration, Trigger Level: (1-20) Cost: (7-10) Mana Attack Damage: (20-25)% of base Effectiveness of Added Damage: (20-25)% Requires Level 28 Swing your wand to cause a number of projectiles to rain down within a large area in front of you, directly targeting the locations of enemies in the area. The locations where each projectile will land are shown with markers before they fall. Each projectile explodes when hitting the ground, dealing area damage and triggering Kinetic Anomaly. Cannot be used by Totems, Traps, or Mines. Increases and Reductions to Spell Damage also apply to Attack Damage from this Skill at 150% of their value Fires 8 Projectiles Base targeting area length is 9 metres Base targeting area width is 4.5 metres Base explosion radius is 1.2 metres Increases and Reductions to Spell Damage also apply to Attack Damage from this Skill at 150% of their value Base duration is 6.00 seconds Base explosion radius is 1.2 metres Maximum 30 Anomalies This Skill is Triggered when Projectiles from Kinetic Rain explode | L6: Orb of Storms Lightning, Spell, AoE, Chaining, Orb Level: (1-20) Cost: (22-16) Mana Cooldown Time: 0.50 sec Can Store 1 Use(s) Cast Time: 0.50 sec Critical Strike Chance: 5.00% Effectiveness of Added Damage: (80-110)% Requires Level 4 Creates a stationary electrical orb that strikes enemies in its area of effect with beams of lightning that can then split to hit more enemies. Modifiers to cast speed will increase how frequently it does this. Casting this skill again will replace the previous orb. Deals (3-304) to (8-913) Lightning Damage Strikes every (3.50-2.55) seconds, and when you use a Lightning Skill near the Orb Strikes every 0.50 seconds while Channelling a Lightning Skill near the Orb Base radius is 2.8 metres Beams Split towards targets within a base radius of 3.5 metres Beam Splits towards 3 additional targets Orb disappears after (10-29) Strikes | M6: Raise Zombie Spell, Minion Level: (1-20) Cost: (9-28) Mana Cast Time: 0.85 sec Raises a zombie minion from a corpse, which will follow you and attack enemies with a melee strike. Maximum (3-6) Raised Zombies Minions have (0-38)% more Maximum Life | N6: Righteous Fire Spell, AoE, Fire Level: (1-20) Cooldown Time: 0.30 sec Can Store 1 Use(s) Cast Time: Instant Requires Level 16 Engulfs you in magical fire that rapidly burns you and nearby enemies. Your spell damage is substantially increased while under this effect. The effect ends when you have 1 life remaining. Deals 70% of your Maximum Life as Base Fire Damage per second Deals 70% of your Maximum Energy Shield as Base Fire Damage per second You Burn for 90% of your Maximum Life per second as Fire Damage You Burn for 70% of your Maximum Energy Shield per second as Fire Damage Grants (20-39)% more Spell Damage Base radius is (1.8-2.3) metres | O6: Summon Carrion Golem Physical, Minion, Spell, Golem Level: (1-20) Cost: (30-54) Mana Cooldown Time: 6.00 sec Can Store 1 Use(s) Cast Time: 1.00 sec Requires Level 34 Summons a Carrion Golem that grants added physical damage for your non-golem minions. The Carrion Golem attacks with a series of slashes that increase in speed and damage, as well as a cascade of bone spikes, and deals more damage for each of your non-golem minions near it. Maximum 1 Summoned Golem Golems deal 5% more Damage per Non-Golem Minion near them, up to 50% Golems grant (7-27) to (11-41) additional Physical Damage for Non-Golem Minions | P6: Vortex Spell, AoE, Cold, Duration, Nova Level: (1-20) Cost: (13-25) Mana Cast Time: 0.75 sec Critical Strike Chance: 6.00% Effectiveness of Added Damage: (130-210)% AoE Radius: 2 Requires Level 28 An icy blast explodes around the caster, dealing cold damage to enemies, and leaving behind a whirling vortex which deals cold damage over time and chills enemies caught in it. Deals (48-933) to (72-1399) Cold Damage Base duration is 3.00 seconds Deals (115.6-2772.8) Base Cold Damage per second Modifiers to Spell Damage apply to this Skill's Damage Over Time effect Base radius is 2 metres Base secondary radius is 2 metres

Sheet SUPPORT
A1: Added Fire Damage Support Fire, Physical, Support Icon: F Level: (1-20) Cost & Reservation Multiplier: 120% Requires Level 8 Supports any skill that hits enemies. Supported Skills gain (25-39)% of Physical Damage as Extra Fire Damage | B1: Brutality Support Physical, Support Icon: U Level: (1-20) Cost & Reservation Multiplier: 140% Requires Level 38 Supports any skill that deals damage. Supported Skills deal (25-39)% more Physical Damage Supported Skills deal no Chaos Damage Supported Skills deal no Elemental Damage | C1: Burning Damage Support Fire, Support Icon: b Level: (1-20) Cost & Reservation Multiplier: 130% Requires Level 31 Supports any skill that hits enemies, or can deal burning damage directly. Supported Skills deal (20-34)% more Burning Damage | D1: Chance to Bleed Support Attack, Physical, Support Icon: E Level: (1-20) Cost & Reservation Multiplier: 120% Supports attack skills. Supported Attacks have 25% chance to cause Bleeding Supported Attacks deal (10-29)% more Damage with Bleeding | E1: Cold to Fire Support Cold, Fire, Support Icon: x Level: (1-20) Cost & Reservation Multiplier: 120% Requires Level 18 Supports any skill that hits enemies. Supported Skills gain (10-29)% of Cold Damage as Extra Fire Damage Supported Skills have 50% of Cold Damage Converted to Fire Damage | F1: Cruelty Support Support, Duration Icon: Y Level: (1-20) Cost & Reservation Multiplier: 140% Requires Level 18 Supports any skill that hits enemies. Minions cannot gain Cruelty. Supported Skills deal (15-24)% more Damage with Hits Cruelty has a Base Duration of 4 seconds Hits from Supported Skills grant Cruelty (0-19)% increased Effect of Cruelty granted by Supported Skills | G1: lemental Damage with Attacks Support Attack, Support Icon: W Level: (1-20) Cost & Reservation Multiplier: 130% Requires Level 18 Supports attack skills. Supported Attack Skills deal (20-34)% more Elemental Damage | H1: Endurance Charge on Melee Stun Support Support, Melee, Attack Icon: e Level: (1-20) Cost & Reservation Multiplier: 120% Requires Level 18 Supports melee attack skills. 4% more Damage per Endurance Charge Supported Skills have (0-19)% reduced Enemy Stun Threshold Gain an Endurance Charge when you Stun an Enemy with a Melee Hit from Supported Skills | I1: Fire Penetration Support Fire, Support Icon: V Level: (1-20) Cost & Reservation Multiplier: 130% Requires Level 31 Supports any skill that hits enemies, making those hits penetrate enemy fire resistance. Supported Skills Penetrate (20-34)% Fire Resistance | J1: Less Duration Support Support, Duration Icon: d Level: (1-20) Cost & Reservation Multiplier: 130% Requires Level 31 Supports any skill that has a duration. Supported Skills deal (10-19)% more Damage Supported Skills have (40-49)% less Skill Effect Duration | K1: Maim Support Attack, Physical, Support Icon: m Level: (1-20) Cost & Reservation Multiplier: 130% Requires Level 8 Supports attack skills, or other skills that can maim enemies. Supported Skills deal (10-19)% more Physical Damage Supported Attacks have 30% chance to Maim on Hit Enemies Maimed by Supported Skills take 10% increased Physical Damage | L1: Melee Physical Damage Support Melee, Physical, Support, Attack Icon: M Level: (1-20) Cost & Reservation Multiplier: 130% Requires Level 18 Supports melee attack skills. Supported Skills deal (30-49)% more Melee Physical Damage Supported Skills deal (30-49)% more Damage with Bleeding and Poison caused by Melee Hits Supported Skills have 10% less Attack Speed | M1: More Duration Support Support, Duration Icon: D Level: (1-20) Cost & Reservation Multiplier: 130% Requires Level 31 Supports any skill with a duration. Supported Skills have (30-39)% more Skill Effect Duration | N1: Multistrike Support Attack, Melee, Support Icon: 3 Level: (1-20) Cost & Reservation Multiplier: 150% Requires Level 38 Supports melee attack skills, making them repeat twice when used, targeting a random enemy each time. Cannot support Vaal skills, channelling skills, travel skills, retaliation skills or triggered skills. Supported Skills Repeat 2 additional times Supported Skills have (35-44)% more Melee Attack Speed Supported Skills deal (30-20)% less Attack Damage First Repeat of Supported Skills deals 22% more Damage Second Repeat of Supported Skills deals 44% more Damage | O1: Pulverise Support AoE, Support, Melee, Attack Icon: P Level: (1-20) Cost & Reservation Multiplier: 130% Requires Level 31 Supports melee attack skills. Supported Skills have (25-34)% increased Area of Effect Supported Skills have 15% less Attack Speed Supported Skills deal (35-49)% more Melee Area Damage | P1: Ruthless Support Slam, Support, Melee, Attack, Strike Icon: u Level: (1-20) Cost & Reservation Multiplier: 120% Supports melee strike or slam skills. Every third time you use a supported attack, that use of the skill will be more powerful. Every third Attack with Supported Melee Attacks deals a Ruthless Blow Ruthless Blows with Supported Skills deal (70-98)% more Melee Damage Ruthless Blows with Supported Skills deal (70-98)% more Damage with Ailments caused by Melee Hits Ruthless Blows with Supported Skills have a base Stun Duration of 0.8 seconds | Q1: Shockwave Support Support, Melee, Attack, AoE Icon: s Level: (1-20) Cost & Reservation Multiplier: 140% Cooldown Time: 1.00 sec Can Store (1-4) Use(s) Requires Level 18 Supports melee attack skills. Cannot support triggered attacks, attacks used by things other than you, or skills which create minions. Supported Skills will Trigger Shockwave on Melee Hit Supported Skills can only be used with Maces, Sceptres or Staves Base radius is (2.4-2.7) metres (0-38)% increased Cooldown Recovery Rate | R1: Stun Support Support Icon: t Level: (1-20) Requires Level 8 Supports any skill that hits enemies, making it easier to stun enemies with those skills. Supported Skills have (30-49)% reduced Enemy Stun Threshold
A3: Added Cold Damage Support Cold, Support Icon: C Level: (1-20) Cost & Reservation Multiplier: 120% Requires Level 8 Supports any skill that hits enemies. Supported Skills have (4-152) to (6-228) added Cold Damag | B3: Additional Accuracy Support Attack, Support Icon: a Level: (1-20) Cost & Reservation Multiplier: 110% Requires Level 8 Supports attack skills. Supported Skills have +(74-1034) to Accuracy Rating | C3: Barrage Support Bow, Attack, Support, Projectile Icon: N Level: (1-20) Cost & Reservation Multiplier: 150% Requires Level 38 Supports projectile attack skills that use bows or wands. Cannot support triggered skills, channelled skills, or skills that create Minions. Supported Skills deal (68-62)% less Damage Supported Skills Fire Projectiles sequentially Supported Skills fire 3 additional Projectiles Supported Skills have 5% more Attack Time per Projectile Supported Skills have 5% more Trap and Mine Throwing Time per Projectile Supported Skills can only be used with Bows or Wands | D3: Chain Support Support, Chaining, Projectile Icon: c Level: (1-20) Cost & Reservation Multiplier: 140% Requires Level 38 Supports projectile skills, and any other skills that chain. Supported Skills Chain +2 times Supported Skills deal (30-11)% less Damage with Hits | E3: Chance to Poison Support Chaos, Support Icon: O Level: (1-20) Cost & Reservation Multiplier: 120% Supports any skill that hits enemies. Supported Skills have 40% chance to Poison on Hit Supported Skills have (1-94) to (2-141) added Chaos Damage | F3: Cold Penetration Support Cold, Support Icon: V Level: (1-20) Cost & Reservation Multiplier: 130% Requires Level 31 Supports any skill that hits enemies, making those hits penetrate enemy cold resistance. Supported Skills Penetrate (20-34)% Cold Resistance | G3: Critical Strike Affliction Support Critical, Support Icon: o Level: (1-20) Cost & Reservation Multiplier: 130% Requires Level 31 Supports any skill that hits enemies. Supported Skills have +(70-98)% Damage over Time Multiplier for Ailments from Critical Strikes | H3: Culling Strike Support Support Icon: X Level: (1-20) Cost & Reservation Multiplier: 110% Requires Level 18 Supports any skill that hits enemies. If enemies are left below 10% of maximum life after being hit by these skills, they will be killed. Kill Enemies that have 10% Life or lower when Hit by Supported Skills Supported Skills deal (0-38)% increased Damage | I3: Deadly Ailments Support Support Icon: i Level: (1-20) Cost & Reservation Multiplier: 140% Requires Level 18 Supports any skill that hits enemies. Supported Skills deal (30-44)% more Damage with Ailments Supported Skills deal 80% less Damage with Hits | J3: Faster Attacks Support Attack, Support Icon: A Level: (1-20) Cost & Reservation Multiplier: 110% Requires Level 8 Supports attack skills. Supported Skills have (20-44)% increased Attack Speed | K3: Faster Projectiles Support Support, Projectile Icon: j Level: (1-20) Cost & Reservation Multiplier: 120% Requires Level 31 Supports projectile skills. Supported Skills have (50-69)% increased Projectile Speed Supported Skills deal (20-29)% increased Projectile Damage | L3: Fork Support Support, Projectile Icon: Y Level: (1-20) Cost & Reservation Multiplier: 130% Requires Level 31 Supports projectile skills, making their projectiles fork into two projectiles the first time they hit an enemy and don't pierce it. Projectiles from Supported Skills Fork Supported Skills deal (-10-9)% more Projectile Damage | M3: Greater Multiple Projectiles Support Support, Projectile Icon: P Level: (1-20) Cost & Reservation Multiplier: 150% Requires Level 38 Supports projectile skills. Supported Skills deal (35-26)% less Projectile Damage Supported Skills fire 4 additional Projectiles | N3: Greater Volley Support Support, Projectile Icon: ≣ Level: (1-20) Cost & Reservation Multiplier: 150% Requires Level 38 Supports skills that fire projectiles from the user. Does not affect projectiles fired from other locations as secondary effects. Does not support skills that fire projectiles in a spiral. Supported Skills fire 4 additional Projectiles Supported Skills also fire Projectiles from up to 4 points on each side of you Supported Skills deal (30-21)% less Projectile Damage | O3: Hypothermia Support Cold, Support Icon: D Level: (1-20) Cost & Reservation Multiplier: 130% Requires Level 31 Supports any skill that deals damage. Supported Skills have +20% chance to Freeze Enemies which are Chilled Supported Skills deal (20-29)% more Cold Damage Over Time Supported Skills deal (20-29)% more Damage with Hits and Ailments against Chilled Enemies | P3: Impale Support Attack, Physical, Support Icon: I Level: (1-20) Cost & Reservation Multiplier: 130% Requires Level 31 Supports attack skills. Supported Attacks have 60% chance to Impale Enemies on Hit Supported Attacks have (0-28)% increased Impale Effect | Q3: Mirage Archer Support Bow, Attack, Support, Duration Icon: M Level: (1-20) Cost & Reservation Multiplier: 130% Requires Level 4 Supports attack skills that can be used with bows. Supported skills can only be used with bows. Cannot support Vaal skills, minion skills, movement skills, or skills used by totems, traps, or mines. Maximum 1 Summoned Mirage Archer When you Hit an Enemy with an Arrow from a Supported Skill, Summon a Mirage Archer which uses that Skill Mirage Archer can use Triggered Attacks as though they were not Triggered Mirage Archer uses Supported Skill with 60% less Attack Speed Mirage Archer lasts 4 seconds Mirage Archer deals (40-31)% less Damage with Supported Skills | R3: Multiple Projectiles Support Support, Projectile Icon: l Level: (1-20) Cost & Reservation Multiplier: 130% Requires Level 8 Supports projectile skills. Supported Skills deal (15-6)% less Projectile Damage Supported Skills fire 2 additional Projectiles | S3: Pierce Support Support, Projectile Icon: p Level: (1-20) Cost & Reservation Multiplier: 120% Requires Level 4 Supports projectile skills. Projectiles from Supported Skills Pierce (2-4) additional Targets Supported Skills deal (0-19)% more Projectile Damage | T3: Returning Projectiles Support Support, Projectile Icon: R Level: (1-20) Cost & Reservation Multiplier: 150% Requires Level 38 Supports projectile skills. Projectiles from Supported Skills Return to you Projectiles from Supported Skills deal (70-66)% less Damage with Hits and Ailments while Returning Projectiles from Supported Skills Pierce all Targets while Returning | U3: Slower Projectiles Support Support, Projectile Icon: J Level: (1-20) Cost & Reservation Multiplier: 120% Requires Level 31 Supports projectile skills. Supported Skills have (20-30)% less Projectile Speed Supported Skills deal (10-19)% more Projectile Damage | V3: Swift Affliction Support Support, Duration Icon: r Level: (1-20) Cost & Reservation Multiplier: 140% Requires Level 31 Supports any skill that has a duration, or can hit enemies to inflict ailments on them. Supported Skills deal (25-39)% more Damage over Time 25% less Duration of Supported Skills and Damaging Ailments they inflict | W3: Vicious Projectiles Support Projectile, Attack, Physical, Chaos, Support Icon: d Level: (1-20) Cost & Reservation Multiplier: 130% Requires Level 18 Supports projectile attack skills. Supported Skills deal (30-49)% more Chaos Damage over Time Supported Skills deal (30-49)% more Physical Damage over Time Supported Skills deal (30-49)% more Physical Projectile Attack Damage Supported Skills have 10% less Projectile Attack Speed | X3: Vile Toxins Support Support Icon: e Level: (1-20) Cost & Reservation Multiplier: 130% Requires Level 38 Supports any skill that hits enemies. Supported Skills deal 5% more Damage with Hits for each Poison on the Enemy, up to (5-8) Supported Skills deal (10-19)% more Damage with Poison | Y3: Void Manipulation Support Chaos, Support Icon: v Level: (1-20) Cost & Reservation Multiplier: 130% Requires Level 8 Supports any skill that deals damage. Supported Skills deal (20-34)% more Chaos Damage Supported Skills deal no Elemental Damage | Z3: Volley Support Support, Projectile Icon: = Level: (1-20) Cost & Reservation Multiplier: 130% Requires Level 4 Supports skills that fire projectiles from the user. Does not affect projectiles fired from other locations as secondary effects. Does not support skills that fire projectiles in a spiral. Supported Skills fire 2 additional Projectiles Supported Skills also fire Projectiles from up to 2 points on each side of you Supported Skills deal (12-3)% less Projectile Damage
D5: Added Chaos Damage Support Chaos, Support Icon: H Level: (1-20) Cost & Reservation Multiplier: 120% Requires Level 31 Supports any skill that hits enemies. Supported Skills have (18-154) to (26-231) added Chaos Damage | E5: Added Lightning Damage Support Lightning, Support Icon: L Level: (1-20) Cost & Reservation Multiplier: 120% Requires Level 8 Supports any skill that hits enemies. Supported Skills have (1-19) to (8-358) added Lightning Damage | F5: Bonechill Support Cold, Support Icon: B Level: (1-20) Cost & Reservation Multiplier: 130% Requires Level 38 Supports any skill that can chill enemies or create chilling areas. (25-44)% increased Effect of Chill inflicted with Supported Skills Enemies Chilled by Supported Skills increase Cold Damage taken by Chill Effect Enemies in Chilling Areas from Supported Skills increase Cold Damage taken by Chill Effect Supported Skills deal (5-14)% more Cold Damage | G5: Combustion Support Fire, Support Icon: i Level: (1-20) Cost & Reservation Multiplier: 130% Requires Level 8 Supports any skill that hits enemies. Supported Skills deal (10-19)% more Fire Damage Supported Skills have 25% chance to Ignite Enemies Ignited by Supported Skills have -10% to Fire Resistance | H5: Concentrated Effect Support Support, AoE Icon: o Level: (1-20) Cost & Reservation Multiplier: 140% Requires Level 18 Supports any skill with an area of effect, regardless of whether that skill deals damage. Supported Skills deal (25-39)% more Area Damage Supported Skills have 30% less Area of Effect | I5: Controlled Destruction Support Spell, Critical, Support Icon: C Level: (1-20) Cost & Reservation Multiplier: 140% Requires Level 18 Supports attack skills, or spell skills that deal damage. Supported Skills have 80% less Critical Strike Chance Supported Skills deal (25-39)% more Spell Damage | J5: Efficacy Support Support, Duration Icon: a Level: (1-20) Cost & Reservation Multiplier: 130% Requires Level 8 Supports any skill that deals damage or has a duration. Supported Skills deal (15-24)% more Damage over Time Supported Skills have (15-24)% increased Skill Effect Duration | K5: Elemental Focus Support Support Icon: F Level: (1-20) Cost & Reservation Multiplier: 130% Requires Level 18 Supports any skill that hits or burns enemies, or inflicts elemental ailments. Supported Skills deal (20-34)% more Elemental Damage Supported Skills cannot inflict Elemental Ailments | L5: Elemental Proliferation Support Cold, Fire, Lightning, Support, AoE Icon: S Level: (1-20) Cost & Reservation Multiplier: 110% Supports any skill that hits enemies, or could otherwise apply elemental ailments. (0-19)% increased Duration of Elemental Ailments on Enemies Elemental Ailments inflicted by Supported Skills spread to other enemies within (1.2-1.5) metres Supported Skills have 20% chance to Freeze, Shock and Ignite | M5: Faster Casting Support Support, Spell Icon: f Level: (1-20) Cost & Reservation Multiplier: 110% Requires Level 18 Supports non-instant spell skills. Supported Skills have (20-39)% increased Cast Speed | N5: Ignite Proliferation Support Fire, Support, AoE Icon: I Level: (1-20) Cost & Reservation Multiplier: 130% Requires Level 38 Supports any skill that hits enemies. Ignites caused by Supported Skills spread to other Enemies within (1.4-2) metres Supported Skills deal (15-24)% more Damage with Ignite | O5: Increased Area of Effect Support Support, AoE Icon: E Level: (1-20) Cost & Reservation Multiplier: 130% Requires Level 38 Supports any skill with an area of effect. Supported Skills have (30-49)% increased Area of Effect | P5: Increased Critical Damage Support Critical, Support Icon: c Level: (1-20) Cost & Reservation Multiplier: 130% Requires Level 18 Supports any skill that hits enemies. Supported Skills have +(100-138)% to Critical Strike Multiplier | Q5: Increased Critical Strikes Support Critical, Support Icon: s Level: (1-20) Cost & Reservation Multiplier: 120% Requires Level 8 Supports any skill that hits enemies. Supported Skills have (60-117)% increased Critical Strike Chance Supported Skills have +2% to Critical Strike Chance | R5: Infused Channelling Support Support, Channelling Icon: b Level: (1-20) Cost & Reservation Multiplier: 130% Requires Level 4 Supports any channelling skill, protecting you from damage while you channel it. Cannot modify the skills of minions. Supported Skills deal (20-29)% more Damage While Channelling a Supported Skill, take 12% less Damage from Hits | S5: Lightning Penetration Support Lightning, Support Icon: V Level: (1-20) Cost & Reservation Multiplier: 130% Requires Level 31 Supports any skill that hits enemies, making those hits penetrate enemy lightning resistance. Supported Skills Penetrate (20-34)% Lightning Resistance | T5: Minion Damage Support Support, Minion Icon: d Level: (1-20) Cost & Reservation Multiplier: 140% Requires Level 8 Supports skills which create Minions. Minions from Supported Skills deal (25-39)% more Damage Minions from Supported Skills have 25% less Maximum Life | U5: Minion Speed Support Movement, Support, Minion Icon: e Level: (1-20) Cost & Reservation Multiplier: 120% Requires Level 18 Supports skills which create Minions. Supported Skills have (25-34)% increased Minion Attack Speed Supported Skills have (25-34)% increased Minion Cast Speed Supported Skills have (25-44)% increased Minion Movement Speed | V5: Physical to Lightning Support Lightning, Physical, Support Icon: x Level: (1-20) Cost & Reservation Multiplier: 120% Requires Level 18 Supports any skill that hits enemies. Supported Skills gain (10-29)% of Physical Damage as Extra Lightning Damage Supported Skills have 50% of Physical Damage Converted to Lightning Damage | W5: Spell Cascade Support AoE, Spell, Support Icon: p Level: (1-20) Cost & Reservation Multiplier: 130% Requires Level 4 Supports spell skills that apply an effect to an area around a targeted location. Cannot support Vaal skills or skills used by totems, traps, or mines. Cannot modify the skills of minions. Supported Skills have (25-16)% less Area of Effect Supported Skills deal (40-31)% less Damage Supported Area of Effect Skills also affect areas in front of and behind the targeted area | X5: Spell Echo Support Spell, Support Icon: k Level: (1-20) Cost & Reservation Multiplier: 140% Requires Level 38 Supports spell skills, making them repeat when cast. Cannot support Vaal skills, totem skills, channelling skills, triggered skills, instant skills, retaliation skills, blink skills, or skills with a reservation. Supported Skills Repeat an additional time Supported Skills have (40-54)% more Cast Speed | Y5: Trinity Support Support Icon: y Level: (1-20) Cost & Reservation Multiplier: 140% Requires Level 18 Supports skills that hit enemies, causing them to gain bonuses while you have resonance of all three elements, and to grant resonance of elements other than the highest one in a hit. There is a maximum of 50 Resonance for each Element. Cannot support triggered skills, instant skills, orb skills, brands, skills with a reservation, or skills used by totems, traps, or mines. Cannot modify the skills of minions. Hits with Supported Skills for which the highest Damage Type is Elemental cause you to gain 25 Resonance of other Elements per second for 2 seconds Lose 5 Resonance per second of each Element you are not gaining Supported Skills deal 3% more Elemental Damage per 5 of lowest Resonance Supported Skills penetrate (7-16)% Elemental Resistances while each Resonance is at least 25 | Z5: Unleash Support Spell, Support Icon: q Level: (1-20) Cost & Reservation Multiplier: 140% Requires Level 38 Supports spell skills, making their effect reoccur when cast. Cannot support skills with cooldowns, triggered skills, Brand skills, Vaal skills, channelling skills, skills with a reservation, or skills used by totems, traps, or mines. Cannot modify the skills of minions. Supported Spells gain a Seal every (0.90-0.71) seconds, to a maximum of 3 Seals Supported Spells are Unsealed when cast, and their effects Reoccur for each Seal lost Supported Skills deal (45-36)% less Damage when Reoccurring

Sheet PARSED_ACTIVE
A1: SourceSheet | B1: SourceCell | C1: GemType | D1: Name | E1: Tags | F1: DamageType | G1: Scaling | H1: MechanicTags | I1: CombatRole | J1: AilmentKeywords | K1: Level | L1: Cost | M1: Reservation | N1: CostReservationMultiplier | O1: CooldownTime | P1: CanStoreUses | Q1: CastTime | R1: RequiresLevel | S1: AttackSpeed | T1: AttackDamage | U1: EffectivenessAddedDamage | V1: AoERadius | W1: ProjectileSpeed | X1: Icon | Y1: Description | Z1: ModifierLines | AA1: RawText
A2: SKILL | B2: A2 | C2: Active | D2: Anger | E2: Aura, Spell, AoE, Fire | F2: Fire | G2: Spell | H2: Aura, AoE | I2: Buff/Aura, Area | K2: (1-20) | M2: 50% Mana | O2: 1.20 sec | P2: 1 Use(s) | Q2: Instant | R2: 24 | Y2: Casts an aura that adds fire damage to the attacks and spells of you and your allies. | Z2: +(0-1.9) metres to radius You and nearby allies deal (16-109) to (23-155) additional Fire Damage with Attacks You and nearby allies deal (16-109) to (23-155) additional Fire Damage with Spells | AA2: Aura, Spell, AoE, Fire Level: (1-20) Reservation: 50% Mana Cooldown Time: 1.20 sec Can Store 1 Use(s) Cast Time: Instant Requires Level 24 Casts an aura that adds fire damage to the attacks and spells of you and your allies. +(0-1.9) metres to radius You and nearby allies deal (16-109) to (23-155) additional Fire Damage with Attacks You and nearby allies deal (16-109) to (23-155) additional Fire Damage with Spells
A3: SKILL | B3: B2 | C3: Active | D3: Earthquake | E3: Attack, AoE, Melee, Duration, Slam | G3: Attack, Melee | H3: AoE, Melee, Slam | I3: Area, Duration/DoT | J3: Shock | K3: (1-20) | L3: (10-13) Mana | R3: 28 | S3: 75% of base | T3: (143-229)% of base | U3: (143-229)% | V3: 18 / 28 | Y3: Smashes the ground, dealing damage in an area and cracking the earth. The crack will erupt in a powerful aftershock after a duration. Cracks created before the first one has erupted will not generate their own aftershocks. Requires an Axe, Mace, Sceptre, Staff or Unarmed. | Z3: Base duration is 1.00 second Aftershock deals 150% more Damage with Hits and Ailments | AA3: Earthquake Attack, AoE, Melee, Duration, Slam Level: (1-20) Cost: (10-13) Mana Attack Speed: 75% of base Attack Damage: (143-229)% of base Effectiveness of Added Damage: (143-229)% AoE Radius: 18 / 28 Requires Level 28 Smashes the ground, dealing damage in an area and cracking the earth. The crack will erupt in a powerful aftershock after a duration. Cracks created before the first one has erupted will not generate their own aftershocks. Requires an Axe, Mace, Sceptre, Staff or Unarmed. Base duration is 1.00 second Aftershock deals 150% more Damage with Hits and Ailments
A4: SKILL | B4: C2 | C4: Active | D4: Exsanguinate | E4: Spell, Chaining, Physical, Duration | F4: Physical | G4: Spell | H4: Chaining | I4: Duration/DoT, Chain | K4: (1-20) | L4: (16-46) Life | Q4: 0.80 sec | R4: 12 | U4: (150-270)% | Y4: Critical Strike Chance: 6.00% Releases several tendrils of blood from your character, targeting enemies in a narrow angle in front of you. The beams deal physical damage and inflict a physical damage over time debuff to enemies, which can stack up to 3 times. Effects which allow skills to chain can apply to these tendrils. | Z4: Deals (17-1193) to (25-1789) Physical Damage Deals (26.9-1534.2) Base Physical Damage per second Base duration is 1.00 second Modifiers to Spell Damage apply to this Skill's Damage Over Time effect Fires tendrils at up to (7-9) Targets | AA4: Exsanguinate Spell, Chaining, Physical, Duration Level: (1-20) Cost: (16-46) Life Cast Time: 0.80 sec Critical Strike Chance: 6.00% Effectiveness of Added Damage: (150-270)% Requires Level 12 Releases several tendrils of blood from your character, targeting enemies in a narrow angle in front of you. The beams deal physical damage and inflict a physical damage over time debuff to enemies, which can stack up to 3 times. Effects which allow skills to chain can apply to these tendrils. Deals (17-1193) to (25-1789) Physical Damage Deals (26.9-1534.2) Base Physical Damage per second Base duration is 1.00 second Modifiers to Spell Damage apply to this Skill's Damage Over Time effect Fires tendrils at up to (7-9) Targets
A5: SKILL | B5: D2 | C5: Active | D5: Ground Slam | E5: Attack, AoE, Melee, Slam | G5: Attack, Melee | H5: AoE, Melee, Slam | I5: Area | J5: Stun | K5: (1-20) | L5: (6-11) Mana | S5: 90% of base | T5: (132-356)% of base | U5: (132-356)% | V5: 35 | Y5: Slams the ground in front of you, creating a wave that travels forward and damages enemies with an increased chance to stun. The wave deals more damage to closer enemies. Requires an Axe, Mace, Sceptre, Staff or Unarmed. | Z5: 25% reduced Enemy Stun Threshold +(0-1) metre to radius Deals up to (40-49)% more Damage with Hits to closer targets | AA5: Ground Slam Attack, AoE, Melee, Slam Level: (1-20) Cost: (6-11) Mana Attack Speed: 90% of base Attack Damage: (132-356)% of base Effectiveness of Added Damage: (132-356)% AoE Radius: 35 Slams the ground in front of you, creating a wave that travels forward and damages enemies with an increased chance to stun. The wave deals more damage to closer enemies. Requires an Axe, Mace, Sceptre, Staff or Unarmed. 25% reduced Enemy Stun Threshold +(0-1) metre to radius Deals up to (40-49)% more Damage with Hits to closer targets
A6: SKILL | B6: E2 | C6: Active | D6: Herald of Ash | E6: Spell, AoE, Fire, Herald, Duration | F6: Fire | G6: Spell | H6: AoE, Herald | I6: Buff/Aura, Area, Duration/DoT | K6: (1-20) | M6: 25% Mana | O6: 1.00 sec | P6: 1 Use(s) | Q6: Instant | R6: 16 | V6: 10 | Y6: Base Burning Damage is 25% of Overkill Damage Buff grants (15-20)% of your Physical Damage as Extra Fire Damage | Z6: Grants a buff providing fire damage based on your physical damage. While you have this buff, if you kill an enemy, other enemies near them will be burned based on the overkill damage. The burn inflicted by this skill can only be affected by modifiers to damage over time (burning damage is damage over time). Base duration is 4.00 seconds (0-38)% more Burning Damage | AA6: Herald of Ash Spell, AoE, Fire, Herald, Duration Level: (1-20) Reservation: 25% Mana Cooldown Time: 1.00 sec Can Store 1 Use(s) Cast Time: Instant AoE Radius: 10 Requires Level 16 Grants a buff providing fire damage based on your physical damage. While you have this buff, if you kill an enemy, other enemies near them will be burned based on the overkill damage. The burn inflicted by this skill can only be affected by modifiers to damage over time (burning damage is damage over time). Base duration is 4.00 seconds Base Burning Damage is 25% of Overkill Damage (0-38)% more Burning Damage Buff grants (15-20)% of your Physical Damage as Extra Fire Damage
A7: SKILL | B7: F2 | C7: Active | D7: Molten Strike | E7: Attack, Projectile, AoE, Melee, Strike, Fire | F7: Fire | G7: Attack, Melee | H7: Projectile, AoE, Melee, Strike | I7: Projectile, Area | K7: (1-20) | L7: (6-10) Mana | T7: (126-329)% of base | U7: (126-329)% | W7: 750 | Y7: Infuses your melee weapon with molten energies to attack with physical and fire damage. This attack causes balls of molten magma to launch forth from the enemies you hit, divided amongst all enemies hit by the strike. These will deal area attack damage to enemies where they land. | Z7: Fires 4 Projectiles 60% of Physical Damage Converted to Fire Damage Projectiles deal 60% less Damage with Hits and Ailments | AA7: Molten Strike Attack, Projectile, AoE, Melee, Strike, Fire Level: (1-20) Cost: (6-10) Mana Attack Damage: (126-329)% of base Effectiveness of Added Damage: (126-329)% Projectile Speed: 750 Infuses your melee weapon with molten energies to attack with physical and fire damage. This attack causes balls of molten magma to launch forth from the enemies you hit, divided amongst all enemies hit by the strike. These will deal area attack damage to enemies where they land. Fires 4 Projectiles 60% of Physical Damage Converted to Fire Damage Projectiles deal 60% less Damage with Hits and Ailments
A8: SKILL | B8: G2 | C8: Active | D8: Pride | E8: Spell, AoE, Aura, Physical | F8: Physical | G8: Spell | H8: AoE, Aura | I8: Buff/Aura, Area | K8: (1-20) | M8: 50% Mana | O8: 1.20 sec | P8: 1 Use(s) | Q8: Instant | R8: 24 | Y8: Casts an aura that causes nearby enemies to take more physical damage. raising up to (30-39)% as they stay in the Aura for 4 seconds | Z8: +(0-1) metre to radius Nearby Enemies take at least (15-19)% more Physical Damage, | AA8: Pride Spell, AoE, Aura, Physical Level: (1-20) Reservation: 50% Mana Cooldown Time: 1.20 sec Can Store 1 Use(s) Cast Time: Instant Requires Level 24 Casts an aura that causes nearby enemies to take more physical damage. +(0-1) metre to radius Nearby Enemies take at least (15-19)% more Physical Damage, raising up to (30-39)% as they stay in the Aura for 4 seconds
A9: SKILL | B9: H2 | C9: Active | D9: Reap | E9: Spell, Physical, AoE, Duration | F9: Physical | G9: Spell | H9: AoE | I9: Area, Duration/DoT | K9: (1-20) | L9: (25-46) Life | Q9: 0.80 sec | R9: 28 | U9: (150-210)% | Y9: Critical Strike Chance: 6.00% A bloody scythe swipes across a selected area, applying a physical damage over time debuff and hitting enemies with physical damage. If any survive, you gain a blood charge which raises the damage and cost of the skill. Players can have 5 maximum blood charges. Gain a Blood Charge if this Skill Hits Enemies and none of them Die Lose a Blood Charge when an Enemy Dies while affected by this Skill's Debuff | Z9: Deals (57-943) to (86-1414) Physical Damage Deals (138.2-2002.5) Base Physical Damage per second Base duration is 1.00 second Modifiers to Spell Damage apply to this Skill's Damage Over Time effect Costs 20% more Life per Blood Charge Deals 15% more Damage per Blood Charge | AA9: Reap Spell, Physical, AoE, Duration Level: (1-20) Cost: (25-46) Life Cast Time: 0.80 sec Critical Strike Chance: 6.00% Effectiveness of Added Damage: (150-210)% Requires Level 28 A bloody scythe swipes across a selected area, applying a physical damage over time debuff and hitting enemies with physical damage. If any survive, you gain a blood charge which raises the damage and cost of the skill. Players can have 5 maximum blood charges. Deals (57-943) to (86-1414) Physical Damage Deals (138.2-2002.5) Base Physical Damage per second Base duration is 1.00 second Modifiers to Spell Damage apply to this Skill's Damage Over Time effect Gain a Blood Charge if this Skill Hits Enemies and none of them Die Lose a Blood Charge when an Enemy Dies while affected by this Skill's Debuff Costs 20% more Life per Blood Charge Deals 15% more Damage per Blood Charge
A10: SKILL | B10: I2 | C10: Active | D10: Smite | E10: Lightning, Melee, Attack, AoE, Duration, Strike, Aura | F10: Lightning | G10: Attack, Melee | H10: Melee, AoE, Strike, Aura | I10: Buff/Aura, Area, Duration/DoT | J10: Shock | K10: (1-20) | L10: (7-12) Mana | S10: 85% of base | T10: (225-488)% of base | U10: (225-488)% | Y10: Performs a melee attack, and causes lightning to strike a nearby enemy, dealing damage in an area. Each target can only be hit once by this skill. Hitting an enemy grants an aura for a duration. Requires a Sword, Axe, Mace, Sceptre, Staff or Unarmed. | Z10: 50% of Physical Damage Converted to Lightning Damage Base duration is 4.00 seconds (30-20)% less Area Damage Base radius is (1.5-2.1) metres Base Aura radius is (3.6-4.2) metres Lightning strikes 1 target within 5 metres Aura grants (1-12) to (4-220) added Lightning Damage Aura grants (10-19)% chance to Shock | AA10: Smite Lightning, Melee, Attack, AoE, Duration, Strike, Aura Level: (1-20) Cost: (7-12) Mana Attack Speed: 85% of base Attack Damage: (225-488)% of base Effectiveness of Added Damage: (225-488)% Performs a melee attack, and causes lightning to strike a nearby enemy, dealing damage in an area. Each target can only be hit once by this skill. Hitting an enemy grants an aura for a duration. Requires a Sword, Axe, Mace, Sceptre, Staff or Unarmed. 50% of Physical Damage Converted to Lightning Damage Base duration is 4.00 seconds (30-20)% less Area Damage Base radius is (1.5-2.1) metres Base Aura radius is (3.6-4.2) metres Lightning strikes 1 target within 5 metres Aura grants (1-12) to (4-220) added Lightning Damage Aura grants (10-19)% chance to Shock
A11: SKILL | B11: J2 | C11: Active | D11: Summon Stone Golem | E11: Minion, Spell, Golem, Physical | F11: Physical | G11: Spell, Minion | H11: Minion | I11: Summon | K11: (1-20) | L11: (30-54) Mana | O11: 6.00 sec | P11: 1 Use(s) | Q11: 1.00 sec | R11: 34 | Y11: Golems grant (33-105) Life Regenerated per second | Z11: Summons a Stone Golem that grants you life regeneration and defences. In addition to its melee attack, the Stone Golem uses a rolling charge and a powerful slam that can taunt enemies. Maximum 1 Summoned Golem Golems grant 20% increased Defences | AA11: Summon Stone Golem Minion, Spell, Golem, Physical Level: (1-20) Cost: (30-54) Mana Cooldown Time: 6.00 sec Can Store 1 Use(s) Cast Time: 1.00 sec Requires Level 34 Summons a Stone Golem that grants you life regeneration and defences. In addition to its melee attack, the Stone Golem uses a rolling charge and a powerful slam that can taunt enemies. Maximum 1 Summoned Golem Golems grant (33-105) Life Regenerated per second Golems grant 20% increased Defences
A12: SKILL | B12: K2 | C12: Active | D12: Swordstorm | E12: Attack, Melee, AoE, Retaliation | G12: Attack, Melee | H12: Melee, AoE, Retaliation | I12: Area | K12: (1-20) | L12: (7-10) Mana | O12: 3.00 sec | P12: 1 Use(s) | R12: 16 | T12: (123-247)% of base | U12: (123-247)% | Y12: Retaliate against a blocked hit with a hail of blades that rains down in front of you, repeatedly dealing the damage of both your weapons combined. Requires Dual Wielding Melee Weapons. | Z12: Cannot be used by default Becomes Usable once for 2 seconds when you Block a Hit Can't be Evaded Base radius is (1.8-2.3) metres Damages Enemies 8 times | AA12: Swordstorm Attack, Melee, AoE, Retaliation Level: (1-20) Cost: (7-10) Mana Cooldown Time: 3.00 sec Can Store 1 Use(s) Attack Damage: (123-247)% of base Effectiveness of Added Damage: (123-247)% Requires Level 16 Retaliate against a blocked hit with a hail of blades that rains down in front of you, repeatedly dealing the damage of both your weapons combined. Requires Dual Wielding Melee Weapons. Cannot be used by default Becomes Usable once for 2 seconds when you Block a Hit Can't be Evaded Base radius is (1.8-2.3) metres Damages Enemies 8 times
A13: SKILL | B13: L2 | C13: Active | D13: Volcanic Fissure | E13: Melee, Attack, Projectile, AoE, Slam, Fire | F13: Fire | G13: Attack, Melee | H13: Melee, Projectile, AoE, Slam | I13: Projectile, Area | K13: (1-20) | L13: (8-13) Mana | R13: 12 | S13: 80% of base | T13: (177-344)% of base | U13: (177-344)% | Y13: Slam the ground, creating a winding fissure that deals area damage while travelling outwards. When it reaches the target location it erupts, releasing a burst of molten projectiles. Requires an Axe, Mace, Sceptre, Staff or Unarmed. | Z13: Fires 5 Projectiles 60% of Physical Damage Converted to Fire Damage Projectiles deal 50% less Damage with Hits and Ailments | AA13: Volcanic Fissure Melee, Attack, Projectile, AoE, Slam, Fire Level: (1-20) Cost: (8-13) Mana Attack Speed: 80% of base Attack Damage: (177-344)% of base Effectiveness of Added Damage: (177-344)% Requires Level 12 Slam the ground, creating a winding fissure that deals area damage while travelling outwards. When it reaches the target location it erupts, releasing a burst of molten projectiles. Requires an Axe, Mace, Sceptre, Staff or Unarmed. Fires 5 Projectiles 60% of Physical Damage Converted to Fire Damage Projectiles deal 50% less Damage with Hits and Ailments
A14: SKILL | B14: A4 | C14: Active | D14: Animate Weapon | E14: Duration, Minion, Spell, Physical | F14: Physical | G14: Spell, Minion | H14: Minion | I14: Summon, Duration/DoT | K14: (1-20) | L14: (4-16) Mana | Q14: 0.60 sec | R14: 4 | Y14: Animates a Melee Weapon Item or Lingering Blade to fight by your side. You cannot animate unidentified Weapons. Will not animate weapons with 6 sockets. Cannot be used by Traps or Mines. Minions' Attacks deal (5-126) to (8-184) additional Physical Damage Animated Lingering Blades deal (1-17) to (2-80) Added Attack Physical Damage | Z14: Base duration is 40.00 seconds Maximum (5-14) Animated Weapons Can use Items requiring up to Level (9-100) Minions deal (0-38)% more Damage Minions have (0-38)% more Attack Speed | AA14: Animate Weapon Duration, Minion, Spell, Physical Level: (1-20) Cost: (4-16) Mana Cast Time: 0.60 sec Requires Level 4 Animates a Melee Weapon Item or Lingering Blade to fight by your side. You cannot animate unidentified Weapons. Will not animate weapons with 6 sockets. Cannot be used by Traps or Mines. Base duration is 40.00 seconds Maximum (5-14) Animated Weapons Can use Items requiring up to Level (9-100) Minions' Attacks deal (5-126) to (8-184) additional Physical Damage Animated Lingering Blades deal (1-17) to (2-80) Added Attack Physical Damage Minions deal (0-38)% more Damage Minions have (0-38)% more Attack Speed
A15: SKILL | B15: B4 | C15: Active | D15: Barrage | E15: Attack, Projectile, Bow | G15: Attack, Bow | H15: Projectile, Bow | I15: Projectile | K15: (1-20) | L15: (5-9) Mana | R15: 12 | S15: 115% of base | T15: (47-54)% of base | U15: (47-55)% | Y15: After a short preparation time, you fire individual projectiles repeatedly with a Bow or Wand. These projectiles have a small randomised spread. This skill cannot be Triggered. | Z15: Fires 5 Projectiles Fires Projectiles sequentially | AA15: Barrage Attack, Projectile, Bow Level: (1-20) Cost: (5-9) Mana Attack Speed: 115% of base Attack Damage: (47-54)% of base Effectiveness of Added Damage: (47-55)% Requires Level 12 After a short preparation time, you fire individual projectiles repeatedly with a Bow or Wand. These projectiles have a small randomised spread. This skill cannot be Triggered. Fires 5 Projectiles Fires Projectiles sequentially
A16: SKILL | B16: C4 | C16: Active | D16: Blade Vortex | E16: Spell, AoE, Duration, Physical | F16: Physical | G16: Spell | H16: AoE | I16: Area, Duration/DoT | K16: (1-20) | L16: (6-16) Mana | Q16: 0.50 sec | R16: 12 | U16: 30% | Y16: Critical Strike Chance: 6.00% This spell creates ethereal blades which orbit in an area around you, dealing damage every 0.6 seconds to all enemies in their radius. As more blades are added, the damage becomes greater and more frequent. | Z16: Deals (3-140) to (5-211) Physical Damage Base duration is 4.00 seconds +(0-0.2) metres to radius 35% increased Hit Rate for each blade 35% more Damage for each blade Can have up to 10 active spinning blades | AA16: Blade Vortex Spell, AoE, Duration, Physical Level: (1-20) Cost: (6-16) Mana Cast Time: 0.50 sec Critical Strike Chance: 6.00% Effectiveness of Added Damage: 30% Requires Level 12 This spell creates ethereal blades which orbit in an area around you, dealing damage every 0.6 seconds to all enemies in their radius. As more blades are added, the damage becomes greater and more frequent. Deals (3-140) to (5-211) Physical Damage Base duration is 4.00 seconds +(0-0.2) metres to radius 35% increased Hit Rate for each blade 35% more Damage for each blade Can have up to 10 active spinning blades
A17: SKILL | B17: D4 | C17: Active | D17: Blast Rain | E17: Fire, Attack, AoE, Projectile, Bow | F17: Fire | G17: Attack, Bow | H17: AoE, Projectile, Bow | I17: Projectile, Area | K17: (1-20) | L17: (7-10) Mana | R17: 28 | T17: (30-35)% of base | U17: (30-36)% | Y17: 100% of Physical Damage Converted to Fire Damage | Z17: Fires arrows up in the air, to rain down in an area. Each arrow deals area damage around where it lands, and they will all overlap on the targeted location. Fires 6 Arrows Penetrates (20-30)% Fire Resistance | AA17: Blast Rain Fire, Attack, AoE, Projectile, Bow Level: (1-20) Cost: (7-10) Mana Attack Damage: (30-35)% of base Effectiveness of Added Damage: (30-36)% Requires Level 28 Fires arrows up in the air, to rain down in an area. Each arrow deals area damage around where it lands, and they will all overlap on the targeted location. Fires 6 Arrows 100% of Physical Damage Converted to Fire Damage Penetrates (20-30)% Fire Resistance
A18: SKILL | B18: E4 | C18: Active | D18: Burning Arrow | E18: Attack, Projectile, Fire, Bow | F18: Fire | G18: Attack, Bow | H18: Projectile, Bow | I18: Projectile | J18: Ignite | K18: (1-20) | L18: (8-14) Mana | S18: 70% of base | T18: (280-420)% of base | U18: (280-420)% | W18: 3260 | Y18: 25% chance to Ignite enemies | Z18: Fires a burning arrow that deals fire damage and has a chance to ignite. 100% of Physical Damage Converted to Fire Damage | AA18: Burning Arrow Attack, Projectile, Fire, Bow Level: (1-20) Cost: (8-14) Mana Attack Speed: 70% of base Attack Damage: (280-420)% of base Effectiveness of Added Damage: (280-420)% Projectile Speed: 3260 Fires a burning arrow that deals fire damage and has a chance to ignite. 25% chance to Ignite enemies 100% of Physical Damage Converted to Fire Damage
A19: SKILL | B19: F4 | C19: Active | D19: Cobra Lash | E19: Attack, Projectile, Chaos | F19: Chaos | G19: Attack | H19: Projectile | I19: Projectile, Chain | J19: Poison | K19: (1-20) | L19: (5-8) Mana | S19: 120% of base | T19: (125-205)% of base | U19: (125-205)% | Y19: 8% more Damage with Hits and Ailments for each remaining Chain | Z19: Fires a poisonous projectile based on your weapon that will chain between enemies. Requires a Dagger or Claw. Chains +(3-5) Times 60% of Physical Damage Converted to Chaos Damage 40% chance to Poison on Hit | AA19: Cobra Lash Attack, Projectile, Chaos Level: (1-20) Cost: (5-8) Mana Attack Speed: 120% of base Attack Damage: (125-205)% of base Effectiveness of Added Damage: (125-205)% Fires a poisonous projectile based on your weapon that will chain between enemies. Requires a Dagger or Claw. 8% more Damage with Hits and Ailments for each remaining Chain Chains +(3-5) Times 60% of Physical Damage Converted to Chaos Damage 40% chance to Poison on Hit
A20: SKILL | B20: G4 | C20: Active | D20: Cyclone | E20: Attack, AoE, Melee, Movement, Channelling | G20: Attack, Melee | H20: AoE, Melee, Movement, Channelling | I20: Area, Channel | K20: (1-20) | L20: (2-3) Mana | R20: 28 | S20: 300% of base | T20: (81-150)% of base | U20: (81-150)% | V20: 1.6 | Y20: Channel this skill to move towards a targeted location while spinning constantly attacking enemies in an area around you. While channelling this skill, you cannot be knocked back. 15% increased Area of Effect per 0.1 metre additional Melee Strike Range | Z20: (30-20)% less Movement Speed | AA20: Cyclone Attack, AoE, Melee, Movement, Channelling Level: (1-20) Cost: (2-3) Mana Attack Speed: 300% of base Attack Damage: (81-150)% of base Effectiveness of Added Damage: (81-150)% AoE Radius: 1.6 Requires Level 28 Channel this skill to move towards a targeted location while spinning constantly attacking enemies in an area around you. While channelling this skill, you cannot be knocked back. 15% increased Area of Effect per 0.1 metre additional Melee Strike Range (30-20)% less Movement Speed
A21: SKILL | B21: H4 | C21: Active | D21: Detonate Dead | E21: Spell, AoE, Fire | F21: Fire | G21: Spell | H21: AoE | I21: Area | K21: (1-20) | L21: (5-20) Mana | Q21: 0.60 sec | R21: 4 | U21: 160% | V21: 22 | Y21: Critical Strike Chance: 6.00% Targets a corpse, and deals spell damage to enemies around the corpse, as well as causing the corpse to explode, dealing fire damage. The explosion is not affected by modifiers to spell damage and cannot be reflected. Explosion deals base Fire Damage equal to (6-7.9)% of the corpse's Maximum Life | Z21: Deals (15-798) to (22-1197) Fire Damage Base radius is (2.2-2.6) metres | AA21: Detonate Dead Spell, AoE, Fire Level: (1-20) Cost: (5-20) Mana Cast Time: 0.60 sec Critical Strike Chance: 6.00% Effectiveness of Added Damage: 160% AoE Radius: 22 Requires Level 4 Targets a corpse, and deals spell damage to enemies around the corpse, as well as causing the corpse to explode, dealing fire damage. The explosion is not affected by modifiers to spell damage and cannot be reflected. Deals (15-798) to (22-1197) Fire Damage Explosion deals base Fire Damage equal to (6-7.9)% of the corpse's Maximum Life Base radius is (2.2-2.6) metres
A22: SKILL | B22: I4 | C22: Active | D22: Explosive Arrow | E22: Attack, Projectile, AoE, Duration, Fire, Bow | F22: Fire | G22: Attack, Bow | H22: Projectile, AoE, Bow | I22: Projectile, Area, Duration/DoT | K22: (1-20) | L22: (7-10) Mana | R22: 28 | V22: 15 | W22: 3260 | Y22: Explosion deals 50% less Base Damage Explosion deals 6% more Damage with Hits per Explosive Arrow on Target Explosion deals 3% more Damage with Ailments per Explosive Arrow on Target | Z22: Fires an arrow which will stick into an enemy or wall, and then explode, dealing area damage around it, either after a duration or when the maximum number of arrows stuck to that target is reached. If an enemy has multiple Explosive Arrows stuck in them, the first one to explode will consume the others, adding their damage to its explosion. Base duration is 1.00 second Explosion will have (47-522) to (71-783) added Fire Damage +0.2 metres to Explosion Radius per Explosive Arrow on Target, up to a maximum of +1.2 metres Maximum 20 Explosive Arrows stuck in an Enemy | AA22: Explosive Arrow Attack, Projectile, AoE, Duration, Fire, Bow Level: (1-20) Cost: (7-10) Mana Projectile Speed: 3260 AoE Radius: 15 Requires Level 28 Fires an arrow which will stick into an enemy or wall, and then explode, dealing area damage around it, either after a duration or when the maximum number of arrows stuck to that target is reached. If an enemy has multiple Explosive Arrows stuck in them, the first one to explode will consume the others, adding their damage to its explosion. Base duration is 1.00 second Explosion deals 50% less Base Damage Explosion will have (47-522) to (71-783) added Fire Damage +0.2 metres to Explosion Radius per Explosive Arrow on Target, up to a maximum of +1.2 metres Explosion deals 6% more Damage with Hits per Explosive Arrow on Target Explosion deals 3% more Damage with Ailments per Explosive Arrow on Target Maximum 20 Explosive Arrows stuck in an Enemy
A23: SKILL | B23: J4 | C23: Active | D23: Explosive Concoction | E23: Attack, AoE, Fire, Cold, Lightning, Projectile | F23: Fire, Cold, Lightning | G23: Attack | H23: AoE, Projectile | I23: Projectile, Area | J23: Ignite | K23: (1-20) | L23: (6-9) Mana | R23: 28 | S23: 115% of base | Y23: Throws a bottle that explodes to deal unarmed attack damage in an area. Can consume charges from your Ruby, Sapphire, and Topaz flasks to add further damage. Requires an empty main hand, and no off-hand weapon. | Z23: (65-806) to (98-1210) Added Fire Damage +6% to Critical Strike Chance Base radius is 1.8 metres Can consume Charges from Ruby, Sapphire, and Topaz Flasks Consumes 1 Charge per Projectile Fired from 1 Flask of each valid type, if possible Deals (57-706) to (86-1058) Added Cold Damage if Charges were consumed from a Sapphire Flask Deals (12-151) to (143-1764) Added Lightning Damage if Charges were consumed from a Topaz Flask +(120-196)% to Damage over Time Multiplier with Ignite if Charges were consumed from a Ruby Flask | AA23: Explosive Concoction Attack, AoE, Fire, Cold, Lightning, Projectile Level: (1-20) Cost: (6-9) Mana Attack Speed: 115% of base Requires Level 28 Throws a bottle that explodes to deal unarmed attack damage in an area. Can consume charges from your Ruby, Sapphire, and Topaz flasks to add further damage. Requires an empty main hand, and no off-hand weapon. (65-806) to (98-1210) Added Fire Damage +6% to Critical Strike Chance Base radius is 1.8 metres Can consume Charges from Ruby, Sapphire, and Topaz Flasks Consumes 1 Charge per Projectile Fired from 1 Flask of each valid type, if possible Deals (57-706) to (86-1058) Added Cold Damage if Charges were consumed from a Sapphire Flask Deals (12-151) to (143-1764) Added Lightning Damage if Charges were consumed from a Topaz Flask +(120-196)% to Damage over Time Multiplier with Ignite if Charges were consumed from a Ruby Flask
A24: SKILL | B24: K4 | C24: Active | D24: Flicker Strike | E24: Attack, Melee, Strike, Movement, Duration | G24: Attack, Melee | H24: Melee, Strike, Movement | I24: Duration/DoT | K24: (1-20) | L24: (5-8) Mana | O24: 2.00 sec | P24: 1 Use(s) | R24: 10 | S24: 120% of base | T24: (177-408)% of base | U24: (177-408)% | Y24: Teleports the character to a nearby monster and attacks with a melee weapon. If no specific monster is targeted, one is picked at random. Grants a buff that increases movement speed for a duration. The cooldown can be bypassed by expending a Frenzy Charge. | Z24: Base duration is 3.00 seconds 10% increased Attack Speed per Frenzy Charge 15% chance to gain a Frenzy Charge on Hit Buff grants 20% increased Movement Speed | AA24: Flicker Strike Attack, Melee, Strike, Movement, Duration Level: (1-20) Cost: (5-8) Mana Cooldown Time: 2.00 sec Can Store 1 Use(s) Attack Speed: 120% of base Attack Damage: (177-408)% of base Effectiveness of Added Damage: (177-408)% Requires Level 10 Teleports the character to a nearby monster and attacks with a melee weapon. If no specific monster is targeted, one is picked at random. Grants a buff that increases movement speed for a duration. The cooldown can be bypassed by expending a Frenzy Charge. Base duration is 3.00 seconds 10% increased Attack Speed per Frenzy Charge 15% chance to gain a Frenzy Charge on Hit Buff grants 20% increased Movement Speed
A25: SKILL | B25: L4 | C25: Active | D25: Frost Blades | E25: Attack, Projectile, Melee, Strike, Cold | F25: Cold | G25: Attack, Melee | H25: Projectile, Melee, Strike | I25: Projectile | K25: (1-20) | L25: (6-10) Mana | T25: (143-409)% of base | U25: (143-409)% | W25: 2250 | Y25: Attack enemies with increased range, releasing icy blades from the first enemy hit which fly at other enemies. Requires a Melee Weapon. | Z25: Fires (5-8) Projectiles 60% of Physical Damage Converted to Cold Damage +(1.8-2.1) metres to Melee Strike Range Projectiles deal 30% less Damage with Hits and Ailments | AA25: Frost Blades Attack, Projectile, Melee, Strike, Cold Level: (1-20) Cost: (6-10) Mana Attack Damage: (143-409)% of base Effectiveness of Added Damage: (143-409)% Projectile Speed: 2250 Attack enemies with increased range, releasing icy blades from the first enemy hit which fly at other enemies. Requires a Melee Weapon. Fires (5-8) Projectiles 60% of Physical Damage Converted to Cold Damage +(1.8-2.1) metres to Melee Strike Range Projectiles deal 30% less Damage with Hits and Ailments
A26: SKILL | B26: M4 | C26: Active | D26: Galvanic Arrow | E26: Lightning, Attack, Projectile, AoE, Bow | F26: Lightning | G26: Attack, Bow | H26: Projectile, AoE, Bow | I26: Projectile, Area | K26: (1-20) | L26: (6-10) Mana | T26: (92-113)% of base | U26: (92-113)% | Y26: Fire a trio of electrical arrows that quickly dissipate, vanishing shortly after being loosed. The arrows are fired with such force that they create a burst of lightning, damaging enemies in a cone in front of you. | Z26: 50% of Physical Damage Converted to Lightning Damage Fires 3 Arrows +(0-0.5) metres to radius Increases and Reductions to Projectile Speed also apply to this Skill's Area of Effect | AA26: Galvanic Arrow Lightning, Attack, Projectile, AoE, Bow Level: (1-20) Cost: (6-10) Mana Attack Damage: (92-113)% of base Effectiveness of Added Damage: (92-113)% Fire a trio of electrical arrows that quickly dissipate, vanishing shortly after being loosed. The arrows are fired with such force that they create a burst of lightning, damaging enemies in a cone in front of you. 50% of Physical Damage Converted to Lightning Damage Fires 3 Arrows +(0-0.5) metres to radius Increases and Reductions to Projectile Speed also apply to this Skill's Area of Effect
A27: SKILL | B27: N4 | C27: Active | D27: Haste | E27: Aura, Spell, AoE | G27: Spell | H27: Aura, AoE | I27: Buff/Aura, Area | K27: (1-20) | M27: 50% Mana | O27: 1.20 sec | P27: 1 Use(s) | Q27: Instant | R27: 24 | V27: 36 | Y27: Casts an aura that increases the movement speed, attack speed and cast speed of you and your allies. | Z27: +(0-1.9) metres to radius You and nearby allies gain (10-16)% increased Movement Speed You and nearby allies gain (15-24)% increased Attack Speed You and nearby allies gain (15-24)% increased Cast Speed | AA27: Haste Aura, Spell, AoE Level: (1-20) Reservation: 50% Mana Cooldown Time: 1.20 sec Can Store 1 Use(s) Cast Time: Instant AoE Radius: 36 Requires Level 24 Casts an aura that increases the movement speed, attack speed and cast speed of you and your allies. +(0-1.9) metres to radius You and nearby allies gain (10-16)% increased Movement Speed You and nearby allies gain (15-24)% increased Attack Speed You and nearby allies gain (15-24)% increased Cast Speed
A28: SKILL | B28: O4 | C28: Active | D28: Hatred | E28: Aura, Spell, AoE, Cold | F28: Cold | G28: Spell | H28: Aura, AoE | I28: Buff/Aura, Area | K28: (1-20) | M28: 50% Mana | O28: 1.20 sec | P28: 1 Use(s) | Q28: Instant | R28: 24 | V28: 36 | Y28: Casts an aura that grants extra cold damage based on physical damage to you and your allies. | Z28: +(0-1.9) metres to radius You and nearby allies gain (30-39)% of Physical Damage as Extra Cold Damage | AA28: Hatred Aura, Spell, AoE, Cold Level: (1-20) Reservation: 50% Mana Cooldown Time: 1.20 sec Can Store 1 Use(s) Cast Time: Instant AoE Radius: 36 Requires Level 24 Casts an aura that grants extra cold damage based on physical damage to you and your allies. +(0-1.9) metres to radius You and nearby allies gain (30-39)% of Physical Damage as Extra Cold Damage
A29: SKILL | B29: P4 | C29: Active | D29: Herald of Agony | E29: Spell, Herald, Minion, Chaos, Physical | F29: Chaos, Physical | G29: Spell, Minion | H29: Herald, Minion | I29: Buff/Aura, Summon | J29: Poison | K29: (1-20) | M29: 25% Mana | O29: 1.00 sec | P29: 1 Use(s) | Q29: Instant | R29: 16 | Y29: Buff grants 20% chance to Poison on Hit Agony Crawler has (2-4)% increased Attack Speed per Virulence you have Agony Crawler deals (5-9)% increased Physical Damage per Virulence you have Agony Crawler has (1-45) to (3-84) Added Physical Damage per Virulence you have | Z29: Grants a buff giving more poison damage and a chance to inflict poison. When you poison an enemy while you have this buff, you gain Virulence, and summon an Agony Crawler minion that uses projectile and area attacks. You will lose Virulence over time, at a rate which increases the more Virulence you have. The minion will die when you have no Virulence. Maximum 1 Summoned Agony Crawler Grants Virulence when you Poison an Enemy Buff grants 10% more Damage with Poison 40 Maximum Virulence Minions cannot Taunt Enemies | AA29: Herald of Agony Spell, Herald, Minion, Chaos, Physical Level: (1-20) Reservation: 25% Mana Cooldown Time: 1.00 sec Can Store 1 Use(s) Cast Time: Instant Requires Level 16 Grants a buff giving more poison damage and a chance to inflict poison. When you poison an enemy while you have this buff, you gain Virulence, and summon an Agony Crawler minion that uses projectile and area attacks. You will lose Virulence over time, at a rate which increases the more Virulence you have. The minion will die when you have no Virulence. Maximum 1 Summoned Agony Crawler Buff grants 20% chance to Poison on Hit Grants Virulence when you Poison an Enemy Buff grants 10% more Damage with Poison 40 Maximum Virulence Minions cannot Taunt Enemies Agony Crawler has (2-4)% increased Attack Speed per Virulence you have Agony Crawler deals (5-9)% increased Physical Damage per Virulence you have Agony Crawler has (1-45) to (3-84) Added Physical Damage per Virulence you have
A30: SKILL | B30: Q4 | C30: Active | D30: Herald of Ice | E30: Spell, AoE, Cold, Herald | F30: Cold | G30: Spell | H30: AoE, Herald | I30: Buff/Aura, Area | K30: (1-20) | M30: 25% Mana | O30: 1.00 sec | P30: 1 Use(s) | Q30: Instant | R30: 16 | U30: 80% | Y30: Damage cannot be Reflected | Z30: Grants a buff adding cold damage to spells and attacks. If you shatter an enemy, this skill will cause them to explode and deal AoE cold damage to enemies near them. This damage is not affected by modifiers to spell damage. Deals (18-308) to (26-462) Cold Damage Base radius is 1.2 metres Buff grants (4-38) to (5-56) Added Attack Cold Damage Buff grants (4-38) to (5-56) Added Spell Cold Damag | AA30: Herald of Ice Spell, AoE, Cold, Herald Level: (1-20) Reservation: 25% Mana Cooldown Time: 1.00 sec Can Store 1 Use(s) Cast Time: Instant Effectiveness of Added Damage: 80% Requires Level 16 Grants a buff adding cold damage to spells and attacks. If you shatter an enemy, this skill will cause them to explode and deal AoE cold damage to enemies near them. This damage is not affected by modifiers to spell damage. Deals (18-308) to (26-462) Cold Damage Damage cannot be Reflected Base radius is 1.2 metres Buff grants (4-38) to (5-56) Added Attack Cold Damage Buff grants (4-38) to (5-56) Added Spell Cold Damag
A31: SKILL | B31: R4 | C31: Active | D31: Ice Shot | E31: Attack, Projectile, AoE, Cold, Bow | F31: Cold | G31: Attack, Bow | H31: Projectile, AoE, Bow | I31: Projectile, Area | J31: Chill | K31: (1-20) | L31: (6-10) Mana | T31: (149-200)% of base | U31: (149-200)% | V31: 23 / 10 | W31: 3260 | Y31: 60% of Physical Damage Converted to Cold Damage | Z31: Fires an arrow that converts some physical damage to cold on its target and converts all physical damage to cold in a cone behind that target. Base radius is 2.4 metres Chills Enemies as though dealing (100-195)% more Damage | AA31: Ice Shot Attack, Projectile, AoE, Cold, Bow Level: (1-20) Cost: (6-10) Mana Attack Damage: (149-200)% of base Effectiveness of Added Damage: (149-200)% Projectile Speed: 3260 AoE Radius: 23 / 10 Fires an arrow that converts some physical damage to cold on its target and converts all physical damage to cold in a cone behind that target. 60% of Physical Damage Converted to Cold Damage Base radius is 2.4 metres Chills Enemies as though dealing (100-195)% more Damage
A32: SKILL | B32: S4 | C32: Active | D32: Lacerate | E32: Attack, AoE, Melee, Physical | F32: Physical | G32: Attack, Melee | H32: AoE, Melee | I32: Area | J32: Bleed | K32: (1-20) | L32: (10-17) Mana | R32: 12 | S32: 60% of base | T32: (171-393)% of base | U32: (171-393)% | V32: 38 | Y32: Slashes twice, releasing waves of force that damage enemies they hit. Enemies in the middle of the slashes can be hit by both. The slashes will have a chance to inflict bleeding in Blood Stance, or have a wider angle in Sand Stance. Can be used with Axes and Swords. You are in Blood Stance by default. | Z32: +(0-0.9) metres to radius (50-88)% more Damage with Bleeding while in Blood Stance 25% chance to cause Bleeding while in Blood Stance 50% increased angle while in Sand Stance | AA32: Lacerate Attack, AoE, Melee, Physical Level: (1-20) Cost: (10-17) Mana Attack Speed: 60% of base Attack Damage: (171-393)% of base Effectiveness of Added Damage: (171-393)% AoE Radius: 38 Requires Level 12 Slashes twice, releasing waves of force that damage enemies they hit. Enemies in the middle of the slashes can be hit by both. The slashes will have a chance to inflict bleeding in Blood Stance, or have a wider angle in Sand Stance. Can be used with Axes and Swords. You are in Blood Stance by default. +(0-0.9) metres to radius (50-88)% more Damage with Bleeding while in Blood Stance 25% chance to cause Bleeding while in Blood Stance 50% increased angle while in Sand Stance
A33: SKILL | B33: T4 | C33: Active | D33: Lightning Arrow | E33: Attack, AoE, Projectile, Lightning, Bow | F33: Lightning | G33: Attack, Bow | H33: AoE, Projectile, Bow | I33: Projectile, Area | J33: Shock | K33: (1-20) | L33: (6-10) Mana | R33: 12 | T33: (149-177)% of base | U33: (149-177)% | W33: 3260 | Y33: 50% of Physical Damage Converted to Lightning Damage | Z33: Fires a charged arrow which damages enemies by causing them to be struck by a bolt of lightning, which also damages a number of surrounding enemies. Hits up to 3 additional enemies near the target Shocks Enemies as though dealing (100-290)% more Damage | AA33: Lightning Arrow Attack, AoE, Projectile, Lightning, Bow Level: (1-20) Cost: (6-10) Mana Attack Damage: (149-177)% of base Effectiveness of Added Damage: (149-177)% Projectile Speed: 3260 Requires Level 12 Fires a charged arrow which damages enemies by causing them to be struck by a bolt of lightning, which also damages a number of surrounding enemies. 50% of Physical Damage Converted to Lightning Damage Hits up to 3 additional enemies near the target Shocks Enemies as though dealing (100-290)% more Damage
A34: SKILL | B34: U4 | C34: Active | D34: Lightning Strike | E34: Attack, Projectile, Melee, Strike, Lightning | F34: Lightning | G34: Attack, Melee | H34: Projectile, Melee, Strike | I34: Projectile | K34: (1-20) | L34: (6-10) Mana | R34: 12 | T34: (198-456)% of base | U34: (198-456)% | Y34: Infuses your melee weapon with electrical energies as you swing. In addition to converting some of your physical damage to lightning damage, the stored energy is released from the weapon as projectiles as you strike, flying out to hit farther-away enemies. The projectiles cannot miss if the melee attack hit a target. | Z34: 50% of Physical Damage Converted to Lightning Damage Fires 3 Projectiles Projectiles deal 50% less Damage with Hits and Ailments | AA34: Lightning Strike Attack, Projectile, Melee, Strike, Lightning Level: (1-20) Cost: (6-10) Mana Attack Damage: (198-456)% of base Effectiveness of Added Damage: (198-456)% Requires Level 12 Infuses your melee weapon with electrical energies as you swing. In addition to converting some of your physical damage to lightning damage, the stored energy is released from the weapon as projectiles as you strike, flying out to hit farther-away enemies. The projectiles cannot miss if the melee attack hit a target. 50% of Physical Damage Converted to Lightning Damage Fires 3 Projectiles Projectiles deal 50% less Damage with Hits and Ailments
A35: SKILL | B35: V4 | C35: Active | D35: Poisonous Concoction | E35: Attack, AoE, Chaos, Projectile | F35: Chaos | G35: Attack | H35: AoE, Projectile | I35: Projectile, Area | J35: Poison | K35: (1-20) | L35: (5-9) Mana | R35: 12 | S35: 115% of base | Y35: Throws a bottle that explodes to deal unarmed attack damage in an area and has a chance to poison. Can consume charges from a Life flask to add further damage. Requires an empty main hand, and no off-hand weapon. Added Chaos Damage equal to (4-16)% of Flask's Recovery Amount if Charges were consumed from a Life Flask | Z35: (22-537) to (33-806) Added Chaos Damage 40% chance to Poison on Hit +6% to Critical Strike Chance Base radius is 1.8 metres Consumes 1 Charge per Projectile Fired from 1 Life Flask, if possible | AA35: Poisonous Concoction Attack, AoE, Chaos, Projectile Level: (1-20) Cost: (5-9) Mana Attack Speed: 115% of base Requires Level 12 Throws a bottle that explodes to deal unarmed attack damage in an area and has a chance to poison. Can consume charges from a Life flask to add further damage. Requires an empty main hand, and no off-hand weapon. (22-537) to (33-806) Added Chaos Damage 40% chance to Poison on Hit +6% to Critical Strike Chance Base radius is 1.8 metres Consumes 1 Charge per Projectile Fired from 1 Life Flask, if possible Added Chaos Damage equal to (4-16)% of Flask's Recovery Amount if Charges were consumed from a Life Flask
A36: SKILL | B36: W4 | C36: Active | D36: Precision | E36: Aura, Critical, Spell, AoE | G36: Spell | H36: Aura, AoE | I36: Buff/Aura, Area | K36: (1-20) | M36: (22-186) Mana | O36: 1.20 sec | P36: 1 Use(s) | Q36: Instant | R36: 10 | Y36: Casts an aura that grants accuracy and critical strike chance to you and your allies. | Z36: +(0-1.9) metres to radius You and nearby allies gain (20-58)% increased Critical Strike Chance You and nearby allies gain +(93-701) to Accuracy Rating | AA36: Precision Aura, Critical, Spell, AoE Level: (1-20) Reservation: (22-186) Mana Cooldown Time: 1.20 sec Can Store 1 Use(s) Cast Time: Instant Requires Level 10 Casts an aura that grants accuracy and critical strike chance to you and your allies. +(0-1.9) metres to radius You and nearby allies gain (20-58)% increased Critical Strike Chance You and nearby allies gain +(93-701) to Accuracy Rating
A37: SKILL | B37: X4 | C37: Active | D37: Rain of Arrows | E37: Attack, AoE, Projectile, Bow | G37: Attack, Bow | H37: AoE, Projectile, Bow | I37: Projectile, Area | K37: (1-20) | L37: (6-10) Mana | R37: 12 | T37: (48-60)% of base | U37: (48-60)% | V37: 24 | Z37: Fires multiple arrows into the air, to land in sequence after a delay, starting at the targeted location and spreading outwards in all directions. Each arrow deals damage in an area around it. Half of the arrows will land directly on targets if there are targets in their range. Fires (18-22) Arrows | AA37: Rain of Arrows Attack, AoE, Projectile, Bow Level: (1-20) Cost: (6-10) Mana Attack Damage: (48-60)% of base Effectiveness of Added Damage: (48-60)% AoE Radius: 24 Requires Level 12 Fires multiple arrows into the air, to land in sequence after a delay, starting at the targeted location and spreading outwards in all directions. Each arrow deals damage in an area around it. Half of the arrows will land directly on targets if there are targets in their range. Fires (18-22) Arrows
A38: SKILL | B38: Y4 | C38: Active | D38: Scourge Arrow | E38: Attack, Projectile, Channelling, Chaos, Bow | F38: Chaos | G38: Attack, Bow | H38: Projectile, Channelling, Bow | I38: Projectile, Channel | K38: (1-20) | L38: (4-5) Mana | R38: 28 | S38: 190% of base | T38: (48-65)% of base | U38: (48-65)% | Y38: Channel to infuse an arrow with chaos, gaining stages while it is held. Release to fire it, leaving spore pods in its wake. Each spore pod blooms, firing thorn arrows, which travel for a short time before dissipating. Modifiers that cause additional projectiles to be fired will only apply to the initial arrows, and the spore pods will be divided between those arrows. | Z38: Arrows Pierce all Targets 60% of Physical Damage Converted to Chaos Damage 150% more Damage with Hits and Ailments per Stage Maximum 5 Stages Leaves 1 Spore Pod per Stage Each Spore Pod fires 9 Thorn Arrows Thorn Arrows deal (60-50)% less Damage | AA38: Scourge Arrow Attack, Projectile, Channelling, Chaos, Bow Level: (1-20) Cost: (4-5) Mana Attack Speed: 190% of base Attack Damage: (48-65)% of base Effectiveness of Added Damage: (48-65)% Requires Level 28 Channel to infuse an arrow with chaos, gaining stages while it is held. Release to fire it, leaving spore pods in its wake. Each spore pod blooms, firing thorn arrows, which travel for a short time before dissipating. Modifiers that cause additional projectiles to be fired will only apply to the initial arrows, and the spore pods will be divided between those arrows. Arrows Pierce all Targets 60% of Physical Damage Converted to Chaos Damage 150% more Damage with Hits and Ailments per Stage Maximum 5 Stages Leaves 1 Spore Pod per Stage Each Spore Pod fires 9 Thorn Arrows Thorn Arrows deal (60-50)% less Damage
A39: SKILL | B39: Z4 | C39: Active | D39: Tornado Shot | E39: Attack, Projectile, Bow | G39: Attack, Bow | H39: Projectile, Bow | I39: Projectile | K39: (1-20) | L39: (9-13) Mana | R39: 28 | S39: 80% of base | T39: (100-120)% of base | U39: (100-120)% | Z39: Fires a piercing shot that travels until it reaches the targeted location. It will then fire projectiles out in all directions from that point, which will travel for a short time before disappearing. Fires 3 secondary Projectiles | AA39: Tornado Shot Attack, Projectile, Bow Level: (1-20) Cost: (9-13) Mana Attack Speed: 80% of base Attack Damage: (100-120)% of base Effectiveness of Added Damage: (100-120)% Requires Level 28 Fires a piercing shot that travels until it reaches the targeted location. It will then fire projectiles out in all directions from that point, which will travel for a short time before disappearing. Fires 3 secondary Projectiles
A40: SKILL | B40: AA4 | C40: Active | D40: Toxic Rain | E40: Attack, AoE, Chaos, Duration, Projectile, Bow | F40: Chaos | G40: Attack, Bow | H40: AoE, Projectile, Bow | I40: Projectile, Area, Duration/DoT | J40: Slow | K40: (1-20) | L40: (6-10) Mana | R40: 12 | T40: (50-72)% of base | U40: (50-73)% | Y40: Fire arrows into the air that rain down around the targeted area, dealing damage to enemies they hit and creating spore pods where they land. Each spore pod deals chaos damage over time to nearby enemies and slows their movement speed. The pods last for a duration before bursting, dealing area damage. Each Spore Pod applies 5% less Movement Speed to nearby Enemies, to a maximum of 30% | Z40: Deals (8-238) Base Chaos Damage per second Base duration is 1.00 second Fires 5 Arrows Modifiers to Projectile Damage apply to this Skill's Damage Over Time effect 60% of Physical Damage Converted to Chaos Damage | AA40: Toxic Rain Attack, AoE, Chaos, Duration, Projectile, Bow Level: (1-20) Cost: (6-10) Mana Attack Damage: (50-72)% of base Effectiveness of Added Damage: (50-73)% Requires Level 12 Fire arrows into the air that rain down around the targeted area, dealing damage to enemies they hit and creating spore pods where they land. Each spore pod deals chaos damage over time to nearby enemies and slows their movement speed. The pods last for a duration before bursting, dealing area damage. Deals (8-238) Base Chaos Damage per second Base duration is 1.00 second Fires 5 Arrows Modifiers to Projectile Damage apply to this Skill's Damage Over Time effect 60% of Physical Damage Converted to Chaos Damage Each Spore Pod applies 5% less Movement Speed to nearby Enemies, to a maximum of 30%
A41: SKILL | B41: A6 | C41: Active | D41: Arc | E41: Spell, Chaining, Lightning | F41: Lightning | G41: Spell | H41: Chaining | I41: Chain | K41: (1-20) | L41: (8-23) Mana | Q41: 0.70 sec | R41: 12 | U41: 120% | Y41: Critical Strike Chance: 6.00% An arc of lightning reaches from the caster to a targeted enemy and chains to other enemies, but not immediately back. Each time the arc chains, it will also chain a secondary arc to another enemy that the main arc has not already hit, which cannot chain further. 15% more Damage with Hits and Ailments for each remaining Chain | Z41: Deals (6-198) to (32-1122) Lightning Damage Chains +(4-7) Times | AA41: Arc Spell, Chaining, Lightning Level: (1-20) Cost: (8-23) Mana Cast Time: 0.70 sec Critical Strike Chance: 6.00% Effectiveness of Added Damage: 120% Requires Level 12 An arc of lightning reaches from the caster to a targeted enemy and chains to other enemies, but not immediately back. Each time the arc chains, it will also chain a secondary arc to another enemy that the main arc has not already hit, which cannot chain further. Deals (6-198) to (32-1122) Lightning Damage Chains +(4-7) Times 15% more Damage with Hits and Ailments for each remaining Chain
A42: SKILL | B42: B6 | C42: Active | D42: Ball Lightning | E42: Spell, Projectile, AoE, Lightning | F42: Lightning | G42: Spell | H42: Projectile, AoE | I42: Projectile, Area | J42: Slow | K42: (1-20) | L42: (12-23) Mana | Q42: 0.70 sec | R42: 28 | U42: 60% | V42: 22 | W42: 400 | Y42: Critical Strike Chance: 5.00% | Z42: Fires a slow-moving projectile that damages each enemy in an area around it repeatedly with bolts of lightning. Deals (2-32) to (47-617) Lightning Damage Base radius is 1.8 metres | AA42: Ball Lightning Spell, Projectile, AoE, Lightning Level: (1-20) Cost: (12-23) Mana Cast Time: 0.70 sec Critical Strike Chance: 5.00% Effectiveness of Added Damage: 60% Projectile Speed: 400 AoE Radius: 22 Requires Level 28 Fires a slow-moving projectile that damages each enemy in an area around it repeatedly with bolts of lightning. Deals (2-32) to (47-617) Lightning Damage Base radius is 1.8 metres
A43: SKILL | B43: C6 | C43: Active | D43: Blight | E43: Spell, Chaos, AoE, Channelling, Duration | F43: Chaos | G43: Spell | H43: AoE, Channelling | I43: Area, Channel, Duration/DoT | J43: Slow | K43: (1-20) | L43: (2-5) Mana | Q43: 0.30 sec | V43: 26 | Y43: Apply a debuff to enemies in front of you which deals chaos damage over time. Enemies who aren't already debuffed by Blight are also hindered for a shorter secondary duration, slowing their movement. Continued channelling adds layers of damage to the debuff, each with their own duration. | Z43: Deals (5.9-421.5) Base Chaos Damage per second Base duration is 2.00 seconds Base secondary duration is 1.00 seconds Modifiers to Spell Damage apply to this Skill's Damage Over Time effect +(0-0.6) metres to radius 80% reduced Movement Speed Debuff can have up to 20 layers of Damage | AA43: Blight Spell, Chaos, AoE, Channelling, Duration Level: (1-20) Cost: (2-5) Mana Cast Time: 0.30 sec AoE Radius: 26 Apply a debuff to enemies in front of you which deals chaos damage over time. Enemies who aren't already debuffed by Blight are also hindered for a shorter secondary duration, slowing their movement. Continued channelling adds layers of damage to the debuff, each with their own duration. Deals (5.9-421.5) Base Chaos Damage per second Base duration is 2.00 seconds Base secondary duration is 1.00 seconds Modifiers to Spell Damage apply to this Skill's Damage Over Time effect +(0-0.6) metres to radius 80% reduced Movement Speed Debuff can have up to 20 layers of Damage
A44: SKILL | B44: D6 | C44: Active | D44: Blazing Salvo | E44: Spell, AoE, Fire, Projectile | F44: Fire | G44: Spell | H44: AoE, Projectile | I44: Projectile, Area | K44: (1-20) | L44: (8-23) Mana | Q44: 0.70 sec | R44: 12 | U44: 60% | Y44: Critical Strike Chance: 6.00% | Z44: Fires projectiles which fly in an arc, dealing area damage on impact with either enemies or the ground near where you target. Targeting farther away causes the projectiles to spread out and land over a wider area. Deals (7-270) to (10-405) Fire Damage Fires (5-7) Projectiles | AA44: Blazing Salvo Spell, AoE, Fire, Projectile Level: (1-20) Cost: (8-23) Mana Cast Time: 0.70 sec Critical Strike Chance: 6.00% Effectiveness of Added Damage: 60% Requires Level 12 Fires projectiles which fly in an arc, dealing area damage on impact with either enemies or the ground near where you target. Targeting farther away causes the projectiles to spread out and land over a wider area. Deals (7-270) to (10-405) Fire Damage Fires (5-7) Projectiles
A45: SKILL | B45: E6 | C45: Active | D45: Eye of Winter | E45: Spell, Projectile, Cold | F45: Cold | G45: Spell | H45: Projectile | I45: Projectile | K45: (1-20) | L45: (14-26) Mana | Q45: 0.80 sec | R45: 28 | U45: 55% | Y45: Critical Strike Chance: 6.00% | Z45: Fires a single eye projectile which constantly releases shard projectiles in a spiral. The shards will damage enemies they impact, dealing cold damage. The eye cannot damage enemies. When the eye dissipates or collides with terrain, it releases a faster spiral of extra shards. Deals (16-245) to (25-367) Cold Damage Modifiers to number of Projectiles only apply to the final Spiral Fires 8 Shard Projectiles in a Spiral when Projectile ends Projectiles continuously gain Damage, up to 200% more Damage by the time they dissipate | AA45: Eye of Winter Spell, Projectile, Cold Level: (1-20) Cost: (14-26) Mana Cast Time: 0.80 sec Critical Strike Chance: 6.00% Effectiveness of Added Damage: 55% Requires Level 28 Fires a single eye projectile which constantly releases shard projectiles in a spiral. The shards will damage enemies they impact, dealing cold damage. The eye cannot damage enemies. When the eye dissipates or collides with terrain, it releases a faster spiral of extra shards. Deals (16-245) to (25-367) Cold Damage Modifiers to number of Projectiles only apply to the final Spiral Fires 8 Shard Projectiles in a Spiral when Projectile ends Projectiles continuously gain Damage, up to 200% more Damage by the time they dissipate
A46: SKILL | B46: F6 | C46: Active | D46: Fireball | E46: Projectile, Spell, AoE, Fire | F46: Fire | G46: Spell | H46: Projectile, AoE | I46: Projectile, Area | J46: Ignite | K46: (1-20) | L46: (6-25) Mana | Q46: 0.75 sec | U46: (260-370)% | V46: 9 | W46: 1040 | Y46: Critical Strike Chance: 6.00% Unleashes a ball of fire towards a target which explodes, damaging nearby foes. | Z46: Deals (9-1640) to (14-2460) Fire Damage 25% chance to Ignite enemies Base radius is (0.9-1.4) metres | AA46: Fireball Projectile, Spell, AoE, Fire Level: (1-20) Cost: (6-25) Mana Cast Time: 0.75 sec Critical Strike Chance: 6.00% Effectiveness of Added Damage: (260-370)% Projectile Speed: 1040 AoE Radius: 9 Unleashes a ball of fire towards a target which explodes, damaging nearby foes. Deals (9-1640) to (14-2460) Fire Damage 25% chance to Ignite enemies Base radius is (0.9-1.4) metres
A47: SKILL | B47: G6 | C47: Active | D47: Forbidden Rite | E47: Spell, AoE, Chaos, Projectile | F47: Chaos | G47: Spell | H47: AoE, Projectile | I47: Projectile, Area | K47: (1-20) | L47: (8-21) Mana | Q47: 0.75 sec | R47: 16 | U47: 110% | Y47: Critical Strike Chance: 6.00% Lobs an exploding projectile near the targeted location, and extra projectiles toward enemies around you. The projectiles deal chaos damage based on your life and energy shield. Casting this spell damages you. | Z47: Deals (15-498) to (22-747) Chaos Damage Deals 5% of your maximum Energy Shield as base Chaos Damage Deals 12% of your maximum Life as base Chaos Damage Take 40% of maximum Life and 25% of maximum Energy Shield as Chaos Damage Fires extra Projectiles at up to (6-7) surrounding Enemies | AA47: Forbidden Rite Spell, AoE, Chaos, Projectile Level: (1-20) Cost: (8-21) Mana Cast Time: 0.75 sec Critical Strike Chance: 6.00% Effectiveness of Added Damage: 110% Requires Level 16 Lobs an exploding projectile near the targeted location, and extra projectiles toward enemies around you. The projectiles deal chaos damage based on your life and energy shield. Casting this spell damages you. Deals (15-498) to (22-747) Chaos Damage Deals 5% of your maximum Energy Shield as base Chaos Damage Deals 12% of your maximum Life as base Chaos Damage Take 40% of maximum Life and 25% of maximum Energy Shield as Chaos Damage Fires extra Projectiles at up to (6-7) surrounding Enemies
A48: SKILL | B48: H6 | C48: Active | D48: Freezing Pulse | E48: Spell, Projectile, Cold | F48: Cold | G48: Spell | H48: Projectile | I48: Projectile | J48: Freeze | K48: (1-20) | L48: (5-21) Mana | Q48: 0.65 sec | U48: (250-330)% | W48: 1800 | Y48: Critical Strike Chance: 6.00% An icy projectile which has a chance to freeze enemies it passes through. The projectile fades quickly, reducing damage and freezing chance until it dissipates. | Z48: Deals (8-1458) to (12-2188) Cold Damage Projectiles Pierce all Targets Projectiles continuously lose Damage, up to 50% less Damage by the time they dissipate Projectiles have 25% chance to Freeze, which is lost over the first quarter of their flight | AA48: Freezing Pulse Spell, Projectile, Cold Level: (1-20) Cost: (5-21) Mana Cast Time: 0.65 sec Critical Strike Chance: 6.00% Effectiveness of Added Damage: (250-330)% Projectile Speed: 1800 An icy projectile which has a chance to freeze enemies it passes through. The projectile fades quickly, reducing damage and freezing chance until it dissipates. Deals (8-1458) to (12-2188) Cold Damage Projectiles Pierce all Targets Projectiles continuously lose Damage, up to 50% less Damage by the time they dissipate Projectiles have 25% chance to Freeze, which is lost over the first quarter of their flight
A49: SKILL | B49: I6 | C49: Active | D49: Herald of Thunder | E49: Spell, AoE, Duration, Lightning, Herald | F49: Lightning | G49: Spell | H49: AoE, Herald | I49: Buff/Aura, Area, Duration/DoT | J49: Shock | K49: (1-20) | M49: 25% Mana | O49: 1.00 sec | P49: 1 Use(s) | Q49: Instant | R49: 16 | V49: 32 | Y49: Storm Hits an Enemy every 0.25 Seconds | Z49: Grants a buff which adds lightning damage to spells and attacks. If you kill a shocked enemy, this skill will create a storm, causing lightning bolts to strike enemies around you for a duration. The damage inflicted by this skill is not affected by modifiers to spell damage. Deals (1-23) to (31-1108) Lightning Damage Cannot inflict Shock Base duration is 6.00 seconds Creates a storm when you Kill a Shocked Enemy Buff grants (2-19) to (7-76) Added Attack Lightning Damage Buff grants (2-19) to (7-76) Added Spell Lightning Damage | AA49: Herald of Thunder Spell, AoE, Duration, Lightning, Herald Level: (1-20) Reservation: 25% Mana Cooldown Time: 1.00 sec Can Store 1 Use(s) Cast Time: Instant AoE Radius: 32 Requires Level 16 Grants a buff which adds lightning damage to spells and attacks. If you kill a shocked enemy, this skill will create a storm, causing lightning bolts to strike enemies around you for a duration. The damage inflicted by this skill is not affected by modifiers to spell damage. Deals (1-23) to (31-1108) Lightning Damage Cannot inflict Shock Base duration is 6.00 seconds Storm Hits an Enemy every 0.25 Seconds Creates a storm when you Kill a Shocked Enemy Buff grants (2-19) to (7-76) Added Attack Lightning Damage Buff grants (2-19) to (7-76) Added Spell Lightning Damage
A50: SKILL | B50: J6 | C50: Active | D50: Kinetic Blast | E50: Attack, Projectile, AoE | G50: Attack | H50: Projectile, AoE | I50: Projectile, Area | K50: (1-20) | L50: (6-9) Mana | R50: 28 | S50: 115% of base | T50: (140-155)% of base | U50: (140-155)% | V50: 14 | Y50: Kinetic Blast creates 4 additional explosions Increases and Reductions to Spell Damage also apply to Attack Damage from this Skill at 200% of their value | Z50: Fires a projectile from a Wand that causes a series of area explosions in a secondary radius around its point of impact, each damaging enemies. 35% less Area Damage Base explosion radius is 1.4 metres Base secondary radius is 2 metres | AA50: Kinetic Blast Attack, Projectile, AoE Level: (1-20) Cost: (6-9) Mana Attack Speed: 115% of base Attack Damage: (140-155)% of base Effectiveness of Added Damage: (140-155)% AoE Radius: 14 Requires Level 28 Fires a projectile from a Wand that causes a series of area explosions in a secondary radius around its point of impact, each damaging enemies. Kinetic Blast creates 4 additional explosions Increases and Reductions to Spell Damage also apply to Attack Damage from this Skill at 200% of their value 35% less Area Damage Base explosion radius is 1.4 metres Base secondary radius is 2 metres
A51: SKILL | B51: K6 | C51: Active | D51: Kinetic Rain | E51: Attack, AoE, Projectile, Duration, Trigger | G51: Attack | H51: AoE, Projectile, Trigger | I51: Projectile, Area, Duration/DoT | K51: (1-20) | L51: (7-10) Mana | R51: 28 | T51: (20-25)% of base | U51: (20-25)% | Y51: Swing your wand to cause a number of projectiles to rain down within a large area in front of you, directly targeting the locations of enemies in the area. The locations where each projectile will land are shown with markers before they fall. Each projectile explodes when hitting the ground, dealing area damage and triggering Kinetic Anomaly. Cannot be used by Totems, Traps, or Mines. Increases and Reductions to Spell Damage also apply to Attack Damage from this Skill at 150% of their value Increases and Reductions to Spell Damage also apply to Attack Damage from this Skill at 150% of their value This Skill is Triggered when Projectiles from Kinetic Rain explode | Z51: Fires 8 Projectiles Base targeting area length is 9 metres Base targeting area width is 4.5 metres Base explosion radius is 1.2 metres Base duration is 6.00 seconds Base explosion radius is 1.2 metres Maximum 30 Anomalies | AA51: Kinetic Rain Attack, AoE, Projectile, Duration, Trigger Level: (1-20) Cost: (7-10) Mana Attack Damage: (20-25)% of base Effectiveness of Added Damage: (20-25)% Requires Level 28 Swing your wand to cause a number of projectiles to rain down within a large area in front of you, directly targeting the locations of enemies in the area. The locations where each projectile will land are shown with markers before they fall. Each projectile explodes when hitting the ground, dealing area damage and triggering Kinetic Anomaly. Cannot be used by Totems, Traps, or Mines. Increases and Reductions to Spell Damage also apply to Attack Damage from this Skill at 150% of their value Fires 8 Projectiles Base targeting area length is 9 metres Base targeting area width is 4.5 metres Base explosion radius is 1.2 metres Increases and Reductions to Spell Damage also apply to Attack Damage from this Skill at 150% of their value Base duration is 6.00 seconds Base explosion radius is 1.2 metres Maximum 30 Anomalies This Skill is Triggered when Projectiles from Kinetic Rain explode
A52: SKILL | B52: L6 | C52: Active | D52: Orb of Storms | E52: Lightning, Spell, AoE, Chaining, Orb | F52: Lightning | G52: Spell | H52: AoE, Chaining, Orb | I52: Area, Chain | K52: (1-20) | L52: (22-16) Mana | O52: 0.50 sec | P52: 1 Use(s) | Q52: 0.50 sec | R52: 4 | U52: (80-110)% | Y52: Critical Strike Chance: 5.00% Creates a stationary electrical orb that strikes enemies in its area of effect with beams of lightning that can then split to hit more enemies. Modifiers to cast speed will increase how frequently it does this. Casting this skill again will replace the previous orb. Strikes every (3.50-2.55) seconds, and when you use a Lightning Skill near the Orb Strikes every 0.50 seconds while Channelling a Lightning Skill near the Orb Beams Split towards targets within a base radius of 3.5 metres | Z52: Deals (3-304) to (8-913) Lightning Damage Base radius is 2.8 metres Beam Splits towards 3 additional targets Orb disappears after (10-29) Strikes | AA52: Orb of Storms Lightning, Spell, AoE, Chaining, Orb Level: (1-20) Cost: (22-16) Mana Cooldown Time: 0.50 sec Can Store 1 Use(s) Cast Time: 0.50 sec Critical Strike Chance: 5.00% Effectiveness of Added Damage: (80-110)% Requires Level 4 Creates a stationary electrical orb that strikes enemies in its area of effect with beams of lightning that can then split to hit more enemies. Modifiers to cast speed will increase how frequently it does this. Casting this skill again will replace the previous orb. Deals (3-304) to (8-913) Lightning Damage Strikes every (3.50-2.55) seconds, and when you use a Lightning Skill near the Orb Strikes every 0.50 seconds while Channelling a Lightning Skill near the Orb Base radius is 2.8 metres Beams Split towards targets within a base radius of 3.5 metres Beam Splits towards 3 additional targets Orb disappears after (10-29) Strikes
A53: SKILL | B53: M6 | C53: Active | D53: Raise Zombie | E53: Spell, Minion | G53: Spell, Minion | H53: Minion | I53: Summon | K53: (1-20) | L53: (9-28) Mana | Q53: 0.85 sec | Y53: Raises a zombie minion from a corpse, which will follow you and attack enemies with a melee strike. | Z53: Maximum (3-6) Raised Zombies Minions have (0-38)% more Maximum Life | AA53: Raise Zombie Spell, Minion Level: (1-20) Cost: (9-28) Mana Cast Time: 0.85 sec Raises a zombie minion from a corpse, which will follow you and attack enemies with a melee strike. Maximum (3-6) Raised Zombies Minions have (0-38)% more Maximum Life
A54: SKILL | B54: N6 | C54: Active | D54: Righteous Fire | E54: Spell, AoE, Fire | F54: Fire | G54: Spell | H54: AoE | I54: Area | K54: (1-20) | O54: 0.30 sec | P54: 1 Use(s) | Q54: Instant | R54: 16 | Y54: Engulfs you in magical fire that rapidly burns you and nearby enemies. Your spell damage is substantially increased while under this effect. The effect ends when you have 1 life remaining. | Z54: Deals 70% of your Maximum Life as Base Fire Damage per second Deals 70% of your Maximum Energy Shield as Base Fire Damage per second You Burn for 90% of your Maximum Life per second as Fire Damage You Burn for 70% of your Maximum Energy Shield per second as Fire Damage Grants (20-39)% more Spell Damage Base radius is (1.8-2.3) metres | AA54: Righteous Fire Spell, AoE, Fire Level: (1-20) Cooldown Time: 0.30 sec Can Store 1 Use(s) Cast Time: Instant Requires Level 16 Engulfs you in magical fire that rapidly burns you and nearby enemies. Your spell damage is substantially increased while under this effect. The effect ends when you have 1 life remaining. Deals 70% of your Maximum Life as Base Fire Damage per second Deals 70% of your Maximum Energy Shield as Base Fire Damage per second You Burn for 90% of your Maximum Life per second as Fire Damage You Burn for 70% of your Maximum Energy Shield per second as Fire Damage Grants (20-39)% more Spell Damage Base radius is (1.8-2.3) metres
A55: SKILL | B55: O6 | C55: Active | D55: Summon Carrion Golem | E55: Physical, Minion, Spell, Golem | F55: Physical | G55: Spell, Minion | H55: Minion | I55: Summon | K55: (1-20) | L55: (30-54) Mana | O55: 6.00 sec | P55: 1 Use(s) | Q55: 1.00 sec | R55: 34 | Y55: Golems deal 5% more Damage per Non-Golem Minion near them, up to 50% Golems grant (7-27) to (11-41) additional Physical Damage for Non-Golem Minions | Z55: Summons a Carrion Golem that grants added physical damage for your non-golem minions. The Carrion Golem attacks with a series of slashes that increase in speed and damage, as well as a cascade of bone spikes, and deals more damage for each of your non-golem minions near it. Maximum 1 Summoned Golem | AA55: Summon Carrion Golem Physical, Minion, Spell, Golem Level: (1-20) Cost: (30-54) Mana Cooldown Time: 6.00 sec Can Store 1 Use(s) Cast Time: 1.00 sec Requires Level 34 Summons a Carrion Golem that grants added physical damage for your non-golem minions. The Carrion Golem attacks with a series of slashes that increase in speed and damage, as well as a cascade of bone spikes, and deals more damage for each of your non-golem minions near it. Maximum 1 Summoned Golem Golems deal 5% more Damage per Non-Golem Minion near them, up to 50% Golems grant (7-27) to (11-41) additional Physical Damage for Non-Golem Minions
A56: SKILL | B56: P6 | C56: Active | D56: Vortex | E56: Spell, AoE, Cold, Duration, Nova | F56: Cold | G56: Spell | H56: AoE, Nova | I56: Area, Duration/DoT | J56: Chill | K56: (1-20) | L56: (13-25) Mana | Q56: 0.75 sec | R56: 28 | U56: (130-210)% | V56: 2 | Y56: Critical Strike Chance: 6.00% An icy blast explodes around the caster, dealing cold damage to enemies, and leaving behind a whirling vortex which deals cold damage over time and chills enemies caught in it. | Z56: Deals (48-933) to (72-1399) Cold Damage Base duration is 3.00 seconds Deals (115.6-2772.8) Base Cold Damage per second Modifiers to Spell Damage apply to this Skill's Damage Over Time effect Base radius is 2 metres Base secondary radius is 2 metres | AA56: Vortex Spell, AoE, Cold, Duration, Nova Level: (1-20) Cost: (13-25) Mana Cast Time: 0.75 sec Critical Strike Chance: 6.00% Effectiveness of Added Damage: (130-210)% AoE Radius: 2 Requires Level 28 An icy blast explodes around the caster, dealing cold damage to enemies, and leaving behind a whirling vortex which deals cold damage over time and chills enemies caught in it. Deals (48-933) to (72-1399) Cold Damage Base duration is 3.00 seconds Deals (115.6-2772.8) Base Cold Damage per second Modifiers to Spell Damage apply to this Skill's Damage Over Time effect Base radius is 2 metres Base secondary radius is 2 metres

Sheet PARSED_SUPPORT
A1: SourceSheet | B1: SourceCell | C1: GemType | D1: Name | E1: Tags | F1: DamageType | G1: Scaling | H1: MechanicTags | I1: CombatRole | J1: AilmentKeywords | K1: Level | L1: Cost | M1: Reservation | N1: CostReservationMultiplier | O1: CooldownTime | P1: CanStoreUses | Q1: CastTime | R1: RequiresLevel | S1: AttackSpeed | T1: AttackDamage | U1: EffectivenessAddedDamage | V1: AoERadius | W1: ProjectileSpeed | X1: Icon | Y1: Description | Z1: ModifierLines | AA1: RawText
A2: SUPPORT | B2: A1 | C2: Support | D2: Added Fire Damage Support | E2: Fire, Physical, Support | F2: Fire, Physical | I2: Direct | K2: (1-20) | N2: 120% | R2: 8 | X2: F | Y2: Supports any skill that hits enemies. | Z2: Supported Skills gain (25-39)% of Physical Damage as Extra Fire Damage | AA2: Added Fire Damage Support Fire, Physical, Support Icon: F Level: (1-20) Cost & Reservation Multiplier: 120% Requires Level 8 Supports any skill that hits enemies. Supported Skills gain (25-39)% of Physical Damage as Extra Fire Damage
A3: SUPPORT | B3: B1 | C3: Support | D3: Brutality Support | E3: Physical, Support | F3: Physical | I3: Direct | K3: (1-20) | N3: 140% | R3: 38 | X3: U | Y3: Supports any skill that deals damage. | Z3: Supported Skills deal (25-39)% more Physical Damage Supported Skills deal no Chaos Damage Supported Skills deal no Elemental Damage | AA3: Brutality Support Physical, Support Icon: U Level: (1-20) Cost & Reservation Multiplier: 140% Requires Level 38 Supports any skill that deals damage. Supported Skills deal (25-39)% more Physical Damage Supported Skills deal no Chaos Damage Supported Skills deal no Elemental Damage
A4: SUPPORT | B4: C1 | C4: Support | D4: Burning Damage Support | E4: Fire, Support | F4: Fire | I4: Direct | K4: (1-20) | N4: 130% | R4: 31 | X4: b | Y4: Supports any skill that hits enemies, or can deal burning damage directly. | Z4: Supported Skills deal (20-34)% more Burning Damage | AA4: Burning Damage Support Fire, Support Icon: b Level: (1-20) Cost & Reservation Multiplier: 130% Requires Level 31 Supports any skill that hits enemies, or can deal burning damage directly. Supported Skills deal (20-34)% more Burning Damage
A5: SUPPORT | B5: D1 | C5: Support | D5: Chance to Bleed Support | E5: Attack, Physical, Support | F5: Physical | G5: Attack | I5: Direct | J5: Bleed | K5: (1-20) | N5: 120% | X5: E | Y5: Supports attack skills. | Z5: Supported Attacks have 25% chance to cause Bleeding Supported Attacks deal (10-29)% more Damage with Bleeding | AA5: Chance to Bleed Support Attack, Physical, Support Icon: E Level: (1-20) Cost & Reservation Multiplier: 120% Supports attack skills. Supported Attacks have 25% chance to cause Bleeding Supported Attacks deal (10-29)% more Damage with Bleeding
A6: SUPPORT | B6: E1 | C6: Support | D6: Cold to Fire Support | E6: Cold, Fire, Support | F6: Cold, Fire | I6: Direct | K6: (1-20) | N6: 120% | R6: 18 | X6: x | Y6: Supports any skill that hits enemies. | Z6: Supported Skills gain (10-29)% of Cold Damage as Extra Fire Damage Supported Skills have 50% of Cold Damage Converted to Fire Damage | AA6: Cold to Fire Support Cold, Fire, Support Icon: x Level: (1-20) Cost & Reservation Multiplier: 120% Requires Level 18 Supports any skill that hits enemies. Supported Skills gain (10-29)% of Cold Damage as Extra Fire Damage Supported Skills have 50% of Cold Damage Converted to Fire Damage
A7: SUPPORT | B7: F1 | C7: Support | D7: Cruelty Support | E7: Support, Duration | I7: Duration/DoT | K7: (1-20) | N7: 140% | R7: 18 | X7: Y | Y7: Supports any skill that hits enemies. Minions cannot gain Cruelty. (0-19)% increased Effect of Cruelty granted by Supported Skills | Z7: Supported Skills deal (15-24)% more Damage with Hits Cruelty has a Base Duration of 4 seconds Hits from Supported Skills grant Cruelty | AA7: Cruelty Support Support, Duration Icon: Y Level: (1-20) Cost & Reservation Multiplier: 140% Requires Level 18 Supports any skill that hits enemies. Minions cannot gain Cruelty. Supported Skills deal (15-24)% more Damage with Hits Cruelty has a Base Duration of 4 seconds Hits from Supported Skills grant Cruelty (0-19)% increased Effect of Cruelty granted by Supported Skills
A8: SUPPORT | B8: G1 | C8: Support | D8: Elemental Damage with Attacks Support | E8: Attack, Support | G8: Attack | I8: Direct | K8: (1-20) | N8: 130% | R8: 18 | X8: W | Y8: Supports attack skills. | Z8: Supported Attack Skills deal (20-34)% more Elemental Damage | AA8: Elemental Damage with Attacks Support Attack, Support Icon: W Level: (1-20) Cost & Reservation Multiplier: 130% Requires Level 18 Supports attack skills. Supported Attack Skills deal (20-34)% more Elemental Damage
A9: SUPPORT | B9: H1 | C9: Support | D9: Endurance Charge on Melee Stun Support | E9: Support, Melee, Attack | G9: Attack, Melee | H9: Melee | I9: Direct | J9: Stun | K9: (1-20) | N9: 120% | R9: 18 | X9: e | Y9: Supports melee attack skills. Gain an Endurance Charge when you Stun an Enemy with a Melee Hit from Supported Skills | Z9: 4% more Damage per Endurance Charge Supported Skills have (0-19)% reduced Enemy Stun Threshold | AA9: Endurance Charge on Melee Stun Support Support, Melee, Attack Icon: e Level: (1-20) Cost & Reservation Multiplier: 120% Requires Level 18 Supports melee attack skills. 4% more Damage per Endurance Charge Supported Skills have (0-19)% reduced Enemy Stun Threshold Gain an Endurance Charge when you Stun an Enemy with a Melee Hit from Supported Skills
A10: SUPPORT | B10: I1 | C10: Support | D10: Fire Penetration Support | E10: Fire, Support | F10: Fire | I10: Direct | K10: (1-20) | N10: 130% | R10: 31 | X10: V | Y10: Supports any skill that hits enemies, making those hits penetrate enemy fire resistance. | Z10: Supported Skills Penetrate (20-34)% Fire Resistance | AA10: Fire Penetration Support Fire, Support Icon: V Level: (1-20) Cost & Reservation Multiplier: 130% Requires Level 31 Supports any skill that hits enemies, making those hits penetrate enemy fire resistance. Supported Skills Penetrate (20-34)% Fire Resistance
A11: SUPPORT | B11: J1 | C11: Support | D11: Less Duration Support | E11: Support, Duration | I11: Duration/DoT | K11: (1-20) | N11: 130% | R11: 31 | X11: d | Y11: Supports any skill that has a duration. | Z11: Supported Skills deal (10-19)% more Damage Supported Skills have (40-49)% less Skill Effect Duration | AA11: Less Duration Support Support, Duration Icon: d Level: (1-20) Cost & Reservation Multiplier: 130% Requires Level 31 Supports any skill that has a duration. Supported Skills deal (10-19)% more Damage Supported Skills have (40-49)% less Skill Effect Duration
A12: SUPPORT | B12: K1 | C12: Support | D12: Maim Support | E12: Attack, Physical, Support | F12: Physical | G12: Attack | I12: Direct | J12: Maim | K12: (1-20) | N12: 130% | R12: 8 | X12: m | Y12: Supports attack skills, or other skills that can maim enemies. | Z12: Supported Skills deal (10-19)% more Physical Damage Supported Attacks have 30% chance to Maim on Hit Enemies Maimed by Supported Skills take 10% increased Physical Damage | AA12: Maim Support Attack, Physical, Support Icon: m Level: (1-20) Cost & Reservation Multiplier: 130% Requires Level 8 Supports attack skills, or other skills that can maim enemies. Supported Skills deal (10-19)% more Physical Damage Supported Attacks have 30% chance to Maim on Hit Enemies Maimed by Supported Skills take 10% increased Physical Damage
A13: SUPPORT | B13: L1 | C13: Support | D13: Melee Physical Damage Support | E13: Melee, Physical, Support, Attack | F13: Physical | G13: Attack, Melee | H13: Melee | I13: Direct | J13: Poison, Bleed | K13: (1-20) | N13: 130% | R13: 18 | X13: M | Y13: Supports melee attack skills. | Z13: Supported Skills deal (30-49)% more Melee Physical Damage Supported Skills deal (30-49)% more Damage with Bleeding and Poison caused by Melee Hits Supported Skills have 10% less Attack Speed | AA13: Melee Physical Damage Support Melee, Physical, Support, Attack Icon: M Level: (1-20) Cost & Reservation Multiplier: 130% Requires Level 18 Supports melee attack skills. Supported Skills deal (30-49)% more Melee Physical Damage Supported Skills deal (30-49)% more Damage with Bleeding and Poison caused by Melee Hits Supported Skills have 10% less Attack Speed
A14: SUPPORT | B14: M1 | C14: Support | D14: More Duration Support | E14: Support, Duration | I14: Duration/DoT | K14: (1-20) | N14: 130% | R14: 31 | X14: D | Y14: Supports any skill with a duration. | Z14: Supported Skills have (30-39)% more Skill Effect Duration | AA14: More Duration Support Support, Duration Icon: D Level: (1-20) Cost & Reservation Multiplier: 130% Requires Level 31 Supports any skill with a duration. Supported Skills have (30-39)% more Skill Effect Duration
A15: SUPPORT | B15: N1 | C15: Support | D15: Multistrike Support | E15: Attack, Melee, Support | G15: Attack, Melee | H15: Melee | I15: Direct | K15: (1-20) | N15: 150% | R15: 38 | X15: 3 | Y15: Supports melee attack skills, making them repeat twice when used, targeting a random enemy each time. Cannot support Vaal skills, channelling skills, travel skills, retaliation skills or triggered skills. | Z15: Supported Skills Repeat 2 additional times Supported Skills have (35-44)% more Melee Attack Speed Supported Skills deal (30-20)% less Attack Damage First Repeat of Supported Skills deals 22% more Damage Second Repeat of Supported Skills deals 44% more Damage | AA15: Multistrike Support Attack, Melee, Support Icon: 3 Level: (1-20) Cost & Reservation Multiplier: 150% Requires Level 38 Supports melee attack skills, making them repeat twice when used, targeting a random enemy each time. Cannot support Vaal skills, channelling skills, travel skills, retaliation skills or triggered skills. Supported Skills Repeat 2 additional times Supported Skills have (35-44)% more Melee Attack Speed Supported Skills deal (30-20)% less Attack Damage First Repeat of Supported Skills deals 22% more Damage Second Repeat of Supported Skills deals 44% more Damage
A16: SUPPORT | B16: O1 | C16: Support | D16: Pulverise Support | E16: AoE, Support, Melee, Attack | G16: Attack, Melee | H16: AoE, Melee | I16: Area | K16: (1-20) | N16: 130% | R16: 31 | X16: P | Y16: Supports melee attack skills. | Z16: Supported Skills have (25-34)% increased Area of Effect Supported Skills have 15% less Attack Speed Supported Skills deal (35-49)% more Melee Area Damage | AA16: Pulverise Support AoE, Support, Melee, Attack Icon: P Level: (1-20) Cost & Reservation Multiplier: 130% Requires Level 31 Supports melee attack skills. Supported Skills have (25-34)% increased Area of Effect Supported Skills have 15% less Attack Speed Supported Skills deal (35-49)% more Melee Area Damage
A17: SUPPORT | B17: P1 | C17: Support | D17: Ruthless Support | E17: Slam, Support, Melee, Attack, Strike | G17: Attack, Melee | H17: Slam, Melee, Strike | I17: Duration/DoT | J17: Stun | K17: (1-20) | N17: 120% | X17: u | Y17: Supports melee strike or slam skills. Every third time you use a supported attack, that use of the skill will be more powerful. Ruthless Blows with Supported Skills deal (70-98)% more Melee Damage Ruthless Blows with Supported Skills deal (70-98)% more Damage with Ruthless Blows with Supported Skills have a base Stun Duration of 0.8 seconds | Z17: Every third Attack with Supported Melee Attacks deals a Ruthless Blow Ailments caused by Melee Hits | AA17: Ruthless Support Slam, Support, Melee, Attack, Strike Icon: u Level: (1-20) Cost & Reservation Multiplier: 120% Supports melee strike or slam skills. Every third time you use a supported attack, that use of the skill will be more powerful. Every third Attack with Supported Melee Attacks deals a Ruthless Blow Ruthless Blows with Supported Skills deal (70-98)% more Melee Damage Ruthless Blows with Supported Skills deal (70-98)% more Damage with Ailments caused by Melee Hits Ruthless Blows with Supported Skills have a base Stun Duration of 0.8 seconds
A18: SUPPORT | B18: Q1 | C18: Support | D18: Shockwave Support | E18: Support, Melee, Attack, AoE | G18: Attack, Melee | H18: Melee, AoE | I18: Area | J18: Shock | K18: (1-20) | N18: 140% | O18: 1.00 sec | P18: (1-4) Use(s) | R18: 18 | X18: s | Y18: Supports melee attack skills. Cannot support triggered attacks, attacks used by things other than you, or skills which create minions. | Z18: Supported Skills will Trigger Shockwave on Melee Hit Supported Skills can only be used with Maces, Sceptres or Staves Base radius is (2.4-2.7) metres (0-38)% increased Cooldown Recovery Rate | AA18: Shockwave Support Support, Melee, Attack, AoE Icon: s Level: (1-20) Cost & Reservation Multiplier: 140% Cooldown Time: 1.00 sec Can Store (1-4) Use(s) Requires Level 18 Supports melee attack skills. Cannot support triggered attacks, attacks used by things other than you, or skills which create minions. Supported Skills will Trigger Shockwave on Melee Hit Supported Skills can only be used with Maces, Sceptres or Staves Base radius is (2.4-2.7) metres (0-38)% increased Cooldown Recovery Rate
A19: SUPPORT | B19: R1 | C19: Support | D19: Stun Support | E19: Support | I19: Direct | J19: Stun | K19: (1-20) | R19: 8 | X19: t | Y19: Supports any skill that hits enemies, making it easier to stun enemies with those skills. | Z19: Supported Skills have (30-49)% reduced Enemy Stun Threshold | AA19: Stun Support Support Icon: t Level: (1-20) Requires Level 8 Supports any skill that hits enemies, making it easier to stun enemies with those skills. Supported Skills have (30-49)% reduced Enemy Stun Threshold
A20: SUPPORT | B20: A3 | C20: Support | D20: Added Cold Damage Support | E20: Cold, Support | F20: Cold | I20: Direct | K20: (1-20) | N20: 120% | R20: 8 | X20: C | Y20: Supports any skill that hits enemies. | Z20: Supported Skills have (4-152) to (6-228) added Cold Damag | AA20: Added Cold Damage Support Cold, Support Icon: C Level: (1-20) Cost & Reservation Multiplier: 120% Requires Level 8 Supports any skill that hits enemies. Supported Skills have (4-152) to (6-228) added Cold Damag
A21: SUPPORT | B21: B3 | C21: Support | D21: Additional Accuracy Support | E21: Attack, Support | G21: Attack | I21: Direct | K21: (1-20) | N21: 110% | R21: 8 | X21: a | Y21: Supports attack skills. | Z21: Supported Skills have +(74-1034) to Accuracy Rating | AA21: Additional Accuracy Support Attack, Support Icon: a Level: (1-20) Cost & Reservation Multiplier: 110% Requires Level 8 Supports attack skills. Supported Skills have +(74-1034) to Accuracy Rating
A22: SUPPORT | B22: C3 | C22: Support | D22: Barrage Support | E22: Bow, Attack, Support, Projectile | G22: Attack, Bow | H22: Bow, Projectile | I22: Projectile | K22: (1-20) | N22: 150% | R22: 38 | X22: N | Y22: Supports projectile attack skills that use bows or wands. Cannot support triggered skills, channelled skills, or skills that create Minions. | Z22: Supported Skills deal (68-62)% less Damage Supported Skills Fire Projectiles sequentially Supported Skills fire 3 additional Projectiles Supported Skills have 5% more Attack Time per Projectile Supported Skills have 5% more Trap and Mine Throwing Time per Projectile Supported Skills can only be used with Bows or Wands | AA22: Barrage Support Bow, Attack, Support, Projectile Icon: N Level: (1-20) Cost & Reservation Multiplier: 150% Requires Level 38 Supports projectile attack skills that use bows or wands. Cannot support triggered skills, channelled skills, or skills that create Minions. Supported Skills deal (68-62)% less Damage Supported Skills Fire Projectiles sequentially Supported Skills fire 3 additional Projectiles Supported Skills have 5% more Attack Time per Projectile Supported Skills have 5% more Trap and Mine Throwing Time per Projectile Supported Skills can only be used with Bows or Wands
A23: SUPPORT | B23: D3 | C23: Support | D23: Chain Support | E23: Support, Chaining, Projectile | H23: Chaining, Projectile | I23: Projectile, Chain | K23: (1-20) | N23: 140% | R23: 38 | X23: c | Y23: Supports projectile skills, and any other skills that chain. | Z23: Supported Skills Chain +2 times Supported Skills deal (30-11)% less Damage with Hits | AA23: Chain Support Support, Chaining, Projectile Icon: c Level: (1-20) Cost & Reservation Multiplier: 140% Requires Level 38 Supports projectile skills, and any other skills that chain. Supported Skills Chain +2 times Supported Skills deal (30-11)% less Damage with Hits
A24: SUPPORT | B24: E3 | C24: Support | D24: Chance to Poison Support | E24: Chaos, Support | F24: Chaos | I24: Direct | J24: Poison | K24: (1-20) | N24: 120% | X24: O | Y24: Supports any skill that hits enemies. | Z24: Supported Skills have 40% chance to Poison on Hit Supported Skills have (1-94) to (2-141) added Chaos Damage | AA24: Chance to Poison Support Chaos, Support Icon: O Level: (1-20) Cost & Reservation Multiplier: 120% Supports any skill that hits enemies. Supported Skills have 40% chance to Poison on Hit Supported Skills have (1-94) to (2-141) added Chaos Damage
A25: SUPPORT | B25: F3 | C25: Support | D25: Cold Penetration Support | E25: Cold, Support | F25: Cold | I25: Direct | K25: (1-20) | N25: 130% | R25: 31 | X25: V | Y25: Supports any skill that hits enemies, making those hits penetrate enemy cold resistance. | Z25: Supported Skills Penetrate (20-34)% Cold Resistance | AA25: Cold Penetration Support Cold, Support Icon: V Level: (1-20) Cost & Reservation Multiplier: 130% Requires Level 31 Supports any skill that hits enemies, making those hits penetrate enemy cold resistance. Supported Skills Penetrate (20-34)% Cold Resistance
A26: SUPPORT | B26: G3 | C26: Support | D26: Critical Strike Affliction Support | E26: Critical, Support | I26: Direct | K26: (1-20) | N26: 130% | R26: 31 | X26: o | Y26: Supports any skill that hits enemies. | Z26: Supported Skills have +(70-98)% Damage over Time Multiplier for Ailments from Critical Strikes | AA26: Critical Strike Affliction Support Critical, Support Icon: o Level: (1-20) Cost & Reservation Multiplier: 130% Requires Level 31 Supports any skill that hits enemies. Supported Skills have +(70-98)% Damage over Time Multiplier for Ailments from Critical Strikes
A27: SUPPORT | B27: H3 | C27: Support | D27: Culling Strike Support | E27: Support | I27: Direct | K27: (1-20) | N27: 110% | R27: 18 | X27: X | Y27: Supports any skill that hits enemies. If enemies are left below 10% of maximum life after being hit by these skills, they will be killed. Kill Enemies that have 10% Life or lower when Hit by Supported Skills | Z27: Supported Skills deal (0-38)% increased Damage | AA27: Culling Strike Support Support Icon: X Level: (1-20) Cost & Reservation Multiplier: 110% Requires Level 18 Supports any skill that hits enemies. If enemies are left below 10% of maximum life after being hit by these skills, they will be killed. Kill Enemies that have 10% Life or lower when Hit by Supported Skills Supported Skills deal (0-38)% increased Damage
A28: SUPPORT | B28: I3 | C28: Support | D28: Deadly Ailments Support | E28: Support | I28: Direct | K28: (1-20) | N28: 140% | R28: 18 | X28: i | Y28: Supports any skill that hits enemies. | Z28: Supported Skills deal (30-44)% more Damage with Ailments Supported Skills deal 80% less Damage with Hits | AA28: Deadly Ailments Support Support Icon: i Level: (1-20) Cost & Reservation Multiplier: 140% Requires Level 18 Supports any skill that hits enemies. Supported Skills deal (30-44)% more Damage with Ailments Supported Skills deal 80% less Damage with Hits
A29: SUPPORT | B29: J3 | C29: Support | D29: Faster Attacks Support | E29: Attack, Support | G29: Attack | I29: Direct | K29: (1-20) | N29: 110% | R29: 8 | X29: A | Y29: Supports attack skills. | Z29: Supported Skills have (20-44)% increased Attack Speed | AA29: Faster Attacks Support Attack, Support Icon: A Level: (1-20) Cost & Reservation Multiplier: 110% Requires Level 8 Supports attack skills. Supported Skills have (20-44)% increased Attack Speed
A30: SUPPORT | B30: K3 | C30: Support | D30: Faster Projectiles Support | E30: Support, Projectile | H30: Projectile | I30: Projectile | K30: (1-20) | N30: 120% | R30: 31 | X30: j | Y30: Supports projectile skills. | Z30: Supported Skills have (50-69)% increased Projectile Speed Supported Skills deal (20-29)% increased Projectile Damage | AA30: Faster Projectiles Support Support, Projectile Icon: j Level: (1-20) Cost & Reservation Multiplier: 120% Requires Level 31 Supports projectile skills. Supported Skills have (50-69)% increased Projectile Speed Supported Skills deal (20-29)% increased Projectile Damage
A31: SUPPORT | B31: L3 | C31: Support | D31: Fork Support | E31: Support, Projectile | H31: Projectile | I31: Projectile | K31: (1-20) | N31: 130% | R31: 31 | X31: Y | Y31: Supports projectile skills, making their projectiles fork into two projectiles the first time they hit an enemy and don't pierce it. | Z31: Projectiles from Supported Skills Fork Supported Skills deal (-10-9)% more Projectile Damage | AA31: Fork Support Support, Projectile Icon: Y Level: (1-20) Cost & Reservation Multiplier: 130% Requires Level 31 Supports projectile skills, making their projectiles fork into two projectiles the first time they hit an enemy and don't pierce it. Projectiles from Supported Skills Fork Supported Skills deal (-10-9)% more Projectile Damage
A32: SUPPORT | B32: M3 | C32: Support | D32: Greater Multiple Projectiles Support | E32: Support, Projectile | H32: Projectile | I32: Projectile | K32: (1-20) | N32: 150% | R32: 38 | X32: P | Y32: Supports projectile skills. | Z32: Supported Skills deal (35-26)% less Projectile Damage Supported Skills fire 4 additional Projectiles | AA32: Greater Multiple Projectiles Support Support, Projectile Icon: P Level: (1-20) Cost & Reservation Multiplier: 150% Requires Level 38 Supports projectile skills. Supported Skills deal (35-26)% less Projectile Damage Supported Skills fire 4 additional Projectiles
A33: SUPPORT | B33: N3 | C33: Support | D33: Greater Volley Support | E33: Support, Projectile | H33: Projectile | I33: Projectile | K33: (1-20) | N33: 150% | R33: 38 | X33: ≣ | Y33: Supports skills that fire projectiles from the user. Does not affect projectiles fired from other locations as secondary effects. Does not support skills that fire projectiles in a spiral. | Z33: Supported Skills fire 4 additional Projectiles Supported Skills also fire Projectiles from up to 4 points on each side of you Supported Skills deal (30-21)% less Projectile Damage | AA33: Greater Volley Support Support, Projectile Icon: ≣ Level: (1-20) Cost & Reservation Multiplier: 150% Requires Level 38 Supports skills that fire projectiles from the user. Does not affect projectiles fired from other locations as secondary effects. Does not support skills that fire projectiles in a spiral. Supported Skills fire 4 additional Projectiles Supported Skills also fire Projectiles from up to 4 points on each side of you Supported Skills deal (30-21)% less Projectile Damage
A34: SUPPORT | B34: O3 | C34: Support | D34: Hypothermia Support | E34: Cold, Support | F34: Cold | I34: Direct | J34: Freeze, Chill | K34: (1-20) | N34: 130% | R34: 31 | X34: D | Y34: Supports any skill that deals damage. | Z34: Supported Skills have +20% chance to Freeze Enemies which are Chilled Supported Skills deal (20-29)% more Cold Damage Over Time Supported Skills deal (20-29)% more Damage with Hits and Ailments against Chilled Enemies | AA34: Hypothermia Support Cold, Support Icon: D Level: (1-20) Cost & Reservation Multiplier: 130% Requires Level 31 Supports any skill that deals damage. Supported Skills have +20% chance to Freeze Enemies which are Chilled Supported Skills deal (20-29)% more Cold Damage Over Time Supported Skills deal (20-29)% more Damage with Hits and Ailments against Chilled Enemies
A35: SUPPORT | B35: P3 | C35: Support | D35: Impale Support | E35: Attack, Physical, Support | F35: Physical | G35: Attack | I35: Direct | J35: Impale | K35: (1-20) | N35: 130% | R35: 31 | X35: I | Y35: Supports attack skills. | Z35: Supported Attacks have 60% chance to Impale Enemies on Hit Supported Attacks have (0-28)% increased Impale Effect | AA35: Impale Support Attack, Physical, Support Icon: I Level: (1-20) Cost & Reservation Multiplier: 130% Requires Level 31 Supports attack skills. Supported Attacks have 60% chance to Impale Enemies on Hit Supported Attacks have (0-28)% increased Impale Effect
A36: SUPPORT | B36: Q3 | C36: Support | D36: Mirage Archer Support | E36: Bow, Attack, Support, Duration | G36: Attack, Bow | H36: Bow | I36: Duration/DoT | K36: (1-20) | N36: 130% | R36: 4 | X36: M | Y36: Supports attack skills that can be used with bows. Supported skills can only be used with bows. Cannot support Vaal skills, minion skills, movement skills, or skills used by totems, traps, or mines. When you Hit an Enemy with an Arrow from a Supported Skill, Summon a Mirage Archer which uses that Skill Mirage Archer can use Triggered Attacks as though they were not Triggered Mirage Archer uses Supported Skill with 60% less Attack Speed Mirage Archer deals (40-31)% less Damage with Supported Skills | Z36: Maximum 1 Summoned Mirage Archer Mirage Archer lasts 4 seconds | AA36: Mirage Archer Support Bow, Attack, Support, Duration Icon: M Level: (1-20) Cost & Reservation Multiplier: 130% Requires Level 4 Supports attack skills that can be used with bows. Supported skills can only be used with bows. Cannot support Vaal skills, minion skills, movement skills, or skills used by totems, traps, or mines. Maximum 1 Summoned Mirage Archer When you Hit an Enemy with an Arrow from a Supported Skill, Summon a Mirage Archer which uses that Skill Mirage Archer can use Triggered Attacks as though they were not Triggered Mirage Archer uses Supported Skill with 60% less Attack Speed Mirage Archer lasts 4 seconds Mirage Archer deals (40-31)% less Damage with Supported Skills
A37: SUPPORT | B37: R3 | C37: Support | D37: Multiple Projectiles Support | E37: Support, Projectile | H37: Projectile | I37: Projectile | K37: (1-20) | N37: 130% | R37: 8 | X37: l | Y37: Supports projectile skills. | Z37: Supported Skills deal (15-6)% less Projectile Damage Supported Skills fire 2 additional Projectiles | AA37: Multiple Projectiles Support Support, Projectile Icon: l Level: (1-20) Cost & Reservation Multiplier: 130% Requires Level 8 Supports projectile skills. Supported Skills deal (15-6)% less Projectile Damage Supported Skills fire 2 additional Projectiles
A38: SUPPORT | B38: S3 | C38: Support | D38: Pierce Support | E38: Support, Projectile | H38: Projectile | I38: Projectile | K38: (1-20) | N38: 120% | R38: 4 | X38: p | Y38: Supports projectile skills. | Z38: Projectiles from Supported Skills Pierce (2-4) additional Targets Supported Skills deal (0-19)% more Projectile Damage | AA38: Pierce Support Support, Projectile Icon: p Level: (1-20) Cost & Reservation Multiplier: 120% Requires Level 4 Supports projectile skills. Projectiles from Supported Skills Pierce (2-4) additional Targets Supported Skills deal (0-19)% more Projectile Damage
A39: SUPPORT | B39: T3 | C39: Support | D39: Returning Projectiles Support | E39: Support, Projectile | H39: Projectile | I39: Projectile | K39: (1-20) | N39: 150% | R39: 38 | X39: R | Y39: Supports projectile skills. | Z39: Projectiles from Supported Skills Return to you Projectiles from Supported Skills deal (70-66)% less Damage with Hits and Ailments while Returning Projectiles from Supported Skills Pierce all Targets while Returning | AA39: Returning Projectiles Support Support, Projectile Icon: R Level: (1-20) Cost & Reservation Multiplier: 150% Requires Level 38 Supports projectile skills. Projectiles from Supported Skills Return to you Projectiles from Supported Skills deal (70-66)% less Damage with Hits and Ailments while Returning Projectiles from Supported Skills Pierce all Targets while Returning
A40: SUPPORT | B40: U3 | C40: Support | D40: Slower Projectiles Support | E40: Support, Projectile | H40: Projectile | I40: Projectile | J40: Slow | K40: (1-20) | N40: 120% | R40: 31 | X40: J | Y40: Supports projectile skills. | Z40: Supported Skills have (20-30)% less Projectile Speed Supported Skills deal (10-19)% more Projectile Damage | AA40: Slower Projectiles Support Support, Projectile Icon: J Level: (1-20) Cost & Reservation Multiplier: 120% Requires Level 31 Supports projectile skills. Supported Skills have (20-30)% less Projectile Speed Supported Skills deal (10-19)% more Projectile Damage
A41: SUPPORT | B41: V3 | C41: Support | D41: Swift Affliction Support | E41: Support, Duration | I41: Duration/DoT | K41: (1-20) | N41: 140% | R41: 31 | X41: r | Y41: Supports any skill that has a duration, or can hit enemies to inflict ailments on them. 25% less Duration of Supported Skills and Damaging Ailments they inflict | Z41: Supported Skills deal (25-39)% more Damage over Time | AA41: Swift Affliction Support Support, Duration Icon: r Level: (1-20) Cost & Reservation Multiplier: 140% Requires Level 31 Supports any skill that has a duration, or can hit enemies to inflict ailments on them. Supported Skills deal (25-39)% more Damage over Time 25% less Duration of Supported Skills and Damaging Ailments they inflict
A42: SUPPORT | B42: W3 | C42: Support | D42: Vicious Projectiles Support | E42: Projectile, Attack, Physical, Chaos, Support | F42: Physical, Chaos | G42: Attack | H42: Projectile | I42: Projectile | K42: (1-20) | N42: 130% | R42: 18 | X42: d | Y42: Supports projectile attack skills. | Z42: Supported Skills deal (30-49)% more Chaos Damage over Time Supported Skills deal (30-49)% more Physical Damage over Time Supported Skills deal (30-49)% more Physical Projectile Attack Damage Supported Skills have 10% less Projectile Attack Speed | AA42: Vicious Projectiles Support Projectile, Attack, Physical, Chaos, Support Icon: d Level: (1-20) Cost & Reservation Multiplier: 130% Requires Level 18 Supports projectile attack skills. Supported Skills deal (30-49)% more Chaos Damage over Time Supported Skills deal (30-49)% more Physical Damage over Time Supported Skills deal (30-49)% more Physical Projectile Attack Damage Supported Skills have 10% less Projectile Attack Speed
A43: SUPPORT | B43: X3 | C43: Support | D43: Vile Toxins Support | E43: Support | I43: Direct | J43: Poison | K43: (1-20) | N43: 130% | R43: 38 | X43: e | Y43: Supports any skill that hits enemies. | Z43: Supported Skills deal 5% more Damage with Hits for each Poison on the Enemy, up to (5-8) Supported Skills deal (10-19)% more Damage with Poison | AA43: Vile Toxins Support Support Icon: e Level: (1-20) Cost & Reservation Multiplier: 130% Requires Level 38 Supports any skill that hits enemies. Supported Skills deal 5% more Damage with Hits for each Poison on the Enemy, up to (5-8) Supported Skills deal (10-19)% more Damage with Poison
A44: SUPPORT | B44: Y3 | C44: Support | D44: Void Manipulation Support | E44: Chaos, Support | F44: Chaos | I44: Direct | K44: (1-20) | N44: 130% | R44: 8 | X44: v | Y44: Supports any skill that deals damage. | Z44: Supported Skills deal (20-34)% more Chaos Damage Supported Skills deal no Elemental Damage | AA44: Void Manipulation Support Chaos, Support Icon: v Level: (1-20) Cost & Reservation Multiplier: 130% Requires Level 8 Supports any skill that deals damage. Supported Skills deal (20-34)% more Chaos Damage Supported Skills deal no Elemental Damage
A45: SUPPORT | B45: Z3 | C45: Support | D45: Volley Support | E45: Support, Projectile | H45: Projectile | I45: Projectile | K45: (1-20) | N45: 130% | R45: 4 | X45: = | Y45: Supports skills that fire projectiles from the user. Does not affect projectiles fired from other locations as secondary effects. Does not support skills that fire projectiles in a spiral. | Z45: Supported Skills fire 2 additional Projectiles Supported Skills also fire Projectiles from up to 2 points on each side of you Supported Skills deal (12-3)% less Projectile Damage | AA45: Volley Support Support, Projectile Icon: = Level: (1-20) Cost & Reservation Multiplier: 130% Requires Level 4 Supports skills that fire projectiles from the user. Does not affect projectiles fired from other locations as secondary effects. Does not support skills that fire projectiles in a spiral. Supported Skills fire 2 additional Projectiles Supported Skills also fire Projectiles from up to 2 points on each side of you Supported Skills deal (12-3)% less Projectile Damage
A46: SUPPORT | B46: D5 | C46: Support | D46: Added Chaos Damage Support | E46: Chaos, Support | F46: Chaos | I46: Direct | K46: (1-20) | N46: 120% | R46: 31 | X46: H | Y46: Supports any skill that hits enemies. | Z46: Supported Skills have (18-154) to (26-231) added Chaos Damage | AA46: Added Chaos Damage Support Chaos, Support Icon: H Level: (1-20) Cost & Reservation Multiplier: 120% Requires Level 31 Supports any skill that hits enemies. Supported Skills have (18-154) to (26-231) added Chaos Damage
A47: SUPPORT | B47: E5 | C47: Support | D47: Added Lightning Damage Support | E47: Lightning, Support | F47: Lightning | I47: Direct | K47: (1-20) | N47: 120% | R47: 8 | X47: L | Y47: Supports any skill that hits enemies. | Z47: Supported Skills have (1-19) to (8-358) added Lightning Damage | AA47: Added Lightning Damage Support Lightning, Support Icon: L Level: (1-20) Cost & Reservation Multiplier: 120% Requires Level 8 Supports any skill that hits enemies. Supported Skills have (1-19) to (8-358) added Lightning Damage
A48: SUPPORT | B48: F5 | C48: Support | D48: Bonechill Support | E48: Cold, Support | F48: Cold | I48: Direct | J48: Chill | K48: (1-20) | N48: 130% | R48: 38 | X48: B | Y48: Supports any skill that can chill enemies or create chilling areas. (25-44)% increased Effect of Chill inflicted with Supported Skills | Z48: Enemies Chilled by Supported Skills increase Cold Damage taken by Chill Effect Enemies in Chilling Areas from Supported Skills increase Cold Damage taken by Chill Effect Supported Skills deal (5-14)% more Cold Damage | AA48: Bonechill Support Cold, Support Icon: B Level: (1-20) Cost & Reservation Multiplier: 130% Requires Level 38 Supports any skill that can chill enemies or create chilling areas. (25-44)% increased Effect of Chill inflicted with Supported Skills Enemies Chilled by Supported Skills increase Cold Damage taken by Chill Effect Enemies in Chilling Areas from Supported Skills increase Cold Damage taken by Chill Effect Supported Skills deal (5-14)% more Cold Damage
A49: SUPPORT | B49: G5 | C49: Support | D49: Combustion Support | E49: Fire, Support | F49: Fire | I49: Direct | J49: Ignite | K49: (1-20) | N49: 130% | R49: 8 | X49: i | Y49: Supports any skill that hits enemies. | Z49: Supported Skills deal (10-19)% more Fire Damage Supported Skills have 25% chance to Ignite Enemies Ignited by Supported Skills have -10% to Fire Resistance | AA49: Combustion Support Fire, Support Icon: i Level: (1-20) Cost & Reservation Multiplier: 130% Requires Level 8 Supports any skill that hits enemies. Supported Skills deal (10-19)% more Fire Damage Supported Skills have 25% chance to Ignite Enemies Ignited by Supported Skills have -10% to Fire Resistance
A50: SUPPORT | B50: H5 | C50: Support | D50: Concentrated Effect Support | E50: Support, AoE | H50: AoE | I50: Area | K50: (1-20) | N50: 140% | R50: 18 | X50: o | Y50: Supports any skill with an area of effect, regardless of whether that skill deals damage. | Z50: Supported Skills deal (25-39)% more Area Damage Supported Skills have 30% less Area of Effect | AA50: Concentrated Effect Support Support, AoE Icon: o Level: (1-20) Cost & Reservation Multiplier: 140% Requires Level 18 Supports any skill with an area of effect, regardless of whether that skill deals damage. Supported Skills deal (25-39)% more Area Damage Supported Skills have 30% less Area of Effect
A51: SUPPORT | B51: I5 | C51: Support | D51: Controlled Destruction Support | E51: Spell, Critical, Support | G51: Spell | I51: Direct | K51: (1-20) | N51: 140% | R51: 18 | X51: C | Y51: Supports attack skills, or spell skills that deal damage. | Z51: Supported Skills have 80% less Critical Strike Chance Supported Skills deal (25-39)% more Spell Damage | AA51: Controlled Destruction Support Spell, Critical, Support Icon: C Level: (1-20) Cost & Reservation Multiplier: 140% Requires Level 18 Supports attack skills, or spell skills that deal damage. Supported Skills have 80% less Critical Strike Chance Supported Skills deal (25-39)% more Spell Damage
A52: SUPPORT | B52: J5 | C52: Support | D52: Efficacy Support | E52: Support, Duration | I52: Duration/DoT | K52: (1-20) | N52: 130% | R52: 8 | X52: a | Y52: Supports any skill that deals damage or has a duration. | Z52: Supported Skills deal (15-24)% more Damage over Time Supported Skills have (15-24)% increased Skill Effect Duration | AA52: Efficacy Support Support, Duration Icon: a Level: (1-20) Cost & Reservation Multiplier: 130% Requires Level 8 Supports any skill that deals damage or has a duration. Supported Skills deal (15-24)% more Damage over Time Supported Skills have (15-24)% increased Skill Effect Duration
A53: SUPPORT | B53: K5 | C53: Support | D53: Elemental Focus Support | E53: Support | I53: Direct | K53: (1-20) | N53: 130% | R53: 18 | X53: F | Y53: Supports any skill that hits or burns enemies, or inflicts elemental ailments. | Z53: Supported Skills deal (20-34)% more Elemental Damage Supported Skills cannot inflict Elemental Ailments | AA53: Elemental Focus Support Support Icon: F Level: (1-20) Cost & Reservation Multiplier: 130% Requires Level 18 Supports any skill that hits or burns enemies, or inflicts elemental ailments. Supported Skills deal (20-34)% more Elemental Damage Supported Skills cannot inflict Elemental Ailments
A54: SUPPORT | B54: L5 | C54: Support | D54: Elemental Proliferation Support | E54: Cold, Fire, Lightning, Support, AoE | F54: Cold, Fire, Lightning | H54: AoE | I54: Area, Duration/DoT | J54: Ignite, Shock, Freeze | K54: (1-20) | N54: 110% | X54: S | Y54: Supports any skill that hits enemies, or could otherwise apply elemental ailments. Elemental Ailments inflicted by Supported Skills spread to other enemies within (1.2-1.5) metres | Z54: (0-19)% increased Duration of Elemental Ailments on Enemies Supported Skills have 20% chance to Freeze, Shock and Ignite | AA54: Elemental Proliferation Support Cold, Fire, Lightning, Support, AoE Icon: S Level: (1-20) Cost & Reservation Multiplier: 110% Supports any skill that hits enemies, or could otherwise apply elemental ailments. (0-19)% increased Duration of Elemental Ailments on Enemies Elemental Ailments inflicted by Supported Skills spread to other enemies within (1.2-1.5) metres Supported Skills have 20% chance to Freeze, Shock and Ignite
A55: SUPPORT | B55: M5 | C55: Support | D55: Faster Casting Support | E55: Support, Spell | G55: Spell | I55: Direct | K55: (1-20) | N55: 110% | R55: 18 | X55: f | Y55: Supports non-instant spell skills. | Z55: Supported Skills have (20-39)% increased Cast Speed | AA55: Faster Casting Support Support, Spell Icon: f Level: (1-20) Cost & Reservation Multiplier: 110% Requires Level 18 Supports non-instant spell skills. Supported Skills have (20-39)% increased Cast Speed
A56: SUPPORT | B56: N5 | C56: Support | D56: Ignite Proliferation Support | E56: Fire, Support, AoE | F56: Fire | H56: AoE | I56: Area | J56: Ignite | K56: (1-20) | N56: 130% | R56: 38 | X56: I | Y56: Supports any skill that hits enemies. Ignites caused by Supported Skills spread to other Enemies within (1.4-2) metres | Z56: Supported Skills deal (15-24)% more Damage with Ignite | AA56: Ignite Proliferation Support Fire, Support, AoE Icon: I Level: (1-20) Cost & Reservation Multiplier: 130% Requires Level 38 Supports any skill that hits enemies. Ignites caused by Supported Skills spread to other Enemies within (1.4-2) metres Supported Skills deal (15-24)% more Damage with Ignite
A57: SUPPORT | B57: O5 | C57: Support | D57: Increased Area of Effect Support | E57: Support, AoE | H57: AoE | I57: Area | K57: (1-20) | N57: 130% | R57: 38 | X57: E | Y57: Supports any skill with an area of effect. | Z57: Supported Skills have (30-49)% increased Area of Effect | AA57: Increased Area of Effect Support Support, AoE Icon: E Level: (1-20) Cost & Reservation Multiplier: 130% Requires Level 38 Supports any skill with an area of effect. Supported Skills have (30-49)% increased Area of Effect
A58: SUPPORT | B58: P5 | C58: Support | D58: Increased Critical Damage Support | E58: Critical, Support | I58: Direct | K58: (1-20) | N58: 130% | R58: 18 | X58: c | Y58: Supports any skill that hits enemies. | Z58: Supported Skills have +(100-138)% to Critical Strike Multiplier | AA58: Increased Critical Damage Support Critical, Support Icon: c Level: (1-20) Cost & Reservation Multiplier: 130% Requires Level 18 Supports any skill that hits enemies. Supported Skills have +(100-138)% to Critical Strike Multiplier
A59: SUPPORT | B59: Q5 | C59: Support | D59: Increased Critical Strikes Support | E59: Critical, Support | I59: Direct | K59: (1-20) | N59: 120% | R59: 8 | X59: s | Y59: Supports any skill that hits enemies. | Z59: Supported Skills have (60-117)% increased Critical Strike Chance Supported Skills have +2% to Critical Strike Chance | AA59: Increased Critical Strikes Support Critical, Support Icon: s Level: (1-20) Cost & Reservation Multiplier: 120% Requires Level 8 Supports any skill that hits enemies. Supported Skills have (60-117)% increased Critical Strike Chance Supported Skills have +2% to Critical Strike Chance
A60: SUPPORT | B60: R5 | C60: Support | D60: Infused Channelling Support | E60: Support, Channelling | H60: Channelling | I60: Channel | K60: (1-20) | N60: 130% | R60: 4 | X60: b | Y60: Supports any channelling skill, protecting you from damage while you channel it. Cannot modify the skills of minions. While Channelling a Supported Skill, take 12% less Damage from Hits | Z60: Supported Skills deal (20-29)% more Damage | AA60: Infused Channelling Support Support, Channelling Icon: b Level: (1-20) Cost & Reservation Multiplier: 130% Requires Level 4 Supports any channelling skill, protecting you from damage while you channel it. Cannot modify the skills of minions. Supported Skills deal (20-29)% more Damage While Channelling a Supported Skill, take 12% less Damage from Hits
A61: SUPPORT | B61: S5 | C61: Support | D61: Lightning Penetration Support | E61: Lightning, Support | F61: Lightning | I61: Direct | K61: (1-20) | N61: 130% | R61: 31 | X61: V | Y61: Supports any skill that hits enemies, making those hits penetrate enemy lightning resistance. | Z61: Supported Skills Penetrate (20-34)% Lightning Resistance | AA61: Lightning Penetration Support Lightning, Support Icon: V Level: (1-20) Cost & Reservation Multiplier: 130% Requires Level 31 Supports any skill that hits enemies, making those hits penetrate enemy lightning resistance. Supported Skills Penetrate (20-34)% Lightning Resistance
A62: SUPPORT | B62: T5 | C62: Support | D62: Minion Damage Support | E62: Support, Minion | G62: Minion | H62: Minion | I62: Summon | K62: (1-20) | N62: 140% | R62: 8 | X62: d | Y62: Supports skills which create Minions. | Z62: Minions from Supported Skills deal (25-39)% more Damage Minions from Supported Skills have 25% less Maximum Life | AA62: Minion Damage Support Support, Minion Icon: d Level: (1-20) Cost & Reservation Multiplier: 140% Requires Level 8 Supports skills which create Minions. Minions from Supported Skills deal (25-39)% more Damage Minions from Supported Skills have 25% less Maximum Life
A63: SUPPORT | B63: U5 | C63: Support | D63: Minion Speed Support | E63: Movement, Support, Minion | G63: Minion | H63: Movement, Minion | I63: Summon | K63: (1-20) | N63: 120% | R63: 18 | X63: e | Y63: Supports skills which create Minions. | Z63: Supported Skills have (25-34)% increased Minion Attack Speed Supported Skills have (25-34)% increased Minion Cast Speed Supported Skills have (25-44)% increased Minion Movement Speed | AA63: Minion Speed Support Movement, Support, Minion Icon: e Level: (1-20) Cost & Reservation Multiplier: 120% Requires Level 18 Supports skills which create Minions. Supported Skills have (25-34)% increased Minion Attack Speed Supported Skills have (25-34)% increased Minion Cast Speed Supported Skills have (25-44)% increased Minion Movement Speed
A64: SUPPORT | B64: V5 | C64: Support | D64: Physical to Lightning Support | E64: Lightning, Physical, Support | F64: Lightning, Physical | I64: Direct | K64: (1-20) | N64: 120% | R64: 18 | X64: x | Y64: Supports any skill that hits enemies. | Z64: Supported Skills gain (10-29)% of Physical Damage as Extra Lightning Damage Supported Skills have 50% of Physical Damage Converted to Lightning Damage | AA64: Physical to Lightning Support Lightning, Physical, Support Icon: x Level: (1-20) Cost & Reservation Multiplier: 120% Requires Level 18 Supports any skill that hits enemies. Supported Skills gain (10-29)% of Physical Damage as Extra Lightning Damage Supported Skills have 50% of Physical Damage Converted to Lightning Damage
A65: SUPPORT | B65: W5 | C65: Support | D65: Spell Cascade Support | E65: AoE, Spell, Support | G65: Spell | H65: AoE | I65: Area | K65: (1-20) | N65: 130% | R65: 4 | X65: p | Y65: Supports spell skills that apply an effect to an area around a targeted location. Cannot support Vaal skills or skills used by totems, traps, or mines. Cannot modify the skills of minions. | Z65: Supported Skills have (25-16)% less Area of Effect Supported Skills deal (40-31)% less Damage Supported Area of Effect Skills also affect areas in front of and behind the targeted area | AA65: Spell Cascade Support AoE, Spell, Support Icon: p Level: (1-20) Cost & Reservation Multiplier: 130% Requires Level 4 Supports spell skills that apply an effect to an area around a targeted location. Cannot support Vaal skills or skills used by totems, traps, or mines. Cannot modify the skills of minions. Supported Skills have (25-16)% less Area of Effect Supported Skills deal (40-31)% less Damage Supported Area of Effect Skills also affect areas in front of and behind the targeted area
A66: SUPPORT | B66: X5 | C66: Support | D66: Spell Echo Support | E66: Spell, Support | G66: Spell | I66: Direct | K66: (1-20) | N66: 140% | R66: 38 | X66: k | Y66: Supports spell skills, making them repeat when cast. Cannot support Vaal skills, totem skills, channelling skills, triggered skills, instant skills, retaliation skills, blink skills, or skills with a reservation. | Z66: Supported Skills Repeat an additional time Supported Skills have (40-54)% more Cast Speed | AA66: Spell Echo Support Spell, Support Icon: k Level: (1-20) Cost & Reservation Multiplier: 140% Requires Level 38 Supports spell skills, making them repeat when cast. Cannot support Vaal skills, totem skills, channelling skills, triggered skills, instant skills, retaliation skills, blink skills, or skills with a reservation. Supported Skills Repeat an additional time Supported Skills have (40-54)% more Cast Speed
A67: SUPPORT | B67: Y5 | C67: Support | D67: Trinity Support | E67: Support | I67: Direct | K67: (1-20) | N67: 140% | R67: 18 | X67: y | Y67: Supports skills that hit enemies, causing them to gain bonuses while you have resonance of all three elements, and to grant resonance of elements other than the highest one in a hit. There is a maximum of 50 Resonance for each Element. Cannot support triggered skills, instant skills, orb skills, brands, skills with a reservation, or skills used by totems, traps, or mines. Cannot modify the skills of minions. | Z67: Hits with Supported Skills for which the highest Damage Type is Elemental cause you to gain 25 Resonance of other Elements per second for 2 seconds Lose 5 Resonance per second of each Element you are not gaining Supported Skills deal 3% more Elemental Damage per 5 of lowest Resonance Supported Skills penetrate (7-16)% Elemental Resistances while each Resonance is at least 25 | AA67: Trinity Support Support Icon: y Level: (1-20) Cost & Reservation Multiplier: 140% Requires Level 18 Supports skills that hit enemies, causing them to gain bonuses while you have resonance of all three elements, and to grant resonance of elements other than the highest one in a hit. There is a maximum of 50 Resonance for each Element. Cannot support triggered skills, instant skills, orb skills, brands, skills with a reservation, or skills used by totems, traps, or mines. Cannot modify the skills of minions. Hits with Supported Skills for which the highest Damage Type is Elemental cause you to gain 25 Resonance of other Elements per second for 2 seconds Lose 5 Resonance per second of each Element you are not gaining Supported Skills deal 3% more Elemental Damage per 5 of lowest Resonance Supported Skills penetrate (7-16)% Elemental Resistances while each Resonance is at least 25
A68: SUPPORT | B68: Z5 | C68: Support | D68: Unleash Support | E68: Spell, Support | G68: Spell | I68: Direct | K68: (1-20) | N68: 140% | R68: 38 | X68: q | Y68: Supports spell skills, making their effect reoccur when cast. Cannot support skills with cooldowns, triggered skills, Brand skills, Vaal skills, channelling skills, skills with a reservation, or skills used by totems, traps, or mines. Cannot modify the skills of minions. | Z68: Supported Spells gain a Seal every (0.90-0.71) seconds, to a maximum of 3 Seals Supported Spells are Unsealed when cast, and their effects Reoccur for each Seal lost Supported Skills deal (45-36)% less Damage when Reoccurring | AA68: Unleash Support Spell, Support Icon: q Level: (1-20) Cost & Reservation Multiplier: 140% Requires Level 38 Supports spell skills, making their effect reoccur when cast. Cannot support skills with cooldowns, triggered skills, Brand skills, Vaal skills, channelling skills, skills with a reservation, or skills used by totems, traps, or mines. Cannot modify the skills of minions. Supported Spells gain a Seal every (0.90-0.71) seconds, to a maximum of 3 Seals Supported Spells are Unsealed when cast, and their effects Reoccur for each Seal lost Supported Skills deal (45-36)% less Damage when Reoccurring

Sheet PARSE_SUMMARY
A1: 항목 | B1: 값 | C1: 설명 | D1: 비고
A2: Active Gem parsed | B2: 55 | C2: SKILL 시트에서 파싱한 액티브 젬 수
A3: Support Gem parsed | B3: 67 | C3: SUPPORT 시트에서 파싱한 보조 젬 수
A4: 원본 보존 | B4: YES | C4: SKILL / SUPPORT 원본 시트는 삭제하지 않음
A5: 추가 시트 | B5: PARSED_ACTIVE | C5: 액티브 젬 구조화 결과
A6: 추가 시트 | B6: PARSED_SUPPORT | C6: 보조 젬 구조화 결과
A7: 주의 | B7: 자동 파싱 | C7: Wiki 원문 형태가 불규칙한 경우 일부 컬럼은 보정 필요 | D7: RawText 보존
A8: 보정 | B8: Anger | C8: SKILL!A2는 이름 줄이 누락되어 설명 기반으로 Anger로 보정
A9: 보정 | B9: Elemental Damage with Attacks Support | C9: SUPPORT!G1 첫 글자 누락 추정값을 보정

Sheet DESIGN_ACTIVE
A1: SourceSheet | B1: SourceCell | C1: GemType | D1: Name | E1: Tags | F1: DamageType | G1: Scaling | H1: MechanicTags | I1: CombatRole | J1: AilmentKeywords | K1: Level | L1: Cost | M1: Reservation | N1: CostReservationMultiplier | O1: CooldownTime | P1: CanStoreUses | Q1: CastTime | R1: RequiresLevel | S1: AttackSpeed | T1: AttackDamage | U1: EffectivenessAddedDamage | V1: AoERadius | W1: ProjectileSpeed | X1: Icon | Y1: Description | Z1: ModifierLines | AA1: RawText | AB1: Archetype | AC1: AI_CombatRole | AD1: DefenseConversion
A2: SKILL | B2: A2 | C2: Active | D2: Anger | E2: Aura, Spell, AoE, Fire | F2: Fire | G2: Spell | H2: Aura, AoE | I2: Buff/Aura, Area | K2: (1-20) | M2: 50% Mana | O2: 1.20 sec | P2: 1 Use(s) | Q2: Instant | R2: 24 | Y2: Casts an aura that adds fire damage to the attacks and spells of you and your... | Z2: +(0-1.9) metres to radius You and nearby allies deal (16-109) to (23-155) add... | AA2: Aura, Spell, AoE, Fire Level: (1-20) Reservation: 50% Mana Cooldown Time: 1.2... | AB2: Aura Buff / Debuff Field | AC2: Buff/Aura / Wave Clear | AD2: 주변 타워/아군에게 지속 버프를 주거나 적에게 약화 효과를 주는 지원형 오라 스킬
A3: SKILL | B3: B2 | C3: Active | D3: Earthquake | E3: Attack, AoE, Melee, Duration, Slam | G3: Attack, Melee | H3: AoE, Melee, Slam | I3: Area, Duration/DoT | J3: Shock | K3: (1-20) | L3: (10-13) Mana | R3: 28 | S3: 75% of base | T3: (143-229)% of base | U3: (143-229)% | V3: 18 / 28 | Y3: Smashes the ground, dealing damage in an area and cracking the earth. The cra... | Z3: Base duration is 1.00 second Aftershock deals 150% more Damage with Hits and ... | AA3: Earthquake Attack, AoE, Melee, Duration, Slam Level: (1-20) Cost: (10-13) Man... | AB3: Melee Slam Area Attack | AC3: Damage over Time / Wave Clear | AD3: 타워 주변 또는 전방 부채꼴 범위에 충격파를 발생시키는 근접 광역 스킬
A4: SKILL | B4: C2 | C4: Active | D4: Exsanguinate | E4: Spell, Chaining, Physical, Duration | F4: Physical | G4: Spell | H4: Chaining | I4: Duration/DoT, Chain | K4: (1-20) | L4: (16-46) Life | Q4: 0.80 sec | R4: 12 | U4: (150-270)% | Y4: Critical Strike Chance: 6.00% Releases several tendrils of blood from your ch... | Z4: Deals (17-1193) to (25-1789) Physical Damage Deals (26.9-1534.2) Base Physica... | AA4: Exsanguinate Spell, Chaining, Physical, Duration Level: (1-20) Cost: (16-46) ... | AB4: Direct Spell | AC4: Wave Clear | AD4: 기본 공격/유틸 효과를 디펜스 게임용 타워 또는 영웅 스킬로 변환
A5: SKILL | B5: D2 | C5: Active | D5: Ground Slam | E5: Attack, AoE, Melee, Slam | G5: Attack, Melee | H5: AoE, Melee, Slam | I5: Area | J5: Stun | K5: (1-20) | L5: (6-11) Mana | S5: 90% of base | T5: (132-356)% of base | U5: (132-356)% | V5: 35 | Y5: Slams the ground in front of you, creating a wave that travels forward and da... | Z5: 25% reduced Enemy Stun Threshold +(0-1) metre to radius Deals up to (40-49)% ... | AA5: Ground Slam Attack, AoE, Melee, Slam Level: (1-20) Cost: (6-11) Mana Attack S... | AB5: Melee Slam Area Attack | AC5: Crowd Control / Wave Clear | AD5: 타워 주변 또는 전방 부채꼴 범위에 충격파를 발생시키는 근접 광역 스킬
A6: SKILL | B6: E2 | C6: Active | D6: Herald of Ash | E6: Spell, AoE, Fire, Herald, Duration | F6: Fire | G6: Spell | H6: AoE, Herald | I6: Buff/Aura, Area, Duration/DoT | K6: (1-20) | M6: 25% Mana | O6: 1.00 sec | P6: 1 Use(s) | Q6: Instant | R6: 16 | V6: 10 | Y6: Base Burning Damage is 25% of Overkill Damage Buff grants (15-20)% of your Ph... | Z6: Grants a buff providing fire damage based on your physical damage. While you ... | AA6: Herald of Ash Spell, AoE, Fire, Herald, Duration Level: (1-20) Reservation: 2... | AB6: Reserved Self-Buff / Herald | AC6: Buff/Aura / Damage over Time / Wave Clear | AD6: 주변 타워/아군에게 지속 버프를 주거나 적에게 약화 효과를 주는 지원형 오라 스킬
A7: SKILL | B7: F2 | C7: Active | D7: Molten Strike | E7: Attack, Projectile, AoE, Melee, Strike, Fire | F7: Fire | G7: Attack, Melee | H7: Projectile, AoE, Melee, Strike | I7: Projectile, Area | K7: (1-20) | L7: (6-10) Mana | T7: (126-329)% of base | U7: (126-329)% | W7: 750 | Y7: Infuses your melee weapon with molten energies to attack with physical and fi... | Z7: Fires 4 Projectiles 60% of Physical Damage Converted to Fire Damage Projectil... | AA7: Molten Strike Attack, Projectile, AoE, Melee, Strike, Fire Level: (1-20) Cost... | AB7: Melee Projectile Hybrid | AC7: Wave Clear | AD7: 지정 방향/라인으로 투사체를 발사하는 Fire 원거리 타워 스킬
A8: SKILL | B8: G2 | C8: Active | D8: Pride | E8: Spell, AoE, Aura, Physical | F8: Physical | G8: Spell | H8: AoE, Aura | I8: Buff/Aura, Area | K8: (1-20) | M8: 50% Mana | O8: 1.20 sec | P8: 1 Use(s) | Q8: Instant | R8: 24 | Y8: Casts an aura that causes nearby enemies to take more physical damage. raisin... | Z8: +(0-1) metre to radius Nearby Enemies take at least (15-19)% more Physical Da... | AA8: Pride Spell, AoE, Aura, Physical Level: (1-20) Reservation: 50% Mana Cooldown... | AB8: Aura Buff / Debuff Field | AC8: Buff/Aura / Wave Clear | AD8: 주변 타워/아군에게 지속 버프를 주거나 적에게 약화 효과를 주는 지원형 오라 스킬
A9: SKILL | B9: H2 | C9: Active | D9: Reap | E9: Spell, Physical, AoE, Duration | F9: Physical | G9: Spell | H9: AoE | I9: Area, Duration/DoT | K9: (1-20) | L9: (25-46) Life | Q9: 0.80 sec | R9: 28 | U9: (150-210)% | Y9: Critical Strike Chance: 6.00% A bloody scythe swipes across a selected area, ... | Z9: Deals (57-943) to (86-1414) Physical Damage Deals (138.2-2002.5) Base Physica... | AA9: Reap Spell, Physical, AoE, Duration Level: (1-20) Cost: (25-46) Life Cast Tim... | AB9: Area Duration / DoT Spell | AC9: Wave Clear | AD9: 바닥 장판을 생성해 일정 시간 동안 지속 피해와 지역 제어를 제공하는 스킬
A10: SKILL | B10: I2 | C10: Active | D10: Smite | E10: Lightning, Melee, Attack, AoE, Duration, Strike, Aura | F10: Lightning | G10: Attack, Melee | H10: Melee, AoE, Strike, Aura | I10: Buff/Aura, Area, Duration/DoT | J10: Shock | K10: (1-20) | L10: (7-12) Mana | S10: 85% of base | T10: (225-488)% of base | U10: (225-488)% | Y10: Performs a melee attack, and causes lightning to strike a nearby enemy, deali... | Z10: 50% of Physical Damage Converted to Lightning Damage Base duration is 4.00 se... | AA10: Smite Lightning, Melee, Attack, AoE, Duration, Strike, Aura Level: (1-20) Cos... | AB10: Aura Buff / Debuff Field | AC10: Buff/Aura / Damage over Time / Wave Clear | AD10: 주변 타워/아군에게 지속 버프를 주거나 적에게 약화 효과를 주는 지원형 오라 스킬
A11: SKILL | B11: J2 | C11: Active | D11: Summon Stone Golem | E11: Minion, Spell, Golem, Physical | F11: Physical | G11: Spell, Minion | H11: Minion | I11: Summon | K11: (1-20) | L11: (30-54) Mana | O11: 6.00 sec | P11: 1 Use(s) | Q11: 1.00 sec | R11: 34 | Y11: Golems grant (33-105) Life Regenerated per second | Z11: Summons a Stone Golem that grants you life regeneration and defences. In addition to its melee attack, the Stone Golem uses a rolling charge and a powerful slam that can taunt enemies. Maximum 1 Summoned Golem Golems grant 20% increased Defences | AA11: Summon Stone Golem Minion, Spell, Golem, Physical Level: (1-20) Cost: (30-54) Mana Cooldown Time: 6.00 sec Can Store 1 Use(s) Cast Time: 1.00 sec Requires Level 34 Summons a Stone Golem that grants you life regeneration and defences. In addition to its melee attack, the Stone Golem uses a rolling charge and a powerful slam that can taunt enemies. Maximum 1 Summoned Golem Golems grant (33-105) Life Regenerated per second Golems grant 20% increased Defences | AB11: Persistent Minion Summon | AC11: Crowd Control / Damage over Time / Autonomous DPS | AD11: 일정 시간 또는 지속적으로 소환체를 생성해 경로 위 적을 자동 공격하는 소환형 타워 스킬
A12: SKILL | B12: K2 | C12: Active | D12: Swordstorm | E12: Attack, Melee, AoE, Retaliation | G12: Attack, Melee | H12: Melee, AoE, Retaliation | I12: Area | K12: (1-20) | L12: (7-10) Mana | O12: 3.00 sec | P12: 1 Use(s) | R12: 16 | T12: (123-247)% of base | U12: (123-247)% | Y12: Retaliate against a blocked hit with a hail of blades that rains down in front of you, repeatedly dealing the damage of both your weapons combined. Requires Dual Wielding Melee Weapons. | Z12: Cannot be used by default Becomes Usable once for 2 seconds when you Block a Hit Can't be Evaded Base radius is (1.8-2.3) metres Damages Enemies 8 times | AA12: Swordstorm Attack, Melee, AoE, Retaliation Level: (1-20) Cost: (7-10) Mana Cooldown Time: 3.00 sec Can Store 1 Use(s) Attack Damage: (123-247)% of base Effectiveness of Added Damage: (123-247)% Requires Level 16 Retaliate against a blocked hit with a hail of blades that rains down in front of you, repeatedly dealing the damage of both your weapons combined. Requires Dual Wielding Melee Weapons. Cannot be used by default Becomes Usable once for 2 seconds when you Block a Hit Can't be Evaded Base radius is (1.8-2.3) metres Damages Enemies 8 times | AB12: Melee Area Attack | AC12: Wave Clear | AD12: 타워 주변 또는 전방 부채꼴 범위에 충격파를 발생시키는 근접 광역 스킬
A13: SKILL | B13: L2 | C13: Active | D13: Volcanic Fissure | E13: Melee, Attack, Projectile, AoE, Slam, Fire | F13: Fire | G13: Attack, Melee | H13: Melee, Projectile, AoE, Slam | I13: Projectile, Area | K13: (1-20) | L13: (8-13) Mana | R13: 12 | S13: 80% of base | T13: (177-344)% of base | U13: (177-344)% | Y13: Slam the ground, creating a winding fissure that deals area damage while travelling outwards. When it reaches the target location it erupts, releasing a burst of molten projectiles. Requires an Axe, Mace, Sceptre, Staff or Unarmed. | Z13: Fires 5 Projectiles 60% of Physical Damage Converted to Fire Damage Projectiles deal 50% less Damage with Hits and Ailments | AA13: Volcanic Fissure Melee, Attack, Projectile, AoE, Slam, Fire Level: (1-20) Cost: (8-13) Mana Attack Speed: 80% of base Attack Damage: (177-344)% of base Effectiveness of Added Damage: (177-344)% Requires Level 12 Slam the ground, creating a winding fissure that deals area damage while travelling outwards. When it reaches the target location it erupts, releasing a burst of molten projectiles. Requires an Axe, Mace, Sceptre, Staff or Unarmed. Fires 5 Projectiles 60% of Physical Damage Converted to Fire Damage Projectiles deal 50% less Damage with Hits and Ailments | AB13: Melee Projectile Hybrid | AC13: Wave Clear | AD13: 지정 방향/라인으로 투사체를 발사하는 Fire 원거리 타워 스킬
A14: SKILL | B14: A4 | C14: Active | D14: Animate Weapon | E14: Duration, Minion, Spell, Physical | F14: Physical | G14: Spell, Minion | H14: Minion | I14: Summon, Duration/DoT | K14: (1-20) | L14: (4-16) Mana | Q14: 0.60 sec | R14: 4 | Y14: Animates a Melee Weapon Item or Lingering Blade to fight by your side. You cannot animate unidentified Weapons. Will not animate weapons with 6 sockets. Cannot be used by Traps or Mines. Minions' Attacks deal (5-126) to (8-184) additional Physical Damage Animated Lingering Blades deal (1-17) to (2-80) Added Attack Physical Damage | Z14: Base duration is 40.00 seconds Maximum (5-14) Animated Weapons Can use Items requiring up to Level (9-100) Minions deal (0-38)% more Damage Minions have (0-38)% more Attack Speed | AA14: Animate Weapon Duration, Minion, Spell, Physical Level: (1-20) Cost: (4-16) Mana Cast Time: 0.60 sec Requires Level 4 Animates a Melee Weapon Item or Lingering Blade to fight by your side. You cannot animate unidentified Weapons. Will not animate weapons with 6 sockets. Cannot be used by Traps or Mines. Base duration is 40.00 seconds Maximum (5-14) Animated Weapons Can use Items requiring up to Level (9-100) Minions' Attacks deal (5-126) to (8-184) additional Physical Damage Animated Lingering Blades deal (1-17) to (2-80) Added Attack Physical Damage Minions deal (0-38)% more Damage Minions have (0-38)% more Attack Speed | AB14: Temporary Object Minion Summon | AC14: Damage over Time / Autonomous DPS | AD14: 일정 시간 또는 지속적으로 소환체를 생성해 경로 위 적을 자동 공격하는 소환형 타워 스킬
A15: SKILL | B15: B4 | C15: Active | D15: Barrage | E15: Attack, Projectile, Bow | G15: Attack, Bow | H15: Projectile, Bow | I15: Projectile | K15: (1-20) | L15: (5-9) Mana | R15: 12 | S15: 115% of base | T15: (47-54)% of base | U15: (47-55)% | Y15: After a short preparation time, you fire individual projectiles repeatedly with a Bow or Wand. These projectiles have a small randomised spread. This skill cannot be Triggered. | Z15: Fires 5 Projectiles Fires Projectiles sequentially | AA15: Barrage Attack, Projectile, Bow Level: (1-20) Cost: (5-9) Mana Attack Speed: 115% of base Attack Damage: (47-54)% of base Effectiveness of Added Damage: (47-55)% Requires Level 12 After a short preparation time, you fire individual projectiles repeatedly with a Bow or Wand. These projectiles have a small randomised spread. This skill cannot be Triggered. Fires 5 Projectiles Fires Projectiles sequentially | AB15: Bow Projectile Attack | AC15: Lane Clear | AD15: 지정 방향/라인으로 투사체를 발사하는 Physical/Elemental 원거리 타워 스킬
A16: SKILL | B16: C4 | C16: Active | D16: Blade Vortex | E16: Spell, AoE, Duration, Physical | F16: Physical | G16: Spell | H16: AoE | I16: Area, Duration/DoT | K16: (1-20) | L16: (6-16) Mana | Q16: 0.50 sec | R16: 12 | U16: 30% | Y16: Critical Strike Chance: 6.00% This spell creates ethereal blades which orbit in an area around you, dealing damage every 0.6 seconds to all enemies in their radius. As more blades are added, the damage becomes greater and more frequent. | Z16: Deals (3-140) to (5-211) Physical Damage Base duration is 4.00 seconds +(0-0.2) metres to radius 35% increased Hit Rate for each blade 35% more Damage for each blade Can have up to 10 active spinning blades | AA16: Blade Vortex Spell, AoE, Duration, Physical Level: (1-20) Cost: (6-16) Mana Cast Time: 0.50 sec Critical Strike Chance: 6.00% Effectiveness of Added Damage: 30% Requires Level 12 This spell creates ethereal blades which orbit in an area around you, dealing damage every 0.6 seconds to all enemies in their radius. As more blades are added, the damage becomes greater and more frequent. Deals (3-140) to (5-211) Physical Damage Base duration is 4.00 seconds +(0-0.2) metres to radius 35% increased Hit Rate for each blade 35% more Damage for each blade Can have up to 10 active spinning blades | AB16: Area Duration / DoT Spell | AC16: Damage over Time / Wave Clear | AD16: 바닥 장판을 생성해 일정 시간 동안 지속 피해와 지역 제어를 제공하는 스킬
A17: SKILL | B17: D4 | C17: Active | D17: Blast Rain | E17: Fire, Attack, AoE, Projectile, Bow | F17: Fire | G17: Attack, Bow | H17: AoE, Projectile, Bow | I17: Projectile, Area | K17: (1-20) | L17: (7-10) Mana | R17: 28 | T17: (30-35)% of base | U17: (30-36)% | Y17: 100% of Physical Damage Converted to Fire Damage | Z17: Fires arrows up in the air, to rain down in an area. Each arrow deals area damage around where it lands, and they will all overlap on the targeted location. Fires 6 Arrows Penetrates (20-30)% Fire Resistance | AA17: Blast Rain Fire, Attack, AoE, Projectile, Bow Level: (1-20) Cost: (7-10) Mana Attack Damage: (30-35)% of base Effectiveness of Added Damage: (30-36)% Requires Level 28 Fires arrows up in the air, to rain down in an area. Each arrow deals area damage around where it lands, and they will all overlap on the targeted location. Fires 6 Arrows 100% of Physical Damage Converted to Fire Damage Penetrates (20-30)% Fire Resistance | AB17: Bow Area Rain / Ground DoT | AC17: Wave Clear | AD17: 지정 방향/라인으로 투사체를 발사하는 Fire 원거리 타워 스킬
A18: SKILL | B18: E4 | C18: Active | D18: Burning Arrow | E18: Attack, Projectile, Fire, Bow | F18: Fire | G18: Attack, Bow | H18: Projectile, Bow | I18: Projectile | J18: Ignite | K18: (1-20) | L18: (8-14) Mana | S18: 70% of base | T18: (280-420)% of base | U18: (280-420)% | W18: 3260 | Y18: 25% chance to Ignite enemies | Z18: Fires a burning arrow that deals fire damage and has a chance to ignite. 100% of Physical Damage Converted to Fire Damage | AA18: Burning Arrow Attack, Projectile, Fire, Bow Level: (1-20) Cost: (8-14) Mana Attack Speed: 70% of base Attack Damage: (280-420)% of base Effectiveness of Added Damage: (280-420)% Projectile Speed: 3260 Fires a burning arrow that deals fire damage and has a chance to ignite. 25% chance to Ignite enemies 100% of Physical Damage Converted to Fire Damage | AB18: Bow Projectile Attack | AC18: Damage over Time / Lane Clear | AD18: 지정 방향/라인으로 투사체를 발사하는 Fire 원거리 타워 스킬
A19: SKILL | B19: F4 | C19: Active | D19: Cobra Lash | E19: Attack, Projectile, Chaos | F19: Chaos | G19: Attack | H19: Projectile | I19: Projectile, Chain | J19: Poison | K19: (1-20) | L19: (5-8) Mana | S19: 120% of base | T19: (125-205)% of base | U19: (125-205)% | Y19: 8% more Damage with Hits and Ailments for each remaining Chain | Z19: Fires a poisonous projectile based on your weapon that will chain between enemies. Requires a Dagger or Claw. Chains +(3-5) Times 60% of Physical Damage Converted to Chaos Damage 40% chance to Poison on Hit | AA19: Cobra Lash Attack, Projectile, Chaos Level: (1-20) Cost: (5-8) Mana Attack Speed: 120% of base Attack Damage: (125-205)% of base Effectiveness of Added Damage: (125-205)% Fires a poisonous projectile based on your weapon that will chain between enemies. Requires a Dagger or Claw. 8% more Damage with Hits and Ailments for each remaining Chain Chains +(3-5) Times 60% of Physical Damage Converted to Chaos Damage 40% chance to Poison on Hit | AB19: Chaining Projectile | AC19: Damage over Time / Wave Clear | AD19: 적 사이를 연쇄 타격하는 Chaos 체인 투사체 타워
A20: SKILL | B20: G4 | C20: Active | D20: Cyclone | E20: Attack, AoE, Melee, Movement, Channelling | G20: Attack, Melee | H20: AoE, Melee, Movement, Channelling | I20: Area, Channel | K20: (1-20) | L20: (2-3) Mana | R20: 28 | S20: 300% of base | T20: (81-150)% of base | U20: (81-150)% | V20: 1.6 | Y20: Channel this skill to move towards a targeted location while spinning constantly attacking enemies in an area around you. While channelling this skill, you cannot be knocked back. 15% increased Area of Effect per 0.1 metre additional Melee Strike Range | Z20: (30-20)% less Movement Speed | AA20: Cyclone Attack, AoE, Melee, Movement, Channelling Level: (1-20) Cost: (2-3) Mana Attack Speed: 300% of base Attack Damage: (81-150)% of base Effectiveness of Added Damage: (81-150)% AoE Radius: 1.6 Requires Level 28 Channel this skill to move towards a targeted location while spinning constantly attacking enemies in an area around you. While channelling this skill, you cannot be knocked back. 15% increased Area of Effect per 0.1 metre additional Melee Strike Range (30-20)% less Movement Speed | AB20: Movement / Mobility Skill | AC20: Wave Clear / Mobility | AD20: 영웅 유닛의 위치 이동, 회피, 진입 패턴으로 사용하는 이동형 액티브 스킬
A21: SKILL | B21: H4 | C21: Active | D21: Detonate Dead | E21: Spell, AoE, Fire | F21: Fire | G21: Spell | H21: AoE | I21: Area | K21: (1-20) | L21: (5-20) Mana | Q21: 0.60 sec | R21: 4 | U21: 160% | V21: 22 | Y21: Critical Strike Chance: 6.00% Targets a corpse, and deals spell damage to ene... | Z21: Deals (15-798) to (22-1197) Fire Damage Base radius is (2.2-2.6) metres | AA21: Detonate Dead Spell, AoE, Fire Level: (1-20) Cost: (5-20) Mana Cast Time: 0.6... | AB21: Area Spell | AC21: Wave Clear | AD21: 지정 범위에 즉발 광역 피해를 주는 캐스터형 타워 스킬
A22: SKILL | B22: I4 | C22: Active | D22: Explosive Arrow | E22: Attack, Projectile, AoE, Duration, Fire, Bow | F22: Fire | G22: Attack, Bow | H22: Projectile, AoE, Bow | I22: Projectile, Area, Duration/DoT | K22: (1-20) | L22: (7-10) Mana | R22: 28 | V22: 15 | W22: 3260 | Y22: Explosion deals 50% less Base Damage Explosion deals 6% more Damage with Hits... | Z22: Fires an arrow which will stick into an enemy or wall, and then explode, deal... | AA22: Explosive Arrow Attack, Projectile, AoE, Duration, Fire, Bow Level: (1-20) Co... | AB22: Bow Projectile Attack | AC22: Wave Clear | AD22: 지정 방향/라인으로 투사체를 발사하는 Fire 원거리 타워 스킬
A23: SKILL | B23: J4 | C23: Active | D23: Explosive Concoction | E23: Attack, AoE, Fire, Cold, Lightning, Projectile | F23: Fire, Cold, Lightning | G23: Attack | H23: AoE, Projectile | I23: Projectile, Area | J23: Ignite | K23: (1-20) | L23: (6-9) Mana | R23: 28 | S23: 115% of base | Y23: Throws a bottle that explodes to deal unarmed attack damage in an area. Can c... | Z23: (65-806) to (98-1210) Added Fire Damage +6% to Critical Strike Chance Base ra... | AA23: Explosive Concoction Attack, AoE, Fire, Cold, Lightning, Projectile Level: (1... | AB23: Explosive Projectile | AC23: Wave Clear | AD23: 직선 투사체가 명중 지점에서 폭발해 범위 피해를 주는 Fire, Cold, Lightning 스플래시 타워
A24: SKILL | B24: K4 | C24: Active | D24: Flicker Strike | E24: Attack, Melee, Strike, Movement, Duration | G24: Attack, Melee | H24: Melee, Strike, Movement | I24: Duration/DoT | K24: (1-20) | L24: (5-8) Mana | O24: 2.00 sec | P24: 1 Use(s) | R24: 10 | S24: 120% of base | T24: (177-408)% of base | U24: (177-408)% | Y24: Teleports the character to a nearby monster and attacks with a melee weapon. ... | Z24: Base duration is 3.00 seconds 10% increased Attack Speed per Frenzy Charge 15... | AA24: Flicker Strike Attack, Melee, Strike, Movement, Duration Level: (1-20) Cost: ... | AB24: Movement / Mobility Skill | AC24: Damage over Time / Single Target / Mobility | AD24: 영웅 유닛의 위치 이동, 회피, 진입 패턴으로 사용하는 이동형 액티브 스킬
A25: SKILL | B25: L4 | C25: Active | D25: Frost Blades | E25: Attack, Projectile, Melee, Strike, Cold | F25: Cold | G25: Attack, Melee | H25: Projectile, Melee, Strike | I25: Projectile | K25: (1-20) | L25: (6-10) Mana | T25: (143-409)% of base | U25: (143-409)% | W25: 2250 | Y25: Attack enemies with increased range, releasing icy blades from the first enem... | Z25: Fires (5-8) Projectiles 60% of Physical Damage Converted to Cold Damage +(1.8... | AA25: Frost Blades Attack, Projectile, Melee, Strike, Cold Level: (1-20) Cost: (6-1... | AB25: Melee Projectile Hybrid | AC25: Lane Clear / Single Target | AD25: 지정 방향/라인으로 투사체를 발사하는 Cold 원거리 타워 스킬
A26: SKILL | B26: M4 | C26: Active | D26: Galvanic Arrow | E26: Lightning, Attack, Projectile, AoE, Bow | F26: Lightning | G26: Attack, Bow | H26: Projectile, AoE, Bow | I26: Projectile, Area | K26: (1-20) | L26: (6-10) Mana | T26: (92-113)% of base | U26: (92-113)% | Y26: Fire a trio of electrical arrows that quickly dissipate, vanishing shortly af... | Z26: 50% of Physical Damage Converted to Lightning Damage Fires 3 Arrows +(0-0.5) ... | AA26: Galvanic Arrow Lightning, Attack, Projectile, AoE, Bow Level: (1-20) Cost: (6... | AB26: Bow Projectile Attack | AC26: Wave Clear | AD26: 지정 방향/라인으로 투사체를 발사하는 Lightning 원거리 타워 스킬
